Workbook

Sheet Master Listings
A1: Investment Name | B1: Sponsor | C1: Structure | D1: Status | E1: Total Offering | F1: Equity | G1: Debt | H1: In-Place LTV | I1: Available Equity | J1: Last Updated | K1: Available Percentage | L1: Property Type | M1: Location | N1: Location (Use) | O1: Total Load | P1: Strategy | Q1: 721 Exchange Exit | R1: Estimated Hold Period | S1: Description | T1: Highlight 1 | U1: Highlight 2 | V1: Highlight 3 | W1: Highlight 4 | X1: Highlight 5 | Y1: Pros | Z1: Cons | AA1: Insights | AB1: Y1 | AC1: Y2 | AD1: Y3 | AE1: Y4 | AF1: Y5 | AG1: Y6 | AH1: Y7 | AI1: Y8 | AJ1: Y9 | AK1: Y10 | AL1: Average Yield | AM1: Tax-Adj. Yield | AN1: Cap Rate Equivalent | AO1: Lender | AP1: Interest Rate | AQ1: Loan Term | AR1: I/O Period | AS1: Amortization | AT1: Y1 DSCR | AU1: Property Address | AV1: Property Photo Link | AW1: DD Folder Link | AX1: Minimum Investment | AY1: Photo Link Use | AZ1: Tax Adjusted Yield (Use) | BA1: Tax Adj Label | BB1: DD Label | BC1: URL | BD1: Sponsor URL | BE1: Prop Type URL | BF1: Sponsor Button Text | BG1: Property Type Button Text | BH1: Sponsor Founded | BI1: Sponsor Description | BJ1: Sponsor AUM | BK1: Full-Cycle Count | BL1: Sponsor AAR | BM1: Sponsor AEM | BN1: Sponsor Hold | BO1: Sponsor Success | BP1: Sponsor Image | BQ1: BM: Avg. Income - Deal | BR1: BM: Avg. Income - MKT | BS1: BM: Avg. Income - Interpret | BT1: BM: Growth - Deal | BU1: BM: Growth- MKT | BV1: BM: Growth - Interpret | BW1: BM: Peak - Deal | BX1: BM: Peak- MKT | BY1: BM: Peak - Interpret | BZ1: List Description | CA1: Investment Description Copy/Paste
A2: AEI Healthcare Portfolio VII DST | B2: AEI Capital Corporation | C2: Delaware Statutory Trust (DST) | D2: Available | E2: 50500000 | F2: 50500000 | G2: 0 | H2: 0.00% LTV | I2: 25680857 | J2: 46169 | K2: =(I2/F2) -> 0.50853182 | L2: Healthcare | M2: AZ, TX, CT | N2: =IFERROR(__xludf.DUMMYFUNCTION("TEXTJOIN("", "", TRUE, SORT(TRANSPOSE(SPLIT(M2, "", ""))))"),"AZ, CT, TX") -> AZ, CT, TX | O2: 9.12% | P2: Core | Q2: Optional | R2: 10 years | S2: Three purpose-built, single-tenant outpatient medical office assets held debt-free in a DST: HonorHealth Complete Care (12,000 SF, Surprise AZ, Phoenix MSA, lease to 2042), Texas Children's Pavilion for Women (12,642 SF, Cedar Park/Austin TX, co-located one block from the tenant's own hospital campus, lease to 2038), and a United Healthcare/ProHealth Physicians clinic (26,547 SF on 6.40 ac, Bristol CT, lease to 2037). Submarkets are infill/Sun Belt growth corridors with strong daytime traffic and household incomes ($78k-$125k) and constrained MOB supply (~6.9% national availability). Thesis is durable, escalating net-lease income from investment-grade-equivalent healthcare credit, underpinned by secular outpatient-care migration and aging demographics. Operating strategy is passive triple-net ownership through an affiliated master tenant, with insurance fully tenant-reimbursed and de minimis trust-level expense; income growth is driven entirely by contractual 2.0%-2.5% escalators. | T2: The portfolio exhibits a credit barbell. Texas Children's Hospital (AA-/Fitch) and the UnitedHealth Group parent (AA-/Fitch, A/AM Best) supply investment-grade-equivalent corporate backing, while HonorHealth (A+/Fitch) is a single-state Arizona nonprofit system. Income is disproportionately weighted to Bristol, whose ~$1.15M gross rent is roughly 44% of in-place rent, concentrating cash flow in a single asset and a single tenant whose parent's Fitch outlook was revised to negative in July 2025 - a trajectory the static AA- marketing presentation omits. | U2: Weighted average remaining lease term is 13.62 years across staggered expirations (Surprise 2042, Austin 2038, Bristol 2037). Duration is asymmetric: the long-dated HonorHealth lease carries the lowest escalator (2.0%), while the largest asset (Bristol) escalates 2.5% only through year 9 and then steps flat, capping income growth on the portfolio's biggest rent stream precisely as the projected disposition window approaches. | V2: Real estate quality is high and recently delivered (2022-2024 vintage), purpose-built for outpatient use. The Austin asset's co-location one block from Texas Children's own hospital campus creates a mission-critical referral linkage that raises renewal probability and tenant switching costs; the Surprise asset is the sole urgent care within a 3.5-mile radius in a high-traffic retail corridor (71,024 VPD). These siting characteristics function as soft barriers to entry that support re-leasing economics. | W2: The debt-free capital structure removes refinancing, maturity, rate-cap, and foreclosure risk entirely, and eliminates the equal-or-greater-debt replacement requirement for 1031 investors averse to boot-offsetting leverage. The structural cost is the absence of positive financial leverage, which mechanically caps levered IRR and is the primary reason the 5.00% going-in distribution sits below comparable leveraged net-lease DSTs. | X2: The triple-net structure with tenant-reimbursed insurance and ~$1,400/year trust-level property expense insulates distributable cash from operating inflation. The qualifier is capital responsibility: the Trust retains certain capex obligations funded only from a modest reserve that declines from $371,000 to ~$67,764 by 2035, drawn down immediately by a $221,000 Connecticut transfer-tax charge in year 1, leaving limited capacity for unbudgeted tenant improvements and condition-assessment items. | Y2: The offering pairs institutional-grade healthcare net-lease credit with a defensive, unlevered balance sheet. Tenants are investment-grade-equivalent corporate operators on long-dated NNN leases (13.62-yr WALT) with contractual 2.0%-2.5% escalators, in demographically supported submarkets benefiting from outpatient-care migration, an aging cohort, and tight MOB supply. The debt-free structure removes refinance, maturity, cap-cost, and foreclosure exposure and offers a clean basis for 1031 capital seeking certainty of monthly income. The sponsor carries a ~40-year, 153-program operating history, including 57 full-cycle 1031 offerings averaging 6.37% annual cash-on-cash, and the distribution schedule escalates from 5.00% to 6.14% over the projected hold. | Z2: Income is concentrated in three single-tenant assets, with Bristol/United Healthcare alone at ~44% of rent, rendering any single vacancy binary to portfolio cash flow. The master tenant is thinly capitalized - funded by a $500,000 demand promissory note (not cash) from an affiliate, with projected Y1 net income of only ~$2,013 - so a subtenant payment interruption would rapidly exhaust the master tenant's cushion and the trust's limited reserves. The Bristol escalator caps at year 9 and steps flat, flattening growth on the largest asset into the disposition window, where that lease (2037 expiry) leaves only ~1.5 years of residual term at a 2035 exit - a material re-leasing/rollover overhang on the highest-rent asset at the point of valuation. The UNH parent's Fitch outlook turned negative in July 2025, and the Bristol lessee is an operating subsidiary rather than the rated parent. Reserve adequacy is thin post the $221,000 CT transfer-tax draw, and a one-month UNH rent abatement (August 2026) dampens Y1 collections. | AA2: This is a low-beta, income-oriented core net-lease vehicle whose return is almost entirely a function of contractual escalators and terminal value, given the absence of leverage and any value-add component. The 5.00% to 6.14% distribution ramp is mechanically supported by the lease schedule, but the early-year spread between subtenant rent collected and master-lease rent paid is razor-thin, concentrating execution risk in the thinly capitalized master tenant. The debt-free design is genuinely defensive in a higher-for-longer regime, sidestepping the leveraged-net-lease maturity wall and cap-cost repricing, but the same feature suppresses yield - the 5.00% going-in sits below AEI's own operating-program current yield (5.48%) and full-cycle average (6.37%), implying reliance on escalators and exit pricing compression to reach target total return. The dominant underwriting sensitivity is terminal value: with no amortization and a fixed escalator schedule, investor IRR is governed by the year-10 disposition pricing against a portfolio whose largest asset will carry only short residual lease term at exit, while Austin (2038) and Surprise (2042) provide longer-dated support to residual value. Feasibility of the projected distributions is reasonable on a contractual basis; the credible variance is in capital-event timing and exit pricing rather than in-place income. | AB2: 0.05 | AC2: 0.0504 | AD2: 0.0507 | AE2: 0.0535 | AF2: 0.0547 | AG2: 0.0563 | AH2: 0.0576 | AI2: 0.059 | AJ2: 0.0603 | AK2: 0.0614 | AL2: 0.0554 | AM2: Not disclosed | AN2: =IFERROR((AB2 * ((1 - VALUE(SUBSTITUTE(H2, " LTV", ""))) + 0.02)) + (PMT(0.0535/12, 25*12, -VALUE(SUBSTITUTE(H2, " LTV", ""))) * 12) + (0.02/10) + (0.03/10) + 0.02, "N/A") -> 0.076 | AO2: None (debt-free) | AP2: N/A (no debt) | AQ2: N/A (no debt) | AR2: N/A (no debt) | AS2: N/A (no debt) | AT2: N/A - no debt service | AV2: https://drive.google.com/file/d/1UpckdXDq8HJjnUzTg9n_WOvsJA0k1qGf/view?usp=sharing | AX2: 100000 | AY2: =IFERROR(__xludf.DUMMYFUNCTION("IF(ISBLANK(AV2), """", IF(REGEXMATCH(AV2, ""/file/d/""), ""https://lh3.googleusercontent.com/d/"" & REGEXEXTRACT(AV2, ""/d/([a-zA-Z0-9_-]+)""), AV2))"),"https://lh3.googleusercontent.com/d/1UpckdXDq8HJjnUzTg9n_WOvsJA0k1qGf") -> https://lh3.googleusercontent.com/d/1UpckdXDq8HJjnUzTg9n_WOvsJA0k1qGf | AZ2: =IF(AM2="Not Disclosed", AB2 + ((14545 / 100000) * (0.32 / (1 - 0.32))), AM2) -> 0.11844706 | BA2: =if(AM2="Not Disclosed", "Est. Tax-Adjusted Yield⁹", "Tax-Adjusted Yield") -> Est. Tax-Adjusted Yield⁹ | BB2: =if(AW2="", "Offering Documents Available By Request", "Download Offering Documents") -> Offering Documents Available By Request | BC2: aei-healthcare-portfolio-vii-dst | BD2: sponsors/aei-capital-corporation | BE2: property-type/healthcare | BF2: ="Learn More About "&B2 -> Learn More About AEI Capital Corporation | BG2: ="Learn More About "&L2&" Properties" -> Learn More About Healthcare Properties | BH2: {=IFERROR(XLOOKUP($B2, 'Sponsor Connection'!$A:$A, 'Sponsor Connection'!$B:$B), )} -> 1970 | BI2: {=IFERROR(XLOOKUP($B2, 'Sponsor Connection'!$A:$A, 'Sponsor Connection'!$D:$D), )} -> AEI is among the longest-tenured names in the net-lease 1031 space, tracing its lineage to 1970 and to what it describes as one of the earliest securitized fractional-ownership structures. The firm's franchise is built on debt-free, all-cash ownership of single-tenant retail, restaurant and healthcare properties leased to credit-quality operators—a conservative posture that strips refinancing and foreclosure risk out of the capital stack and has carried it through multiple real estate cycles. With decades of completed full-cycle programs behind it, AEI markets stability and longevity over scale or sector breadth, a profile that resonates with risk-averse exchangers prioritizing capital preservation over yield. | BJ2: {=IF($B2="", "", LET(aum, IFERROR(XLOOKUP($B2, 'Sponsor Connection'!$A:$A, 'Sponsor Connection'!$C:$C), ""), IF(OR(aum="", aum=0), "Not Reported", aum)))} -> 1610000000 | BK2: {=IF(ISBLANK($B2), "", LET(val, IFERROR(XLOOKUP($B2, 'Sponsor Connection'!$A:$A, 'Sponsor Connection'!$M:$M), ""), IF(OR(ISBLANK(val), val="", val=0), "Not Reported", val)))} -> 48 | BL2: {=IF(ISBLANK($B2), "", LET(val, IFERROR(XLOOKUP($B2, 'Sponsor Connection'!$A:$A, 'Sponsor Connection'!$N:$N), ""), IF(val="", "Not Reported", val)))} -> 0.067466667 | BM2: {=IF(ISBLANK($B2), "", LET(val, IFERROR(XLOOKUP($B2, 'Sponsor Connection'!$A:$A, 'Sponsor Connection'!$O:$O), ""), IF(val="", "Not Reported", val)))} -> 1.548125 | BN2: {=IF(ISBLANK($B2), "", LET(val, IFERROR(XLOOKUP($B2, 'Sponsor Connection'!$A:$A, 'Sponsor Connection'!$P:$P), ""), IF(val="", "Not Reported", val)))} -> 13.315417 | BO2: {=IF(ISBLANK($B2), "", LET(val, IFERROR(XLOOKUP($B2, 'Sponsor Connection'!$A:$A, 'Sponsor Connection'!$Q:$Q), ""), IF(val="", "Not Reported", val)))} -> 1 | BP2: https://img.logo.dev/aeifunds.com?token=pk_FIVsDKgZTvCedVXXtt2rEg&size=200&retina=true | BQ2: =AL2 -> 0.0554 | BR2: =IFERROR(VLOOKUP(L2, Benchmarks!$A$2:$D$15, 2, FALSE), "Not Analyzed") -> 0.0641 | BS2: =IFERROR(IF(OR(ISBLANK(BQ2), ISBLANK(BR2)), "", IF(ABS(BQ2-BR2)/BQ2 <= 0.1, "Meets Average", IF(BQ2 > BR2, "Above Average", "Below Average"))), "Not Analyzed") -> Below Average | BT2: =iferror((BW2-AB2)/AB2, 0) -> 0.228 | BU2: =IFERROR(VLOOKUP(L2, Benchmarks!$A$2:$D$15, 4, FALSE), "Not Analyzed") -> 0.15430055 | BV2: =IFERROR(IF(OR(ISBLANK(BT2), ISBLANK(BU2)), "", IF(ABS(BT2-BU2)/BT2 <= 0.1, "Meets Average", IF(BT2 > BU2, "Above Average", "Below Average"))), "Not Analyzed") -> Above Average | BW2: =max(AB2:AK2) -> 0.0614 | BX2: =IFERROR(VLOOKUP(L2, Benchmarks!$A$2:$D$15, 3, FALSE), "Not Analyzed") -> 0.07025 | BY2: =IFERROR(IF(OR(ISBLANK(BW2), ISBLANK(BX2)), "", IF(ABS(BW2-BX2)/BW2 <= 0.1, "Meets Average", IF(BW2 > BX2, "Above Average", "Below Average"))), "Not Analyzed") -> Below Average | BZ2: ="Investment: " & A2 & " | Sponsor: " & B2 & " | Structure: " & C2 & " | Status: " & D2 & " | LTV: " & H2 & " | Availability: " & K2 & " | Location: " & N2 & " | Strategy: " & P2 & " | 721 Exchange Exit: " & Q2 & " | Estimated Hold: " & R2 & " | Cap Rate Equivalent: " & AN2 & " | Minimum Investment: " & AX2 -> Investment: AEI Healthcare Portfolio VII DST | Sponsor: AEI Capital Corporation | Structure: Delaware Statutory Trust (DST) | Status: Available | LTV: 0.00% LTV | Availability: 0.508531821782178 | Location: AZ, CT, TX | Strategy: Core | 721 Exchange Exit: Optional | Estimated Hold: 10 years | Cap Rate Equivalent: 0.076 | Minimum Investment: 100000 | CA2: =A2&" ("&H2&")"&CHAR(10)&CHAR(10)&"AEI Healthcare Portfolio VII is a debt-free Delaware Statutory Trust holding three purpose-built, single-tenant outpatient medical office assets across Arizona, Texas, and Connecticut, net-leased to healthcare operators on terms running to 2037-2042. Cont"&"ractual 2.0%-2.5% annual escalators and tenant-reimbursed insurance produce escalating net-lease income with minimal trust-level expense. The all-cash structure carries no refinancing or interest-rate exposure, positioning the offering as a core, income-o"&"riented vehicle underpinned by secular outpatient-care migration and aging demographics."&CHAR(10)&CHAR(10)&">> Download Offering Documents"&CHAR(10)&"https://www.baker1031.com/sponsors/aei-capital-corporation" -> AEI Healthcare Portfolio VII DST (0.00% LTV) AEI Healthcare Portfolio VII is a debt-free Delaware Statutory Trust holding three purpose-built, single-tenant outpatient medical office assets across Arizona, Texas, and Connecticut, net-leased to healthcare operators on terms running to 2037-2042. Contractual 2.0%-2.5% annual escalators and tenant-reimbursed insurance produce escalating net-lease income with minimal trust-level expense. The all-cash structure carries no refinancing or interest-rate exposure, positioning the offering as a core, income-oriented vehicle underpinned by secular outpatient-care migration and aging demographics. >> Download Offering Documents https://www.baker1031.com/sponsors/aei-capital-corporation
A3: Blue Door Property II, DST | B3: SmartStop | C3: Delaware Statutory Trust (DST) | D3: Available | E3: 64766336 | F3: 64766336 | G3: 0 | H3: 0.00% LTV | I3: 41797727 | J3: 46113 | K3: =(I3/F3) -> 0.64536192 | L3: Self-Storage | M3: FL, TX | N3: =IFERROR(__xludf.DUMMYFUNCTION("TEXTJOIN("", "", TRUE, SORT(TRANSPOSE(SPLIT(M3, "", ""))))"),"FL, TX") -> FL, TX | O3: 13.02% | P3: Core-Plus | Q3: Optional | R3: 10 years | S3: Three stabilized self-storage facilities (~301,000 rentable SF; 2,281 storage units and 98 vehicle/RV spaces) held debt-free in a parent/operating DST structure and operated under the SmartStop Self Storage brand: 6707 Narcoossee Road, Orlando FL (97,300 SF, 677 units, 2003 vintage, in the high-growth Lake Nona/Narcoossee corridor), 3701 FM Road 2181, Corinth TX (97,050 SF, 766 units, 2000-2005 vintage, Denton County/DFW), and 7905 Spencer Highway, Pasadena TX (106,618 SF, 838 units plus 81 vehicle spaces, 2003-2007 vintage, Houston/Bay Area). Portfolio occupancy is ~91.2%. The properties are leased to an affiliated master tenant under a 10-year master lease with a base/additional/bonus-rent waterfall, and managed by a SmartStop-affiliated property manager. Thesis is inflation-responsive operating income from necessity-based self-storage in Sun Belt growth markets, with month-to-month rental structure enabling active revenue management and an optional Section 721 rollover into the sponsor's affiliated operating partnership. | T3: The portfolio is operated under the SmartStop Self Storage platform (ultimate parent SmartStop Self Storage REIT, NYSE: SMA), a scaled institutional self-storage owner-operator with established revenue-management systems. Operating control, master-tenant, and property-management functions all sit with SmartStop affiliates, aligning the assets with a national operator's pricing and marketing infrastructure; the same arrangement concentrates execution dependence on a single, vertically affiliated operator rather than diversified third parties. | U3: The Orlando asset anchors the portfolio in the Lake Nona/Narcoossee corridor, among the fastest-growing submarkets in the Sun Belt, with heavy 2023-2024 residential delivery (multiple 250-350 unit multifamily projects and a 156-room hotel) generating new household formation that drives storage demand. The same pipeline, however, includes a 100,000 SF self-storage facility delivered in 2024, an explicit competitive-supply signal in a sector where demand is hyper-local to a roughly three-mile trade area. | V3: Self-storage's month-to-month rental structure permits near-continuous repricing through revenue management, providing inflation pass-through that fixed long-term net leases cannot replicate; the master-lease waterfall channels this upside to investors via Additional Rent and Bonus Rent (80% of gross income above stated breakpoints), so forecast distributions escalate from 4.41% to 5.06% on operating performance rather than contractual escalators. The offset is structurally higher tenant churn and occupancy volatility than credit-tenant net lease. | W3: The portfolio was acquired free and clear with cash, eliminating mortgage, refinancing, maturity, rate-cap, and foreclosure risk, and removing the equal-or-greater-debt replacement requirement for 1031 investors averse to boot-offsetting leverage. The trust agreement nonetheless preserves the ability to incur future financing, so the debt-free position is a current state rather than a permanent covenant. | X3: For cash (non-1031) investors the structure delivers substantial depreciation shelter, with roughly 74-77% of forecast cash flow sheltered and a tax-equivalent yield averaging approximately 6.16% against a 40% assumed effective tax rate. Combined with the bonus-rent participation, this positions the offering as an income vehicle with embedded tax efficiency and modest operating upside rather than a fixed-coupon instrument. | Y3: The offering provides debt-free ownership of a diversified, stabilized self-storage portfolio (three facilities across two high-growth Sun Belt states) operated by a scaled public-REIT platform with institutional revenue-management capability. The month-to-month lease structure permits inflation pass-through, and the master-lease bonus-rent waterfall gives investors direct participation in NOI upside, supporting a distribution ramp from 4.41% to 5.06% over the forecast. Depreciation shelter is meaningful for cash investors (~6.16% average tax-equivalent yield), the capital structure carries no refinancing or maturity exposure, and an optional Section 721 contribution offers a potential tax-deferred exit path into the sponsor's affiliated operating partnership. | Z3: The going-in distribution is low at 4.41%, below comparable net-lease DSTs, and reaching 5.06% by year 10 depends on revenue-management execution and bonus-rent realization rather than contractual escalators. Self-storage is supply-sensitive and demand is hyper-local; the Lake Nona submarket already absorbed a new 100,000 SF facility in 2024, a direct competitive threat to the Orlando asset. Operating dependence is concentrated in newly formed SmartStop affiliates (the property manager was formed July 2024) acting as master tenant, manager, and asset manager, with a thinly capitalized affiliated master tenant and no third-party operating diversification. The 721 exit would deliver OP units in SSGT III's operating partnership, a private, non-traded REIT, not the NYSE-listed SmartStop, so the rollover liquidity is into an illiquid private vehicle dependent on SSGT III's own future liquidity events. The assets are older vintage (2000-2007) than new-construction net-lease product, with a single $1,854,800 reserve covering three aging facilities, and total load is high at 13.02% with a 2.52% acquisition fee and a 2.0% disposition fee further compressing net proceeds. | AA3: This is a debt-free, core-plus self-storage vehicle whose return mechanics differ structurally from net-lease DSTs: distributions track operating NOI through a base/additional/bonus-rent waterfall rather than fixed credit-tenant escalators, so the 4.41% to 5.06% ramp is a function of SmartStop's revenue-management execution and submarket fundamentals, not a contractual obligation. The unlevered structure is defensive against the rate environment but caps return, leaving the investment case resting on self-storage's inflation pass-through, the depreciation shelter (~75% of cash flow; ~6.16% average tax-equivalent yield for cash investors), and the optional 721 rollover. Underwriting feasibility hinges on sustaining and growing ~91% occupancy and street rates across three Sun Belt facilities against visible new supply in Lake Nona. The dominant risk-adjusted question is whether revenue-management upside and bonus rent justify a sub-5% going-in yield and a ~13% load over a 10-year horizon, with terminal value and the form and liquidity of any 721 consideration, private SSGT III OP units, as the principal exit sensitivities. | AB3: 0.0441 | AC3: 0.0451 | AD3: 0.0455 | AE3: 0.0461 | AF3: 0.0464 | AG3: 0.047 | AH3: 0.0481 | AI3: 0.0486 | AJ3: 0.0496 | AK3: 0.0506 | AL3: 0.0471 | AM3: 0.0616 | AN3: =IFERROR((AB3 * ((1 - VALUE(SUBSTITUTE(H3, " LTV", ""))) + 0.02)) + (PMT(0.0535/12, 25*12, -VALUE(SUBSTITUTE(H3, " LTV", ""))) * 12) + (0.02/10) + (0.03/10) + 0.02, "N/A") -> 0.069982 | AO3: None (debt-free) | AP3: N/A (no debt) | AQ3: N/A (no debt) | AR3: N/A (no debt) | AS3: N/A (no debt) | AT3: N/A - no debt service | AU3: 7905 Spencer Highway, Pasadena, TX | AV3: https://drive.google.com/file/d/1-val7swkH1VPNam90f34CrzczJjcQaHO/view?usp=sharing | AX3: 100000 | AY3: =IFERROR(__xludf.DUMMYFUNCTION("IF(ISBLANK(AV3), """", IF(REGEXMATCH(AV3, ""/file/d/""), ""https://lh3.googleusercontent.com/d/"" & REGEXEXTRACT(AV3, ""/d/([a-zA-Z0-9_-]+)""), AV3))"),"https://lh3.googleusercontent.com/d/1-val7swkH1VPNam90f34CrzczJjcQaHO") -> https://lh3.googleusercontent.com/d/1-val7swkH1VPNam90f34CrzczJjcQaHO | AZ3: =IF(AM3="Not Disclosed", AB3 + ((14545 / 100000) * (0.32 / (1 - 0.32))), AM3) -> 0.0616 | BA3: =if(AM3="Not Disclosed", "Est. Tax-Adjusted Yield⁹", "Tax-Adjusted Yield") -> Tax-Adjusted Yield | BB3: =if(AW3="", "Offering Documents Available By Request", "Download Offering Documents") -> Offering Documents Available By Request | BC3: blue-door-property-ii-dst | BD3: sponsors/smartstop | BE3: property-type/self-storage | BF3: ="Learn More About "&B3 -> Learn More About SmartStop | BG3: ="Learn More About "&L3&" Properties" -> Learn More About Self-Storage Properties | BH3: {=IFERROR(XLOOKUP($B3, 'Sponsor Connection'!$A:$A, 'Sponsor Connection'!$B:$B), )} -> 2013 | BI3: {=IFERROR(XLOOKUP($B3, 'Sponsor Connection'!$A:$A, 'Sponsor Connection'!$D:$D), )} -> SmartStop is a self-storage REIT (NYSE: SMA) that completed an $810 million IPO in April 2025 and sponsors self-storage DSTs through its broader platform, with assets in the $7 billion-plus range post-listing. Its pure-play self-storage focus, internal management and combined U.S.-and-Canada footprint give it a clean, single-sector thesis, and the recent public listing adds a transparency and liquidity dimension uncommon among DST sponsors. For exchangers, it offers concentrated exposure to a resilient, low-operating-intensity asset class. | BJ3: {=IF($B3="", "", LET(aum, IFERROR(XLOOKUP($B3, 'Sponsor Connection'!$A:$A, 'Sponsor Connection'!$C:$C), ""), IF(OR(aum="", aum=0), "Not Reported", aum)))} -> 7000000000 | BK3: {=IF(ISBLANK($B3), "", LET(val, IFERROR(XLOOKUP($B3, 'Sponsor Connection'!$A:$A, 'Sponsor Connection'!$M:$M), ""), IF(OR(ISBLANK(val), val="", val=0), "Not Reported", val)))} -> Not Reported | BL3: {=IF(ISBLANK($B3), "", LET(val, IFERROR(XLOOKUP($B3, 'Sponsor Connection'!$A:$A, 'Sponsor Connection'!$N:$N), ""), IF(val="", "Not Reported", val)))} -> No Data | BM3: {=IF(ISBLANK($B3), "", LET(val, IFERROR(XLOOKUP($B3, 'Sponsor Connection'!$A:$A, 'Sponsor Connection'!$O:$O), ""), IF(val="", "Not Reported", val)))} -> No Data | BN3: {=IF(ISBLANK($B3), "", LET(val, IFERROR(XLOOKUP($B3, 'Sponsor Connection'!$A:$A, 'Sponsor Connection'!$P:$P), ""), IF(val="", "Not Reported", val)))} -> No Data | BO3: {=IF(ISBLANK($B3), "", LET(val, IFERROR(XLOOKUP($B3, 'Sponsor Connection'!$A:$A, 'Sponsor Connection'!$Q:$Q), ""), IF(val="", "Not Reported", val)))} -> No Data | BP3: {=IFERROR(XLOOKUP($B3, 'Sponsor Connection'!$A:$A, 'Sponsor Connection'!$L:$L), )} -> https://img.logo.dev/smartstop.com?token=pk_FIVsDKgZTvCedVXXtt2rEg&size=200&retina=true | BQ3: =AL3 -> 0.0471 | BR3: =IFERROR(VLOOKUP(L3, Benchmarks!$A$2:$D$15, 2, FALSE), "Not Analyzed") -> 0.04495 | BS3: =IFERROR(IF(OR(ISBLANK(BQ3), ISBLANK(BR3)), "", IF(ABS(BQ3-BR3)/BQ3 <= 0.1, "Meets Average", IF(BQ3 > BR3, "Above Average", "Below Average"))), "Not Analyzed") -> Meets Average | BT3: =iferror((BW3-AB3)/AB3, 0) -> 0.14739229 | BU3: =IFERROR(VLOOKUP(L3, Benchmarks!$A$2:$D$15, 4, FALSE), "Not Analyzed") -> 0.13869615 | BV3: =IFERROR(IF(OR(ISBLANK(BT3), ISBLANK(BU3)), "", IF(ABS(BT3-BU3)/BT3 <= 0.1, "Meets Average", IF(BT3 > BU3, "Above Average", "Below Average"))), "Not Analyzed") -> Meets Average | BW3: =max(AB3:AK3) -> 0.0506 | BX3: =IFERROR(VLOOKUP(L3, Benchmarks!$A$2:$D$15, 3, FALSE), "Not Analyzed") -> 0.0479 | BY3: =IFERROR(IF(OR(ISBLANK(BW3), ISBLANK(BX3)), "", IF(ABS(BW3-BX3)/BW3 <= 0.1, "Meets Average", IF(BW3 > BX3, "Above Average", "Below Average"))), "Not Analyzed") -> Meets Average | BZ3: ="Investment: " & A3 & " | Sponsor: " & B3 & " | Structure: " & C3 & " | Status: " & D3 & " | LTV: " & H3 & " | Availability: " & K3 & " | Location: " & N3 & " | Strategy: " & P3 & " | 721 Exchange Exit: " & Q3 & " | Estimated Hold: " & R3 & " | Cap Rate Equivalent: " & AN3 & " | Minimum Investment: " & AX3 -> Investment: Blue Door Property II, DST | Sponsor: SmartStop | Structure: Delaware Statutory Trust (DST) | Status: Available | LTV: 0.00% LTV | Availability: 0.645361920736106 | Location: FL, TX | Strategy: Core-Plus | 721 Exchange Exit: Optional | Estimated Hold: 10 years | Cap Rate Equivalent: 0.069982 | Minimum Investment: 100000 | CA3: =A3&" ("&H3&")"&CHAR(10)&CHAR(10)&"Blue Door Property II is a debt-free DST holding three stabilized SmartStop-branded self-storage facilities (~301,000 SF; 2,281 units) in the Orlando, DFW, and Houston Sun Belt growth corridors at ~91.2% occupancy. The assets are operated under a 10-year "&"affiliated master lease with a base/additional/bonus-rent waterfall and active, month-to-month revenue management. The thesis targets inflation-responsive operating income from necessity-based storage, with an optional Section 721 rollover into the sponso"&"r's affiliated operating partnership."&CHAR(10)&CHAR(10)&">> Download Offering Documents"&CHAR(10)&"https://www.baker1031.com/sponsors/smartstop" -> Blue Door Property II, DST (0.00% LTV) Blue Door Property II is a debt-free DST holding three stabilized SmartStop-branded self-storage facilities (~301,000 SF; 2,281 units) in the Orlando, DFW, and Houston Sun Belt growth corridors at ~91.2% occupancy. The assets are operated under a 10-year affiliated master lease with a base/additional/bonus-rent waterfall and active, month-to-month revenue management. The thesis targets inflation-responsive operating income from necessity-based storage, with an optional Section 721 rollover into the sponsor's affiliated operating partnership. >> Download Offering Documents https://www.baker1031.com/sponsors/smartstop
A4: Blue Door Property III, DST | B4: SmartStop | C4: Delaware Statutory Trust (DST) | D4: Available | E4: 52636335 | F4: 28444976 | G4: 24191359 | H4: 45.96% LTV | I4: 28444976 | J4: 45974 | K4: =(I4/F4) -> 1 | L4: Self-Storage | M4: AZ, FL, TX | N4: =IFERROR(__xludf.DUMMYFUNCTION("TEXTJOIN("", "", TRUE, SORT(TRANSPOSE(SPLIT(M4, "", ""))))"),"AZ, FL, TX") -> AZ, FL, TX | O4: 15.19% | P4: Core-Plus | Q4: Optional | R4: 7 years | S4: Three self-storage facilities (~1,927 storage units, 24 modular outdoor units, 12 vehicle spaces) held in a parent/operating DST structure, financed at 45.96% LTV and operated under the SmartStop Self Storage brand: 4860 North 83rd Avenue, Phoenix AZ (711 units, ~82,435 SF), 460 Florida Central Parkway, Longwood FL (542 units, 12 vehicle spaces), and 8110 S. Cockrell Hill Road, Dallas TX (674 units plus 24 modular outdoor units). Portfolio occupancy is ~90% (~92% at Phoenix). Each property carries a separate fixed-rate interest-only mortgage from a SmartStop-affiliated lender (aggregate $24,191,359), and each is leased to a state-specific affiliated master tenant under its own master lease with a base/additional/bonus-rent waterfall, managed by a SmartStop-affiliated property manager. Thesis is leveraged, inflation-responsive operating income from necessity-based self-storage across three Sun Belt metros, with active revenue management and an optional Section 721 rollover into the sponsor's affiliated operating partnership ahead of the November 2032 loan maturity. | T4: This is a leveraged structure (45.96% LTV) financed with three separate fixed-rate mortgages at 5.00%, interest-only for the full seven-year term from SMST Lender, LLC, a SmartStop affiliate, maturing November 13, 2032. Interest-only with no amortization maximizes current distributions but builds no principal equity, so the entire $24.19M balloons at maturity; the seven-year hold is explicitly structured to dispose of the assets before that date, and the affiliated-lender, related-party terms warrant independent scrutiny. | U4: The portfolio is operated under the SmartStop Self Storage platform (ultimate parent SmartStop Self Storage REIT, NYSE: SMA), with state-specific affiliated master tenants and a SmartStop-affiliated property manager. This aligns the assets with a scaled operator's revenue-management and marketing infrastructure, while concentrating master-tenant, management, lending, and 721-counterparty roles within a single sponsor family rather than diversified third parties. | V4: Geographic diversification spans three independent Sun Belt storage trade areas, Phoenix, the Orlando/Longwood corridor, and Dallas, at roughly 90% occupancy (about 92% at Phoenix). Spreading income across three metros with distinct supply-demand dynamics reduces the single-market concentration risk inherent to a one-submarket storage deal, though self-storage demand remains hyper-local within each. | W4: At a 5.00% fixed borrowing cost against the portfolio's going-in NOI yield, the moderate leverage modestly amplifies investor cash-on-cash relative to an all-equity structure, and the interest-only feature removes amortization drag to support current distributions. The trade-off is that no equity is built through paydown, leaving exit value entirely dependent on NOI growth and the terminal value against a fixed principal balloon. | X4: The combination of leverage (interest deductibility) and depreciation produces high tax shelter, roughly 89-92% of cash flow sheltered in the early years, yielding an average tax-equivalent yield near 7.08% for non-1031 cash investors at a 40% assumed effective rate. The after-tax profile is materially stronger than the ~4.28% pre-tax cash-on-cash, positioning the offering as a tax-efficient leveraged income vehicle. | Y4: The offering provides a geographically diversified self-storage portfolio across three Sun Belt metros operated by the SmartStop public-REIT platform, with institutional revenue-management capability and month-to-month leases that permit inflation pass-through and bonus-rent upside. Financing is fixed-rate (5.00%) and interest-only, locking coupon cost and maximizing current distributions, and Year 1 debt-service coverage is healthy at 1.81x. Depreciation and interest shelter are substantial (~7.08% average tax-equivalent yield for cash investors), and an optional Section 721 contribution offers a potential tax-deferred exit into the sponsor's affiliated operating partnership. | Z4: The financing is interest-only with a hard seven-year balloon (November 2032) and no amortization, so the full $24.19M principal must be refinanced or repaid at exit; any delay forces extension at floating SOFR plus 1.50%, surrendering the 5.00% fixed coupon precisely at the maturity wall. Financing, master tenants, property management, and the 721 counterparty are all SmartStop affiliates, creating pervasive conflicts with no arm's-length check on loan or lease terms, and each master tenant is capitalized only by a small demand note from the affiliated operating partnership ($441,000 Phoenix, $322,000 Dallas, among them), reducible by retained earnings. Going-in cash yield is low at 4.00%, reaching only 4.52% by year 7 and dependent on revenue-management execution and bonus rent, against a high 15.19% load plus a 2.0% disposition fee. The 721 consideration would be units in SS Growth Operating Partnership III, a private, non-traded REIT, not the listed SmartStop, and the appraised value ($45.3M) sits only marginally above purchase price ($44.24M), leaving thin day-one equity cushion against 45.96% leverage (debt-to-appraised-value roughly 53%) in a supply-sensitive sector. | AA4: Blue Door III is a moderately leveraged, core-plus self-storage vehicle that contrasts sharply with its debt-free sibling: the 45.96% LTV fixed-rate interest-only financing amplifies both cash-on-cash and tax shelter while imposing a defined seven-year refinancing-or-sale imperative tied to the November 2032 maturity. The investment case rests on SmartStop lifting NOI across three Sun Belt facilities through revenue management, with the interest-only structure front-loading distributions but building no principal equity, so terminal value is wholly a function of NOI growth and exit pricing against a balloon. Pervasive affiliation across lender, master tenants, manager, and 721 counterparty concentrates both operational alignment and conflict risk in one sponsor family, and the thin day-one equity cushion leaves limited margin if storage fundamentals soften. The after-tax profile is the strongest feature, roughly 89-92% early-year shelter and a ~7.08% tax-equivalent yield for cash investors, but the 4.00% pre-tax going-in yield, 15.19% load, and floating-rate extension risk make the offering most coherent for tax-sensitive investors comfortable with leverage and a defined exit window rather than those prioritizing capital preservation. | AB4: 0.04 | AC4: 0.0425 | AD4: 0.0427 | AE4: 0.0428 | AF4: 0.0431 | AG4: 0.0432 | AH4: 0.0452 | AI4: Sold | AJ4: Sold | AK4: Sold | AL4: 0.0428 | AM4: 0.0708 | AN4: =IFERROR((AB4 * ((1 - VALUE(SUBSTITUTE(H4, " LTV", ""))) + 0.02)) + (PMT(0.0535/12, 25*12, -VALUE(SUBSTITUTE(H4, " LTV", ""))) * 12) + (0.02/10) + (0.03/10) + 0.02, "N/A") -> 0.080791891 | AO4: SMST Lender, LLC | AP4: 5.00% (Fixed) | AQ4: 7 years | AR4: 7 years | AS4: N/A (interest-only) | AT4: 1.81x | AU4: 4860 North 83rd Avenue, Phoenix, AZ | AV4: https://lh3.googleusercontent.com/d/1GCvzEMexmpTgjlyyGJUhAnO2MFsnLqaV | AX4: 100000 | AY4: =IFERROR(__xludf.DUMMYFUNCTION("IF(ISBLANK(AV4), """", IF(REGEXMATCH(AV4, ""/file/d/""), ""https://lh3.googleusercontent.com/d/"" & REGEXEXTRACT(AV4, ""/d/([a-zA-Z0-9_-]+)""), AV4))"),"https://lh3.googleusercontent.com/d/1GCvzEMexmpTgjlyyGJUhAnO2MFsnLqaV") -> https://lh3.googleusercontent.com/d/1GCvzEMexmpTgjlyyGJUhAnO2MFsnLqaV | AZ4: =IF(AM4="Not Disclosed", AB4 + ((14545 / 100000) * (0.32 / (1 - 0.32))), AM4) -> 0.0708 | BA4: =if(AM4="Not Disclosed", "Est. Tax-Adjusted Yield⁹", "Tax-Adjusted Yield") -> Tax-Adjusted Yield | BB4: =if(AW4="", "Offering Documents Available By Request", "Download Offering Documents") -> Offering Documents Available By Request | BC4: blue-door-property-iii-dst | BD4: sponsors/smartstop | BE4: property-type/self-storage | BF4: ="Learn More About "&B4 -> Learn More About SmartStop | BG4: ="Learn More About "&L4&" Properties" -> Learn More About Self-Storage Properties | BH4: {=IFERROR(XLOOKUP($B4, 'Sponsor Connection'!$A:$A, 'Sponsor Connection'!$B:$B), )} -> 2013 | BI4: {=IFERROR(XLOOKUP($B4, 'Sponsor Connection'!$A:$A, 'Sponsor Connection'!$D:$D), )} -> SmartStop is a self-storage REIT (NYSE: SMA) that completed an $810 million IPO in April 2025 and sponsors self-storage DSTs through its broader platform, with assets in the $7 billion-plus range post-listing. Its pure-play self-storage focus, internal management and combined U.S.-and-Canada footprint give it a clean, single-sector thesis, and the recent public listing adds a transparency and liquidity dimension uncommon among DST sponsors. For exchangers, it offers concentrated exposure to a resilient, low-operating-intensity asset class. | BJ4: {=IF($B4="", "", LET(aum, IFERROR(XLOOKUP($B4, 'Sponsor Connection'!$A:$A, 'Sponsor Connection'!$C:$C), ""), IF(OR(aum="", aum=0), "Not Reported", aum)))} -> 7000000000 | BK4: {=IF(ISBLANK($B4), "", LET(val, IFERROR(XLOOKUP($B4, 'Sponsor Connection'!$A:$A, 'Sponsor Connection'!$M:$M), ""), IF(OR(ISBLANK(val), val="", val=0), "Not Reported", val)))} -> Not Reported | BL4: {=IF(ISBLANK($B4), "", LET(val, IFERROR(XLOOKUP($B4, 'Sponsor Connection'!$A:$A, 'Sponsor Connection'!$N:$N), ""), IF(val="", "Not Reported", val)))} -> No Data | BM4: {=IF(ISBLANK($B4), "", LET(val, IFERROR(XLOOKUP($B4, 'Sponsor Connection'!$A:$A, 'Sponsor Connection'!$O:$O), ""), IF(val="", "Not Reported", val)))} -> No Data | BN4: {=IF(ISBLANK($B4), "", LET(val, IFERROR(XLOOKUP($B4, 'Sponsor Connection'!$A:$A, 'Sponsor Connection'!$P:$P), ""), IF(val="", "Not Reported", val)))} -> No Data | BO4: {=IF(ISBLANK($B4), "", LET(val, IFERROR(XLOOKUP($B4, 'Sponsor Connection'!$A:$A, 'Sponsor Connection'!$Q:$Q), ""), IF(val="", "Not Reported", val)))} -> No Data | BP4: {=IFERROR(XLOOKUP($B4, 'Sponsor Connection'!$A:$A, 'Sponsor Connection'!$L:$L), )} -> https://img.logo.dev/smartstop.com?token=pk_FIVsDKgZTvCedVXXtt2rEg&size=200&retina=true | BQ4: =AL4 -> 0.0428 | BR4: =IFERROR(VLOOKUP(L4, Benchmarks!$A$2:$D$15, 2, FALSE), "Not Analyzed") -> 0.04495 | BS4: =IFERROR(IF(OR(ISBLANK(BQ4), ISBLANK(BR4)), "", IF(ABS(BQ4-BR4)/BQ4 <= 0.1, "Meets Average", IF(BQ4 > BR4, "Above Average", "Below Average"))), "Not Analyzed") -> Meets Average | BT4: =iferror((BW4-AB4)/AB4, 0) -> 0.13 | BU4: =IFERROR(VLOOKUP(L4, Benchmarks!$A$2:$D$15, 4, FALSE), "Not Analyzed") -> 0.13869615 | BV4: =IFERROR(IF(OR(ISBLANK(BT4), ISBLANK(BU4)), "", IF(ABS(BT4-BU4)/BT4 <= 0.1, "Meets Average", IF(BT4 > BU4, "Above Average", "Below Average"))), "Not Analyzed") -> Meets Average | BW4: =max(AB4:AK4) -> 0.0452 | BX4: =IFERROR(VLOOKUP(L4, Benchmarks!$A$2:$D$15, 3, FALSE), "Not Analyzed") -> 0.0479 | BY4: =IFERROR(IF(OR(ISBLANK(BW4), ISBLANK(BX4)), "", IF(ABS(BW4-BX4)/BW4 <= 0.1, "Meets Average", IF(BW4 > BX4, "Above Average", "Below Average"))), "Not Analyzed") -> Meets Average | BZ4: ="Investment: " & A4 & " | Sponsor: " & B4 & " | Structure: " & C4 & " | Status: " & D4 & " | LTV: " & H4 & " | Availability: " & K4 & " | Location: " & N4 & " | Strategy: " & P4 & " | 721 Exchange Exit: " & Q4 & " | Estimated Hold: " & R4 & " | Cap Rate Equivalent: " & AN4 & " | Minimum Investment: " & AX4 -> Investment: Blue Door Property III, DST | Sponsor: SmartStop | Structure: Delaware Statutory Trust (DST) | Status: Available | LTV: 45.96% LTV | Availability: 1 | Location: AZ, FL, TX | Strategy: Core-Plus | 721 Exchange Exit: Optional | Estimated Hold: 7 years | Cap Rate Equivalent: 0.0807918912165384 | Minimum Investment: 100000 | CA4: =A4&" ("&H4&")"&CHAR(10)&CHAR(10)&"Blue Door Property III is a leveraged DST holding three SmartStop-branded self-storage facilities (~1,927 units) across Phoenix, Longwood, and Dallas at ~90% occupancy, financed at 45.96% LTV on separate fixed-rate, interest-only mortgages aggregating $24"&".2M. Each asset is leased to a state-specific affiliated master tenant under a base/additional/bonus-rent waterfall with active revenue management. The thesis targets leveraged, inflation-responsive storage income with an optional Section 721 rollover ahe"&"ad of the November 2032 loan maturity."&CHAR(10)&CHAR(10)&">> Download Offering Documents"&CHAR(10)&"https://www.baker1031.com/sponsors/smartstop" -> Blue Door Property III, DST (45.96% LTV) Blue Door Property III is a leveraged DST holding three SmartStop-branded self-storage facilities (~1,927 units) across Phoenix, Longwood, and Dallas at ~90% occupancy, financed at 45.96% LTV on separate fixed-rate, interest-only mortgages aggregating $24.2M. Each asset is leased to a state-specific affiliated master tenant under a base/additional/bonus-rent waterfall with active revenue management. The thesis targets leveraged, inflation-responsive storage income with an optional Section 721 rollover ahead of the November 2032 loan maturity. >> Download Offering Documents https://www.baker1031.com/sponsors/smartstop
A5: Blue Owl Real Estate Exchange V DST | B5: Blue Owl | C5: Delaware Statutory Trust (DST) | D5: Coming Soon / Under Review | E5: 269491892 | F5: 269491892 | G5: 0 | H5: 0.00% LTV | I5: 269491892 | J5: 46028 | K5: =(I5/F5) -> 1 | L5: Industrial | M5: KY, OH, MI | N5: =IFERROR(__xludf.DUMMYFUNCTION("TEXTJOIN("", "", TRUE, SORT(TRANSPOSE(SPLIT(M5, "", ""))))"),"KY, MI, OH") -> KY, MI, OH | O5: 7.50% | P5: Core | Q5: Mandatory | R5: 2 years | S5: Three single-tenant net-leased industrial manufacturing properties held debt-free in a parent/operating DST structure: 111 Cosma Drive, Bowling Green KY (~1,351,200 SF on ~134 acres), 100% leased to Bowling Green Metalforming LLC, a wholly-owned subsidiary of Magna International Inc.; and two American Rheinmetall (Loc Performance Products) facilities, 1115 South Wayne Street, Saint Marys OH (~701,000 SF, 1939-1973 vintage) and 13505 North Haggerty Road, Plymouth MI (~289,000 SF, 2002), each leased to a subsidiary of Rheinmetall AG. Both tenant leases carry ~20-year base terms, with escalators of 1.25% per annum (Magna) and 2.0% per annum (American Rheinmetall). The Magna site includes a ground-lease and industrial-revenue-bond structure providing tax abatement. The properties are owned free and clear, with the trust agreements prohibiting permanent financing, and the master lease is guaranteed by Blue Owl's Operating Partnership subject to a net-worth standard. Thesis is durable, long-duration credit-tenant net-lease income with an optional Section 721 rollover into the non-listed, perpetual-life Blue Owl Real Estate Net Lease Trust. | T5: The portfolio is leased to subsidiaries of two substantial industrial credits: Bowling Green Metalforming, a wholly-owned unit of Magna International, a publicly traded global Tier-1 automotive supplier, and Loc Performance/American Rheinmetall, a subsidiary of Rheinmetall AG, a German defense and industrial group benefiting from the European defense-spending expansion. The Rheinmetall-linked defense exposure is a differentiated, counter-cyclical demand driver atypical of net-lease portfolios, though both leases sit with operating subsidiaries rather than the rated parents. | U5: Both the Magna and American Rheinmetall properties carry approximately 20-year base lease terms, producing an exceptionally long weighted-average lease term that underpins durable contractual income and supports the perpetual-life UPREIT thesis. Escalators differ materially, 2.0% per annum for American Rheinmetall versus a below-market 1.25% per annum for Magna, the latter eroding real income over the multi-decade term. | V5: The portfolio is owned free and clear, and the trust agreements affirmatively prohibit the trustee from placing permanent financing, eliminating refinancing, maturity, and interest-rate risk entirely and removing the equal-or-greater-debt replacement requirement for 1031 investors. The structural cost is the absence of positive leverage, which caps levered return and is the primary reason the going-in distribution sits in the high-4% range. | W5: The FMV Option permits Blue Owl's Operating Partnership, at its sole discretion, to acquire investor interests for OP units in the non-listed, perpetual-life Blue Owl Real Estate Net Lease Trust after a two-year hold, offering a potential tax-deferred path into a large, diversified net-lease REIT platform. The exchange is into a non-traded, illiquid vehicle whose NAV, redemption terms, and exercise timing are sponsor-controlled, ceding investor control and price transparency. | X5: The assets are large, special-purpose manufacturing facilities purpose-built for their incumbents, the Magna plant alone spanning ~1.35M SF on 134 acres, which makes them mission-critical to tenant operations and raises renewal probability, but also concentrates re-leasing and repurposing risk given limited alternative-use demand if a tenant vacates. The AR Ohio asset is of 1939-1973 vintage, and the Magna site carries ground-lease and industrial-revenue-bond complexity tied to its tax abatement. | Y5: The offering provides a long-duration (~20-year WALT) single-tenant net-lease industrial portfolio leased to subsidiaries of two substantial industrial credits, Magna International and Rheinmetall AG, with the defense-linked Rheinmetall exposure adding a differentiated, counter-cyclical demand tailwind. The structure is debt-free with leverage contractually prohibited, removing all refinancing and maturity risk, and the master lease is guaranteed by Blue Owl's Operating Partnership subject to a net-worth covenant. Distributions begin at 4.77% and step up to 6.01% over the 20-year forecast, and the optional Section 721 FMV Option offers a tax-deferred path into the large, diversified, perpetual-life Blue Owl net-lease REIT. | Z5: The properties are large, special-purpose manufacturing facilities with limited alternative-use demand and elevated re-leasing cost if a tenant vacates, and the AR Ohio asset is of 1939-1973 vintage. Both leases are with operating subsidiaries (Bowling Green Metalforming, Loc Performance) rather than the rated parents, and the only contractual credit backstop is Blue Owl's own Operating Partnership guaranty subject to a net-worth standard, concentrating credit support within the sponsor family. The Magna escalator is a below-market 1.25% per annum, eroding real income across a 20-year term, and the Magna site's ground-lease/industrial-revenue-bond structure adds title and tax-abatement complexity. The 721 consideration would be units in the non-listed, perpetual-life Blue Owl REIT, an illiquid vehicle with sponsor-controlled NAV and redemption gates, exercisable only at the Operating Partnership's discretion. Going-in cash yield is modest at 4.77% against a 7.50% upfront load plus ongoing servicing and management fees and a disposition fee. | AA5: Blue Owl V is a debt-free, long-duration credit-tenant net-lease industrial vehicle engineered as a feeder into Blue Owl's perpetual-life net-lease REIT via an optional Section 721 UPREIT. Return is almost entirely contractual and front-loaded by 20-year leases with modest 1.25%-2.0% escalators, so the investment is fundamentally an income-and-tax-deferral play rather than a total-return or appreciation strategy, consistent with its stated capital-preservation objective. The two credits are substantial but exposure runs through operating subsidiaries backed only by the sponsor's Operating Partnership guaranty, and the assets' special-purpose nature concentrates risk in tenant retention over a multi-decade horizon. The defining feature is the perpetual UPREIT optionality: rather than a defined sale, the likely path is conversion into non-listed Blue Owl REIT OP units, moving investors from a discrete, transparent net-lease portfolio into a sponsor-managed, illiquid NAV REIT, attractive for tax-deferral continuity and diversification but ceding control, liquidity, and valuation transparency. The 4.77% going-in distribution is well-supported by in-place contractual rent; the principal sensitivities are long-horizon tenant retention at special-purpose assets and the terms and timing of the eventual 721 conversion. | AB5: 0.0477 | AC5: 0.0477 | AD5: 0.0477 | AE5: 0.0477 | AF5: 0.0477 | AG5: 0.0515 | AH5: 0.0515 | AI5: 0.0515 | AJ5: 0.0515 | AK5: 0.0515 | AL5: 0.0496 | AM5: Not disclosed | AN5: =IFERROR((AB5 * ((1 - VALUE(SUBSTITUTE(H5, " LTV", ""))) + 0.02)) + (PMT(0.0535/12, 25*12, -VALUE(SUBSTITUTE(H5, " LTV", ""))) * 12) + (0.02/10) + (0.03/10) + 0.02, "N/A") -> 0.073654 | AO5: None (debt-free) | AP5: N/A (no debt) | AQ5: N/A (no debt) | AR5: N/A (no debt) | AS5: N/A (no debt) | AT5: N/A - no debt service | AU5: 111 Cosma Drive, Bowling Green, KY | AV5: https://drive.google.com/file/d/1SYLj4lsZa73K392bDZMcdABsto2FWap9/view?usp=sharing | AX5: 100000 | AY5: =IFERROR(__xludf.DUMMYFUNCTION("IF(ISBLANK(AV5), """", IF(REGEXMATCH(AV5, ""/file/d/""), ""https://lh3.googleusercontent.com/d/"" & REGEXEXTRACT(AV5, ""/d/([a-zA-Z0-9_-]+)""), AV5))"),"https://lh3.googleusercontent.com/d/1SYLj4lsZa73K392bDZMcdABsto2FWap9") -> https://lh3.googleusercontent.com/d/1SYLj4lsZa73K392bDZMcdABsto2FWap9 | AZ5: =IF(AM5="Not Disclosed", AB5 + ((14545 / 100000) * (0.32 / (1 - 0.32))), AM5) -> 0.11614706 | BA5: =if(AM5="Not Disclosed", "Est. Tax-Adjusted Yield⁹", "Tax-Adjusted Yield") -> Est. Tax-Adjusted Yield⁹ | BB5: =if(AW5="", "Offering Documents Available By Request", "Download Offering Documents") -> Offering Documents Available By Request | BC5: blue-owl-real-estate-exchange-v-dst | BD5: sponsors/blue-owl | BE5: property-type/industrial | BF5: ="Learn More About "&B5 -> Learn More About Blue Owl | BG5: ="Learn More About "&L5&" Properties" -> Learn More About Industrial Properties | BH5: {=IFERROR(XLOOKUP($B5, 'Sponsor Connection'!$A:$A, 'Sponsor Connection'!$B:$B), )} -> 2009 | BI5: {=IFERROR(XLOOKUP($B5, 'Sponsor Connection'!$A:$A, 'Sponsor Connection'!$D:$D), )} -> Blue Owl Capital is a roughly $273 billion alternatives manager whose net-lease pedigree—anchored by the Oak Street platform it absorbed—feeds its DST/1031 vehicle, Blue Owl Real Estate Exchange (OREX). The strategy is purpose-built around triple-net, sale-leaseback assets leased to creditworthy corporate tenants, a cash-flow-stable profile well suited to exchange investors seeking predictability. With a permanent-capital orientation and a diversified credit-and-real-assets platform behind it, OREX brings institutional sourcing to a niche that rewards tenant credit discipline. | BJ5: {=IF($B5="", "", LET(aum, IFERROR(XLOOKUP($B5, 'Sponsor Connection'!$A:$A, 'Sponsor Connection'!$C:$C), ""), IF(OR(aum="", aum=0), "Not Reported", aum)))} -> 273000000000 | BK5: {=IF(ISBLANK($B5), "", LET(val, IFERROR(XLOOKUP($B5, 'Sponsor Connection'!$A:$A, 'Sponsor Connection'!$M:$M), ""), IF(OR(ISBLANK(val), val="", val=0), "Not Reported", val)))} -> Not Reported | BL5: {=IF(ISBLANK($B5), "", LET(val, IFERROR(XLOOKUP($B5, 'Sponsor Connection'!$A:$A, 'Sponsor Connection'!$N:$N), ""), IF(val="", "Not Reported", val)))} -> No Data | BM5: {=IF(ISBLANK($B5), "", LET(val, IFERROR(XLOOKUP($B5, 'Sponsor Connection'!$A:$A, 'Sponsor Connection'!$O:$O), ""), IF(val="", "Not Reported", val)))} -> No Data | BN5: {=IF(ISBLANK($B5), "", LET(val, IFERROR(XLOOKUP($B5, 'Sponsor Connection'!$A:$A, 'Sponsor Connection'!$P:$P), ""), IF(val="", "Not Reported", val)))} -> No Data | BO5: {=IF(ISBLANK($B5), "", LET(val, IFERROR(XLOOKUP($B5, 'Sponsor Connection'!$A:$A, 'Sponsor Connection'!$Q:$Q), ""), IF(val="", "Not Reported", val)))} -> No Data | BP5: {=IFERROR(XLOOKUP($B5, 'Sponsor Connection'!$A:$A, 'Sponsor Connection'!$L:$L), )} -> https://img.logo.dev/blueowl.com?token=pk_FIVsDKgZTvCedVXXtt2rEg&size=200&retina=true | BQ5: =AL5 -> 0.0496 | BR5: =IFERROR(VLOOKUP(L5, Benchmarks!$A$2:$D$15, 2, FALSE), "Not Analyzed") -> 0 | BS5: =IFERROR(IF(OR(ISBLANK(BQ5), ISBLANK(BR5)), "", IF(ABS(BQ5-BR5)/BQ5 <= 0.1, "Meets Average", IF(BQ5 > BR5, "Above Average", "Below Average"))), "Not Analyzed") -> Above Average | BT5: =iferror((BW5-AB5)/AB5, 0) -> 0.07966457 | BU5: =IFERROR(VLOOKUP(L5, Benchmarks!$A$2:$D$15, 4, FALSE), "Not Analyzed") -> 0.14414694 | BV5: =IFERROR(IF(OR(ISBLANK(BT5), ISBLANK(BU5)), "", IF(ABS(BT5-BU5)/BT5 <= 0.1, "Meets Average", IF(BT5 > BU5, "Above Average", "Below Average"))), "Not Analyzed") -> Below Average | BW5: =max(AB5:AK5) -> 0.0515 | BX5: =IFERROR(VLOOKUP(L5, Benchmarks!$A$2:$D$15, 3, FALSE), "Not Analyzed") -> 0.05854 | BY5: =IFERROR(IF(OR(ISBLANK(BW5), ISBLANK(BX5)), "", IF(ABS(BW5-BX5)/BW5 <= 0.1, "Meets Average", IF(BW5 > BX5, "Above Average", "Below Average"))), "Not Analyzed") -> Below Average | BZ5: ="Investment: " & A5 & " | Sponsor: " & B5 & " | Structure: " & C5 & " | Status: " & D5 & " | LTV: " & H5 & " | Availability: " & K5 & " | Location: " & N5 & " | Strategy: " & P5 & " | 721 Exchange Exit: " & Q5 & " | Estimated Hold: " & R5 & " | Cap Rate Equivalent: " & AN5 & " | Minimum Investment: " & AX5 -> Investment: Blue Owl Real Estate Exchange V DST | Sponsor: Blue Owl | Structure: Delaware Statutory Trust (DST) | Status: Coming Soon / Under Review | LTV: 0.00% LTV | Availability: 1 | Location: KY, MI, OH | Strategy: Core | 721 Exchange Exit: Mandatory | Estimated Hold: 2 years | Cap Rate Equivalent: 0.073654 | Minimum Investment: 100000 | CA5: =A5&" ("&H5&")"&CHAR(10)&CHAR(10)&"Blue Owl Real Estate Exchange V is a debt-free DST holding three single-tenant net-leased industrial manufacturing properties leased to subsidiaries of Magna International and Rheinmetall AG on ~20-year base terms. The Bowling Green Metalforming site carr"&"ies a ground-lease and industrial-revenue-bond structure providing tax abatement, and the trust agreements prohibit permanent financing. The thesis is durable, long-duration credit-tenant net-lease income with an optional Section 721 rollover into the per"&"petual-life Blue Owl Real Estate Net Lease Trust."&CHAR(10)&CHAR(10)&">> Download Offering Documents"&CHAR(10)&"https://www.baker1031.com/sponsors/blue-owl" -> Blue Owl Real Estate Exchange V DST (0.00% LTV) Blue Owl Real Estate Exchange V is a debt-free DST holding three single-tenant net-leased industrial manufacturing properties leased to subsidiaries of Magna International and Rheinmetall AG on ~20-year base terms. The Bowling Green Metalforming site carries a ground-lease and industrial-revenue-bond structure providing tax abatement, and the trust agreements prohibit permanent financing. The thesis is durable, long-duration credit-tenant net-lease income with an optional Section 721 rollover into the perpetual-life Blue Owl Real Estate Net Lease Trust. >> Download Offering Documents https://www.baker1031.com/sponsors/blue-owl
A6: BR Churchill Downs, DST | B6: Bluerock | C6: Delaware Statutory Trust (DST) | D6: Closed | E6: 68517539 | F6: 37778539 | G6: 30739000 | H6: 44.86% LTV | I6: 0 | J6: 46196 | K6: =(I6/F6) -> 0 | L6: Multifamily | M6: NC | N6: =IFERROR(__xludf.DUMMYFUNCTION("TEXTJOIN("", "", TRUE, SORT(TRANSPOSE(SPLIT(M6, "", ""))))"),"NC") -> NC | O6: 13.15% | P6: Value-Add | Q6: Mandatory | R6: 7-10 years | S6: A 272-unit Class B, direct-entry townhome and garden-style apartment community at 800 Churchill Downs Drive, Aberdeen NC, in the Pinehurst Metro (Moore County), on ~21.31 acres with 288,480 rentable SF (one-, two-, and three-bedroom units averaging 1,061 SF), completed in 2000 and 2003. The Trust acquired the Property in April 2025 for $56.6M, ~$1.3M below appraised value, financed with a $30,739,000 KeyBank/Fannie Mae DUS first mortgage (44.86% loan-to-capitalization, 5.13% fixed, interest-only, maturing May 2035) and equity. The business plan is value-add: in-unit washer/dryer installation, light interior upgrades to classic finishes, and exterior/landscaping/signage improvements atop $1.5M of prior-owner capex, supported by revenue-management software and third-party management (RPM Living). The Property is leased to an affiliated Master Tenant under a 10-year master lease paying Base Rent (debt service), Additional Rent (monthly distributions), and Supplemental Rent (performance distributions). The Pinehurst Metro sits ~70-90 miles from the high-growth Charlotte and Raleigh-Durham metros, with a golf-tourism-anchored economy and proximity to Fort Liberty. Exit options include an optional Section 721 FMV rollover into a Bluerock-affiliated operating partnership. | T6: The investment thesis is operational value creation on a Class B community with below-market rents (income-to-rent ratio ~4.5x on ~$79,000 average household income). The program installs in-unit washers and dryers at a rent premium, applies light interior upgrades to original finishes, and refreshes exteriors, landscaping, and signage, layered on $1.5M of capital already deployed by prior owners, with revenue-management software and a national third-party manager (RPM Living) engaged to drive rate growth. | U6: The Property was acquired for $56.6M, approximately $1.3M below appraised value, providing a measure of day-one valuation cushion against the 44.86% leverage. The discount is modest in percentage terms (~2.3% of purchase price), so the equity margin of safety is real but thin. | V6: The asset sits in the Pinehurst Metro, ranked the top micropolitan area in North Carolina for seven consecutive years and tenth nationally, positioned roughly equidistant (70-90 miles) between the high-growth Charlotte and Raleigh-Durham metros. The local economy is anchored by golf tourism (Home of American Golf, the USGA's second headquarters, and future U.S. Opens including 2029, with ~$805M in annual golf-tourism impact) and supported by healthcare and Fort Liberty defense employment. | W6: Financing is a $30.74M KeyBank loan originated under the Fannie Mae DUS program, fixed at 5.13% and interest-only for the full 10-year term (maturing May 2035), at 44.86% loan-to-capitalization. The agency execution provides institutional terms and the interest-only structure maximizes current distributions and supports a healthy 2.04x Year 1 coverage, but the full principal balloons at maturity and prepayment/defeasance provisions constrain the exit window. | X6: The master lease channels return through three layers: Base Rent covering debt service, Additional Rent producing a flat ~4.25% monthly distribution, and Supplemental Rent equal to 90% of revenue above a stated breakpoint. As the value-add program lifts revenue, investor cash-on-cash is forecast to ramp from 4.28% to 6.33%, a performance-linked upside atypical of stabilized DSTs, though the affiliated master tenant retains the Base Rent spread and 10% of the Supplemental Rent. | Y6: The offering pairs a below-appraised-value entry on a Class B multifamily asset with a defined value-add plan, in a supply-constrained, top-ranked North Carolina micropolitan market between two high-growth metros. Fannie Mae DUS fixed-rate financing at 5.13% delivers a healthy 2.04x Year 1 DSCR with interest-only payments that maximize current distributions, and the master-lease Supplemental Rent gives investors performance-linked upside that ramps cash-on-cash from 4.28% to 6.33%. Depreciation shelter is substantial (roughly 82%-127% of cash flow sheltered; ~8.7% average tax-equivalent yield), and broad demand tailwinds, a national housing shortage, depressed new multifamily supply, and the homeownership affordability gap, support the rental thesis. | Z6: The going-in distribution is modest at ~4.25%, and reaching the 6.33% forecast depends entirely on executing the value-add and clearing the Supplemental Rent breakpoint, operational and lease-up risk rather than contractual income. The day-one equity cushion is thin (acquired only ~$1.3M, ~2.3%, below appraised value) against 44.86% leverage, and the KeyBank loan is interest-only with the full $30.74M ballooning at the May 2035 maturity, with prepayment and defeasance provisions that constrain the 7-10 year exit window. The master tenant is a thinly capitalized Sponsor affiliate funded by an Operating Partnership demand note, and it retains the Base-Rent-to-breakpoint spread plus 10% of Supplemental Rent, partially misaligning upside. The Property is single-asset, single-market (Aberdeen/Pinehurst), Class B of 2000/2003 vintage with ~$1.2M of identified long-term capital needs, and the local economy concentrates in golf tourism and Fort Liberty defense activity. Insurance-cost inflation is a demonstrated risk: a related Sponsor program cut distributions from 4.25% to 3.00% in 2024 on a 62% year-over-year insurance spike before restoring them. | AA6: BR Churchill Downs is a leveraged value-add multifamily DST with a bifurcated return profile: a modest ~4.25% contractual Additional Rent floor plus performance-linked Supplemental Rent that, if the business plan executes, lifts cash-on-cash toward ~6.3% and averages ~5.2% over a 7-10 year hold. Unlike stabilized net-lease DSTs, the thesis depends on operational execution, washer/dryer installs, light renovations, and revenue management lifting Class B rents in the supply-constrained Pinehurst micropolitan market. The Fannie Mae DUS fixed-rate interest-only loan provides strong 2.04x coverage and front-loads distributions but builds no equity and balloons in 2035, so terminal value hinges on NOI growth and exit pricing against a thin day-one basis discount. The after-tax profile is a meaningful draw (~8.7% average tax-equivalent yield on high depreciation shelter). The dominant sensitivities are value-add execution and rent growth, insurance-cost inflation (a proven distribution risk in the sponsor's related programs), and refinancing or selling the balloon within the hold window; the optional Section 721 FMV conversion into a Bluerock-affiliated operating partnership offers a tax-deferred alternative exit, but into an illiquid, sponsor-controlled vehicle. | AB6: 0.0428 | AC6: 0.0427 | AD6: 0.0449 | AE6: 0.0482 | AF6: 0.0515 | AG6: 0.0539 | AH6: 0.0563 | AI6: 0.0587 | AJ6: 0.0611 | AK6: 0.0633 | AL6: 0.0523 | AM6: 0.0874 | AN6: =IFERROR((AB6 * ((1 - VALUE(SUBSTITUTE(H6, " LTV", ""))) + 0.02)) + (PMT(0.0535/12, 25*12, -VALUE(SUBSTITUTE(H6, " LTV", ""))) * 12) + (0.02/10) + (0.03/10) + 0.02, "N/A") -> 0.082032997 | AO6: KeyBank National Association | AP6: 5.13% (Fixed) | AQ6: 10 years | AR6: 10 years | AS6: N/A (interest-only) | AT6: 2.04x | AU6: 800 Churchill Downs Drive, Aberdeen, NC | AV6: https://drive.google.com/file/d/1DlAEjC2ku2pfRp6bY4ULgY41HtnLzfVb/view?usp=sharing | AX6: 100000 | AY6: =IFERROR(__xludf.DUMMYFUNCTION("IF(ISBLANK(AV6), """", IF(REGEXMATCH(AV6, ""/file/d/""), ""https://lh3.googleusercontent.com/d/"" & REGEXEXTRACT(AV6, ""/d/([a-zA-Z0-9_-]+)""), AV6))"),"https://lh3.googleusercontent.com/d/1DlAEjC2ku2pfRp6bY4ULgY41HtnLzfVb") -> https://lh3.googleusercontent.com/d/1DlAEjC2ku2pfRp6bY4ULgY41HtnLzfVb | AZ6: =IF(AM6="Not Disclosed", AB6 + ((14545 / 100000) * (0.32 / (1 - 0.32))), AM6) -> 0.0874 | BA6: =if(AM6="Not Disclosed", "Est. Tax-Adjusted Yield⁹", "Tax-Adjusted Yield") -> Tax-Adjusted Yield | BB6: =if(AW6="", "Offering Documents Available By Request", "Download Offering Documents") -> Offering Documents Available By Request | BC6: br-churchill-downs-dst | BD6: sponsors/bluerock | BE6: property-type/multifamily | BF6: ="Learn More About "&B6 -> Learn More About Bluerock | BG6: ="Learn More About "&L6&" Properties" -> Learn More About Multifamily Properties | BH6: {=IFERROR(XLOOKUP($B6, 'Sponsor Connection'!$A:$A, 'Sponsor Connection'!$B:$B), )} -> 2002 | BI6: {=IFERROR(XLOOKUP($B6, 'Sponsor Connection'!$A:$A, 'Sponsor Connection'!$D:$D), )} -> Bluerock has sponsored syndicated 1031 exchanges for more than eighteen years, and its Bluerock Value Exchange (BVEX) arm packages multifamily, industrial and other core sectors into what it markets as 'Premier Exchange Properties.' Backed by a broader Bluerock platform of roughly $19 billion that also spans interval funds, the firm pairs institutional acquisition capability with a long DST track record across multiple cycles. Its national footprint and sector breadth position it as a diversified mid-to-large sponsor rather than a single-asset specialist. | BJ6: {=IF($B6="", "", LET(aum, IFERROR(XLOOKUP($B6, 'Sponsor Connection'!$A:$A, 'Sponsor Connection'!$C:$C), ""), IF(OR(aum="", aum=0), "Not Reported", aum)))} -> 19000000000 | BK6: {=IF(ISBLANK($B6), "", LET(val, IFERROR(XLOOKUP($B6, 'Sponsor Connection'!$A:$A, 'Sponsor Connection'!$M:$M), ""), IF(OR(ISBLANK(val), val="", val=0), "Not Reported", val)))} -> 97 | BL6: {=IF(ISBLANK($B6), "", LET(val, IFERROR(XLOOKUP($B6, 'Sponsor Connection'!$A:$A, 'Sponsor Connection'!$N:$N), ""), IF(val="", "Not Reported", val)))} -> 0.21387835 | BM6: {=IF(ISBLANK($B6), "", LET(val, IFERROR(XLOOKUP($B6, 'Sponsor Connection'!$A:$A, 'Sponsor Connection'!$O:$O), ""), IF(val="", "Not Reported", val)))} -> 1.7736082 | BN6: {=IF(ISBLANK($B6), "", LET(val, IFERROR(XLOOKUP($B6, 'Sponsor Connection'!$A:$A, 'Sponsor Connection'!$P:$P), ""), IF(val="", "Not Reported", val)))} -> 4.0041237 | BO6: {=IF(ISBLANK($B6), "", LET(val, IFERROR(XLOOKUP($B6, 'Sponsor Connection'!$A:$A, 'Sponsor Connection'!$Q:$Q), ""), IF(val="", "Not Reported", val)))} -> 0.93814433 | BP6: {=IFERROR(XLOOKUP($B6, 'Sponsor Connection'!$A:$A, 'Sponsor Connection'!$L:$L), )} -> https://img.logo.dev/bluerockexchange.com?token=pk_FIVsDKgZTvCedVXXtt2rEg&size=200&retina=true | BQ6: =AL6 -> 0.0523 | BR6: =IFERROR(VLOOKUP(L6, Benchmarks!$A$2:$D$15, 2, FALSE), "Not Analyzed") -> 0.050338 | BS6: =IFERROR(IF(OR(ISBLANK(BQ6), ISBLANK(BR6)), "", IF(ABS(BQ6-BR6)/BQ6 <= 0.1, "Meets Average", IF(BQ6 > BR6, "Above Average", "Below Average"))), "Not Analyzed") -> Meets Average | BT6: =iferror((BW6-AB6)/AB6, 0) -> 0.47897196 | BU6: =IFERROR(VLOOKUP(L6, Benchmarks!$A$2:$D$15, 4, FALSE), "Not Analyzed") -> 0.24736349 | BV6: =IFERROR(IF(OR(ISBLANK(BT6), ISBLANK(BU6)), "", IF(ABS(BT6-BU6)/BT6 <= 0.1, "Meets Average", IF(BT6 > BU6, "Above Average", "Below Average"))), "Not Analyzed") -> Above Average | BW6: =max(AB6:AK6) -> 0.0633 | BX6: =IFERROR(VLOOKUP(L6, Benchmarks!$A$2:$D$15, 3, FALSE), "Not Analyzed") -> 0.052895455 | BY6: =IFERROR(IF(OR(ISBLANK(BW6), ISBLANK(BX6)), "", IF(ABS(BW6-BX6)/BW6 <= 0.1, "Meets Average", IF(BW6 > BX6, "Above Average", "Below Average"))), "Not Analyzed") -> Above Average | BZ6: ="Investment: " & A6 & " | Sponsor: " & B6 & " | Structure: " & C6 & " | Status: " & D6 & " | LTV: " & H6 & " | Availability: " & K6 & " | Location: " & N6 & " | Strategy: " & P6 & " | 721 Exchange Exit: " & Q6 & " | Estimated Hold: " & R6 & " | Cap Rate Equivalent: " & AN6 & " | Minimum Investment: " & AX6 -> Investment: BR Churchill Downs, DST | Sponsor: Bluerock | Structure: Delaware Statutory Trust (DST) | Status: Closed | LTV: 44.86% LTV | Availability: 0 | Location: NC | Strategy: Value-Add | 721 Exchange Exit: Mandatory | Estimated Hold: 7-10 years | Cap Rate Equivalent: 0.0820329974580921 | Minimum Investment: 100000 | CA6: =A6&" ("&H6&")"&CHAR(10)&CHAR(10)&"BR Churchill Downs is a 272-unit Class B townhome and garden apartment community in the Pinehurst Metro (Aberdeen, NC), acquired in April 2025 for $56.6M, ~$1.3M below appraised value, and financed with a $30.7M KeyBank/Fannie Mae DUS loan (5.13% fixed, i"&"nterest-only, 44.86% LTC). The value-add business plan layers in-unit washer/dryer installation and interior/exterior upgrades atop $1.5M of prior-owner capex under RPM Living management. The Pinehurst Metro sits 70-90 miles from the Charlotte and Raleigh"&"-Durham growth markets, with an optional Section 721 FMV rollover into a Bluerock-affiliated operating partnership."&CHAR(10)&CHAR(10)&">> Download Offering Documents"&CHAR(10)&"https://www.baker1031.com/sponsors/bluerock" -> BR Churchill Downs, DST (44.86% LTV) BR Churchill Downs is a 272-unit Class B townhome and garden apartment community in the Pinehurst Metro (Aberdeen, NC), acquired in April 2025 for $56.6M, ~$1.3M below appraised value, and financed with a $30.7M KeyBank/Fannie Mae DUS loan (5.13% fixed, interest-only, 44.86% LTC). The value-add business plan layers in-unit washer/dryer installation and interior/exterior upgrades atop $1.5M of prior-owner capex under RPM Living management. The Pinehurst Metro sits 70-90 miles from the Charlotte and Raleigh-Durham growth markets, with an optional Section 721 FMV rollover into a Bluerock-affiliated operating partnership. >> Download Offering Documents https://www.baker1031.com/sponsors/bluerock
A7: BR Diversified Industrial Portfolio 7, DST | B7: Bluerock | C7: Delaware Statutory Trust (DST) | D7: Limited Availability | E7: 60051084 | F7: 60051084 | G7: 0 | H7: 0.00% LTV | I7: 7900000 | J7: 46196 | K7: =(I7/F7) -> 0.13155466 | L7: Industrial | M7: VA, MO, FL, AL | N7: =IFERROR(__xludf.DUMMYFUNCTION("TEXTJOIN("", "", TRUE, SORT(TRANSPOSE(SPLIT(M7, "", ""))))"),"AL, FL, MO, VA") -> AL, FL, MO, VA | O7: 11.67% | P7: Core-Plus | Q7: Mandatory | R7: 7-10 years | S7: Five single-tenant industrial properties (~552,438 RSF total) held debt-free in a parent/operating DST under the BIGR Exchange platform, 100% leased on in-place absolute/triple-net leases with a ~11.7-year WALT: Quality Property, Prince George/Richmond VA (141,568 SF, 2007, leased to NVR, Inc. (NYSE: NVR; S&P BBB+) to 2039, manufacturing/distribution with industrial outdoor storage); Corporate Property, Bridgeton/St. Louis MO (238,113 SF, 1996, leased to BlueLinx (NYSE: BXC; S&P B+) to 2037, warehouse/outdoor storage); Saland (41,600 SF, 2021) and Beachwood (45,096 SF, 2017) Properties, Jacksonville FL (both leased to Woodsman Kitchen & Flooring to 2038); and Shields Property, Huntsville AL (86,061 SF, 1997, leased to DESHAZO Automation to 2032). Properties acquired ~$1.35M below appraised value, in Sunbelt and industrial-corridor markets with rents ~25% below submarket and ~13% projected cumulative market rent growth through 2029. The Trust leases all five to an affiliated Master Tenant under a 10-year master lease paying Base, Additional, and Supplemental Rent, distributed up to investors. Exit options include an optional Section 721 FMV rollover into a Bluerock-affiliated operating partnership within ~7-10 years. | T7: The portfolio spans five properties and four tenants, mixing NYSE-listed credits with private regional operators: NVR (NYSE: NVR; S&P BBB+, ~$22B market cap, fourth-largest U.S. homebuilder) at Richmond and BlueLinx (NYSE: BXC; S&P B+, national building-products distributor) at St. Louis, plus privately held Woodsman Kitchen & Flooring (Jacksonville, two assets, ~45% of local new-home cabinetry) and DESHAZO Automation (Huntsville, custom robotics and cranes). Leases are absolute/triple-net, though two of the four tenants are unrated private companies and the leases sit with the operating tenants rather than rated parents. | U7: The Properties are owned free and clear with no mortgage, eliminating refinancing, maturity, rate-cap, and foreclosure risk and removing the equal-or-greater-debt replacement requirement for 1031 investors averse to boot-offsetting leverage. The structural cost is the absence of positive leverage, which caps levered return and is the primary reason the 4.80% going-in distribution sits in the high-4% range. | V7: In-place income is durable and long-dated, with a weighted-average lease term of ~11.7 years across staggered expirations (DESHAZO 2032, BlueLinx 2037, Woodsman 2038, NVR 2039) and contractual annual rent escalations, supporting escalating contractual income across the 7-10 year hold. | W7: In-place rents are approximately 25% below current submarket levels on average, with ~13% projected cumulative market rent growth through 2029 and the industrial sector forecast to lead all major CRE sectors in NOI growth (~4.1% annualized 2026-2029). This positions the portfolio for rent capture on rollover and terminal-value appreciation, though the long ~11.7-year WALT means little of that mark-to-market is realized during the hold. | X7: The Corporate Property (St. Louis, 5+ acres of paved industrial outdoor storage) and Quality Property (Richmond, 9 acres of paved industrial outdoor storage) carry highly coveted industrial outdoor storage, a supply-constrained use that can command a scarcity-demand premium and support both income and exit value. | Y7: A debt-free, 100%-leased diversified industrial net-lease portfolio across five Sunbelt and industrial-corridor assets in four states, with a long ~11.7-year WALT on absolute/triple-net leases anchored by two NYSE-listed credits (NVR, S&P BBB+; BlueLinx, S&P B+) plus two private regional operators. The unlevered structure removes all refinancing, maturity, and foreclosure risk and the equal-or-greater-debt 1031 requirement. Embedded upside is meaningful: rents ~25% below market, ~13% projected cumulative market rent growth through 2029, and industrial NOI growth leading all CRE sectors, supported by two scarce industrial-outdoor-storage sites. Distributions ramp from 4.97% to 6.12% via performance-based Supplemental Rent; the portfolio was acquired ~$1.35M below appraised value, with moderate depreciation shelter (~6.9% average tax-equivalent yield). | Z7: The going-in distribution is modest at 4.80% (Base plus Additional Rent), and reaching 6.12% depends on performance-based Supplemental Rent rather than fully contractual income. Two of the four tenants (Woodsman, DESHAZO) are privately held and unrated, and DESHAZO carries the shortest lease (2032 expiry, ~84-month term), creating earlier rollover exposure on that asset; all leases sit with operating tenants rather than rated parents. The master tenant is a thinly capitalized Sponsor affiliate funded by an Operating Partnership demand note, and the sponsor, master tenant, manager, and 721 counterparty roles are concentrated within the Bluerock family. The ~25%-below-market rent upside is largely unrealized during a 7-10 year hold given the ~11.7-year WALT, making it primarily a terminal-value/appreciation thesis dependent on exit pricing and rent growth materializing. Three properties (Beachwood, Saland, Quality) sit in hurricane-susceptible zones, total load is ~11.67% of equity plus a 3.5% disposition fee, and depreciation shelter is comparatively low (~31%-38% of cash flow) given the debt-free, reserve-heavy capitalization. | AA7: BR Diversified Industrial Portfolio 7 is a debt-free, income-oriented industrial net-lease DST whose return splits between a flat ~4.80% contractual Base-plus-Additional Rent floor and a performance-linked Supplemental Rent layer that lifts cash-on-cash to ~6.1% and averages ~5.5% over a 7-10 year hold. Like Bluerock's other net-lease offerings, it pairs durable long-WALT (~11.7-year) contractual income from a diversified five-asset, four-tenant pool with an explicit appreciation thesis grounded in ~25%-below-market rents and a favorable industrial supply/demand backdrop. The unlevered structure is genuinely defensive against the rate environment, sidestepping the leveraged-DST maturity wall, but caps yield and leaves terminal value as the dominant return driver, since the long WALT means little of the mark-to-market upside is realized during the hold. The key sensitivities are exit pricing and the pace of industrial rent growth, tenant retention and renewal at lease expiry (notably DESHAZO in 2032), and the credit performance of two unrated private tenants; the optional Section 721 FMV conversion into a Bluerock-affiliated operating partnership offers a tax-deferred alternative exit into an illiquid, sponsor-controlled vehicle. The after-tax profile is a secondary benefit (~6.9% average tax-equivalent yield), though the depreciation shelter (~31%-38%) is lower than leveraged peers given no interest deduction. | AB7: 0.0497 | AC7: 0.0506 | AD7: 0.0517 | AE7: 0.0531 | AF7: 0.0546 | AG7: 0.0557 | AH7: 0.0568 | AI7: 0.058 | AJ7: 0.0595 | AK7: 0.0612 | AL7: 0.0551 | AM7: 0.0687 | AN7: =IFERROR((AB7 * ((1 - VALUE(SUBSTITUTE(H7, " LTV", ""))) + 0.02)) + (PMT(0.0535/12, 25*12, -VALUE(SUBSTITUTE(H7, " LTV", ""))) * 12) + (0.02/10) + (0.03/10) + 0.02, "N/A") -> 0.075694 | AO7: None (debt-free) | AP7: N/A (no debt) | AQ7: N/A (no debt) | AR7: N/A (no debt) | AS7: N/A (no debt) | AT7: N/A - no debt service | AU7: 13860 Corporate Woods Trail, Bridgeton, MO | AV7: https://lh3.googleusercontent.com/d/1c1Pdo3bRQdhIdMVlnFyaF36rQSG-IO1k | AX7: 100000 | AY7: =IFERROR(__xludf.DUMMYFUNCTION("IF(ISBLANK(AV7), """", IF(REGEXMATCH(AV7, ""/file/d/""), ""https://lh3.googleusercontent.com/d/"" & REGEXEXTRACT(AV7, ""/d/([a-zA-Z0-9_-]+)""), AV7))"),"https://lh3.googleusercontent.com/d/1c1Pdo3bRQdhIdMVlnFyaF36rQSG-IO1k") -> https://lh3.googleusercontent.com/d/1c1Pdo3bRQdhIdMVlnFyaF36rQSG-IO1k | AZ7: =IF(AM7="Not Disclosed", AB7 + ((14545 / 100000) * (0.32 / (1 - 0.32))), AM7) -> 0.0687 | BA7: =if(AM7="Not Disclosed", "Est. Tax-Adjusted Yield⁹", "Tax-Adjusted Yield") -> Tax-Adjusted Yield | BB7: =if(AW7="", "Offering Documents Available By Request", "Download Offering Documents") -> Offering Documents Available By Request | BC7: br-diversified-industrial-portfolio-7-dst | BD7: sponsors/bluerock | BE7: property-type/industrial | BF7: ="Learn More About "&B7 -> Learn More About Bluerock | BG7: ="Learn More About "&L7&" Properties" -> Learn More About Industrial Properties | BH7: {=IFERROR(XLOOKUP($B7, 'Sponsor Connection'!$A:$A, 'Sponsor Connection'!$B:$B), )} -> 2002 | BI7: {=IFERROR(XLOOKUP($B7, 'Sponsor Connection'!$A:$A, 'Sponsor Connection'!$D:$D), )} -> Bluerock has sponsored syndicated 1031 exchanges for more than eighteen years, and its Bluerock Value Exchange (BVEX) arm packages multifamily, industrial and other core sectors into what it markets as 'Premier Exchange Properties.' Backed by a broader Bluerock platform of roughly $19 billion that also spans interval funds, the firm pairs institutional acquisition capability with a long DST track record across multiple cycles. Its national footprint and sector breadth position it as a diversified mid-to-large sponsor rather than a single-asset specialist. | BJ7: {=IF($B7="", "", LET(aum, IFERROR(XLOOKUP($B7, 'Sponsor Connection'!$A:$A, 'Sponsor Connection'!$C:$C), ""), IF(OR(aum="", aum=0), "Not Reported", aum)))} -> 19000000000 | BK7: {=IF(ISBLANK($B7), "", LET(val, IFERROR(XLOOKUP($B7, 'Sponsor Connection'!$A:$A, 'Sponsor Connection'!$M:$M), ""), IF(OR(ISBLANK(val), val="", val=0), "Not Reported", val)))} -> 97 | BL7: {=IF(ISBLANK($B7), "", LET(val, IFERROR(XLOOKUP($B7, 'Sponsor Connection'!$A:$A, 'Sponsor Connection'!$N:$N), ""), IF(val="", "Not Reported", val)))} -> 0.21387835 | BM7: {=IF(ISBLANK($B7), "", LET(val, IFERROR(XLOOKUP($B7, 'Sponsor Connection'!$A:$A, 'Sponsor Connection'!$O:$O), ""), IF(val="", "Not Reported", val)))} -> 1.7736082 | BN7: {=IF(ISBLANK($B7), "", LET(val, IFERROR(XLOOKUP($B7, 'Sponsor Connection'!$A:$A, 'Sponsor Connection'!$P:$P), ""), IF(val="", "Not Reported", val)))} -> 4.0041237 | BO7: {=IF(ISBLANK($B7), "", LET(val, IFERROR(XLOOKUP($B7, 'Sponsor Connection'!$A:$A, 'Sponsor Connection'!$Q:$Q), ""), IF(val="", "Not Reported", val)))} -> 0.93814433 | BP7: {=IFERROR(XLOOKUP($B7, 'Sponsor Connection'!$A:$A, 'Sponsor Connection'!$L:$L), )} -> https://img.logo.dev/bluerockexchange.com?token=pk_FIVsDKgZTvCedVXXtt2rEg&size=200&retina=true | BQ7: =AL7 -> 0.0551 | BR7: =IFERROR(VLOOKUP(L7, Benchmarks!$A$2:$D$15, 2, FALSE), "Not Analyzed") -> 0 | BS7: =IFERROR(IF(OR(ISBLANK(BQ7), ISBLANK(BR7)), "", IF(ABS(BQ7-BR7)/BQ7 <= 0.1, "Meets Average", IF(BQ7 > BR7, "Above Average", "Below Average"))), "Not Analyzed") -> Above Average | BT7: =iferror((BW7-AB7)/AB7, 0) -> 0.23138833 | BU7: =IFERROR(VLOOKUP(L7, Benchmarks!$A$2:$D$15, 4, FALSE), "Not Analyzed") -> 0.14414694 | BV7: =IFERROR(IF(OR(ISBLANK(BT7), ISBLANK(BU7)), "", IF(ABS(BT7-BU7)/BT7 <= 0.1, "Meets Average", IF(BT7 > BU7, "Above Average", "Below Average"))), "Not Analyzed") -> Above Average | BW7: =max(AB7:AK7) -> 0.0612 | BX7: =IFERROR(VLOOKUP(L7, Benchmarks!$A$2:$D$15, 3, FALSE), "Not Analyzed") -> 0.05854 | BY7: =IFERROR(IF(OR(ISBLANK(BW7), ISBLANK(BX7)), "", IF(ABS(BW7-BX7)/BW7 <= 0.1, "Meets Average", IF(BW7 > BX7, "Above Average", "Below Average"))), "Not Analyzed") -> Meets Average | BZ7: ="Investment: " & A7 & " | Sponsor: " & B7 & " | Structure: " & C7 & " | Status: " & D7 & " | LTV: " & H7 & " | Availability: " & K7 & " | Location: " & N7 & " | Strategy: " & P7 & " | 721 Exchange Exit: " & Q7 & " | Estimated Hold: " & R7 & " | Cap Rate Equivalent: " & AN7 & " | Minimum Investment: " & AX7 -> Investment: BR Diversified Industrial Portfolio 7, DST | Sponsor: Bluerock | Structure: Delaware Statutory Trust (DST) | Status: Limited Availability | LTV: 0.00% LTV | Availability: 0.131554661028267 | Location: AL, FL, MO, VA | Strategy: Core-Plus | 721 Exchange Exit: Mandatory | Estimated Hold: 7-10 years | Cap Rate Equivalent: 0.075694 | Minimum Investment: 100000 | CA7: =A7&" ("&H7&")"&CHAR(10)&CHAR(10)&"BR Diversified Industrial Portfolio 7 is a debt-free DST holding five single-tenant industrial properties (~552,438 SF; ~11.7-year WALT) on absolute/triple-net leases to tenants including NVR, BlueLinx, Woodsman, and DESHAZO Automation. The assets were ac"&"quired ~$1.35M below appraised value in Sun Belt and industrial-corridor markets where in-place rents run ~25% below submarket. The thesis is diversified net-lease income with embedded mark-to-market upside and an optional Section 721 FMV rollover into a "&"Bluerock-affiliated operating partnership."&CHAR(10)&CHAR(10)&">> Download Offering Documents"&CHAR(10)&"https://www.baker1031.com/sponsors/bluerock" -> BR Diversified Industrial Portfolio 7, DST (0.00% LTV) BR Diversified Industrial Portfolio 7 is a debt-free DST holding five single-tenant industrial properties (~552,438 SF; ~11.7-year WALT) on absolute/triple-net leases to tenants including NVR, BlueLinx, Woodsman, and DESHAZO Automation. The assets were acquired ~$1.35M below appraised value in Sun Belt and industrial-corridor markets where in-place rents run ~25% below submarket. The thesis is diversified net-lease income with embedded mark-to-market upside and an optional Section 721 FMV rollover into a Bluerock-affiliated operating partnership. >> Download Offering Documents https://www.baker1031.com/sponsors/bluerock
A8: BREX Net Lease Industrial I DST | B8: Brookfield | C8: Delaware Statutory Trust (DST) | D8: Limited Availability | E8: 164055365 | F8: 80055365 | G8: 84000000 | H8: 51.20% LTV | I8: 250000 | J8: 46202 | K8: =(I8/F8) -> 0.0031228388 | L8: Industrial | M8: MA | N8: =IFERROR(__xludf.DUMMYFUNCTION("TEXTJOIN("", "", TRUE, SORT(TRANSPOSE(SPLIT(M8, "", ""))))"),"MA") -> MA | O8: 7.50% | P8: Core | Q8: Mandatory | R8: 7 years | S8: A single Class A, single-story industrial warehouse and distribution center, 221,999 SF (plus ~220,000 SF rooftop parking and 515 spaces; ~441,999 SF gross building area), constructed in 2022 at 34 Market Street, Everett MA, in a dense urban-infill submarket less than five miles north of downtown Boston. The Property is 100% triple-net-leased to Amazon.com Services LLC (Amazon; S&P/Moody's AA/A1) with ~12 years of remaining term (Master Lease / Amazon Lease base term to March 23, 2046), 2.5% annual rent increases, and three 5-year renewal options at 98% of fair market value. The Trust acquired the Property in March 2026 for $155.4M (appraised at $158.0M), financed with an $84.0M PNC Bank loan (7-year term, maturing March 2033, variable SOFR+1.45% hedged to an effective fixed 4.837%) at 51.20% loan-to-cost, and leases it to a Brookfield/BF REIT-affiliated Master Tenant. Exit options include an optional Section 721 FMV rollover into the Brookfield REIT (BF REIT) operating partnership for OP units or cash, with a ~7-year base-case hold to loan maturity. | T8: The Property is 100% leased to Amazon (S&P/Moody's AA/A1), among the strongest corporate credits in net lease, on an absolute-triple-net basis. The lessee is Amazon.com Services LLC, the operating subsidiary, and the building is a purpose-built last-mile distribution facility integral to Amazon's Boston-market logistics, supporting renewal probability; the renewal options reset at 98% of fair market value, a modest below-market mechanic. | U8: The lease is long-dated, with ~12 years of remaining term (base term to March 2046) and fixed 2.5% annual rent increases, providing durable, contractually escalating income well beyond the 7-year base-case hold and underpinning residual value at exit. | V8: The asset occupies an irreplaceable infill location less than five miles north of downtown Boston in a dense, supply-constrained submarket with limited developable industrial land, a high-barrier last-mile position that supports both in-place rent and exit pricing; 2022 Class A construction and expandable loading capacity add functional durability. | W8: The $84.0M PNC Bank loan (unaffiliated lender) at an effective fixed 4.837% generates positive leverage over the asset's in-place yield, lifting investor cash-on-cash to a 6.10% going-in and ramping to 7.96% by year 7, a materially higher current yield than unlevered net-lease DSTs. The interest-only structure maximizes distributions, but the full $84.0M balloons at the March 2033 maturity and the interest-rate hedge resets at the fifth anniversary. | X8: The offering is sponsored by Brookfield (via Brookfield Real Estate Income Trust and its operating partnership), carries a comparatively low 7.50% total load with no separate acquisition fee, and provides an optional Section 721 UPREIT into BF REIT's operating partnership, a tax-deferred path into a large, diversified institutional REIT platform. | Y8: A debt-advantaged single-tenant net-lease DST anchored by a AA/A1 Amazon credit on a long-dated (~12-year, to 2046) absolute-triple-net lease with 2.5% annual escalators, in an irreplaceable urban-infill location less than five miles from downtown Boston. The 2022 Class A construction, a $155.4M purchase below the $158.0M appraised value, and effective fixed 4.837% PNC financing produce strong positive leverage, lifting cash-on-cash from 6.10% to 7.96% over the seven-year hold (~7.01% average), well above unlevered net-lease peers. The total load is low at 7.50% with no acquisition fee, the lender is an unaffiliated third party (PNC), Year 1 DSCR is a healthy 2.33x, and the optional Section 721 FMV option offers a tax-deferred rollover into Brookfield's institutional REIT platform. | Z8: The trust is a single asset with a single tenant, so all cash flow and residual value depend on Amazon's performance and the ultimate renewal of one lease; the lessee is the operating subsidiary (Amazon.com Services LLC) and renewal options reset at 98% of fair market value. The $84.0M loan is interest-only with the full balance ballooning at the March 2033 maturity, and the rate is fixed only via a hedge that must be extended or replaced at the fifth anniversary, introducing hedge-rollover and cost risk plus a refinancing wall at year 7 that the sponsor's own forecast assumes is met by raising additional investor capital. The master tenant is a thinly capitalized Brookfield affiliate funded through the Operating Partnership, and sponsor, master tenant, and 721 counterparty roles are concentrated within the Brookfield family. The site carries identified environmental conditions (an Activity and Use Limitation with sub-slab vapor-mitigation over residual subsurface contamination) and roof and membrane warranties of varying duration (expiring 2032-2042), and the specialized last-mile configuration concentrates re-leasing risk if Amazon vacates. Any 721 consideration would be units in a non-listed Brookfield REIT vehicle, illiquid with sponsor-controlled NAV. | AA8: BREX Net Lease Industrial I is an institutionally sponsored, leveraged single-tenant net-lease DST whose return is driven by positive financial leverage on a top-tier credit rather than operational upside: an effective fixed 4.837% loan lifts a contractually 2.5%-escalating Amazon income stream to a 6.10%-to-7.96% cash-on-cash ramp (~7.01% average) over a seven-year hold. The investment case rests on the durability of one AA/A1 tenant in an irreplaceable Boston infill location on a lease running to 2046, well beyond the hold, which supports residual value, while the comparatively low 7.50% load and unaffiliated PNC financing distinguish it from higher-fee, affiliated-lender DSTs. The dominant risk-adjusted considerations are single-asset and single-tenant concentration, the interest-only balloon and hedge reset at the 2033 maturity (the base-case exit point, with the forecast assuming additional capital is raised if the loan is extended), and the form and timing of the optional Section 721 conversion into Brookfield's non-listed REIT operating partnership. Underwriting feasibility is high on in-place contractual income given Amazon's credit and the long lease; the credible variance lies in exit pricing, refinancing conditions at year 7, and eventual UPREIT terms rather than in-place cash flow. No tax-equivalent yield is disclosed in the offering materials. | AB8: 0.061 | AC8: 0.0638 | AD8: 0.0669 | AE8: 0.07 | AF8: 0.0731 | AG8: 0.0762 | AH8: 0.0796 | AI8: Sold | AJ8: Sold | AK8: Sold | AL8: 0.0701 | AM8: Not disclosed | AN8: =IFERROR((AB8 * ((1 - VALUE(SUBSTITUTE(H8, " LTV", ""))) + 0.02)) + (PMT(0.0535/12, 25*12, -VALUE(SUBSTITUTE(H8, " LTV", ""))) * 12) + (0.02/10) + (0.03/10) + 0.02, "N/A") -> 0.093169149 | AO8: PNC Bank, National Association | AP8: 4.84% (Fixed via hedge) | AQ8: 7 years | AR8: 7 years | AS8: N/A (interest-only) | AT8: 2.33x | AU8: 34 Market Street, Everett, MA | AV8: https://lh3.googleusercontent.com/d/1AgkmSZx56AVVBdJWPqlDqfYNMqSiQ0sq | AX8: 100000 | AY8: =IFERROR(__xludf.DUMMYFUNCTION("IF(ISBLANK(AV8), """", IF(REGEXMATCH(AV8, ""/file/d/""), ""https://lh3.googleusercontent.com/d/"" & REGEXEXTRACT(AV8, ""/d/([a-zA-Z0-9_-]+)""), AV8))"),"https://lh3.googleusercontent.com/d/1AgkmSZx56AVVBdJWPqlDqfYNMqSiQ0sq") -> https://lh3.googleusercontent.com/d/1AgkmSZx56AVVBdJWPqlDqfYNMqSiQ0sq | AZ8: =IF(AM8="Not Disclosed", AB8 + ((14545 / 100000) * (0.32 / (1 - 0.32))), AM8) -> 0.12944706 | BA8: =if(AM8="Not Disclosed", "Est. Tax-Adjusted Yield⁹", "Tax-Adjusted Yield") -> Est. Tax-Adjusted Yield⁹ | BB8: =if(AW8="", "Offering Documents Available By Request", "Download Offering Documents") -> Offering Documents Available By Request | BC8: brex-net-lease-industrial-i-dst | BD8: sponsors/brookfield | BE8: property-type/industrial | BF8: ="Learn More About "&B8 -> Learn More About Brookfield | BG8: ="Learn More About "&L8&" Properties" -> Learn More About Industrial Properties | BH8: {=IFERROR(XLOOKUP($B8, 'Sponsor Connection'!$A:$A, 'Sponsor Connection'!$B:$B), )} -> 1899 | BI8: {=IFERROR(XLOOKUP($B8, 'Sponsor Connection'!$A:$A, 'Sponsor Connection'!$D:$D), )} -> Brookfield is a global owner-operator of real assets with well over $1 trillion in AUM and roughly $31 billion in U.S. institutional real estate, and it reaches retail and exchange investors through the Brookfield Real Estate Income Trust. Its competitive advantage is operational rather than financial-engineering: deep in-house operating platforms across infrastructure, renewables and property allow it to drive value at the asset level. Backed by a perpetual-capital base and a 125-year institutional lineage, Brookfield brings owner-operator scale that few sponsors can replicate, with DST/non-traded vehicles a small slice of the whole. | BJ8: {=IF($B8="", "", LET(aum, IFERROR(XLOOKUP($B8, 'Sponsor Connection'!$A:$A, 'Sponsor Connection'!$C:$C), ""), IF(OR(aum="", aum=0), "Not Reported", aum)))} -> 1000000000000 | BK8: {=IF(ISBLANK($B8), "", LET(val, IFERROR(XLOOKUP($B8, 'Sponsor Connection'!$A:$A, 'Sponsor Connection'!$M:$M), ""), IF(OR(ISBLANK(val), val="", val=0), "Not Reported", val)))} -> Not Reported | BL8: {=IF(ISBLANK($B8), "", LET(val, IFERROR(XLOOKUP($B8, 'Sponsor Connection'!$A:$A, 'Sponsor Connection'!$N:$N), ""), IF(val="", "Not Reported", val)))} -> No Data | BM8: {=IF(ISBLANK($B8), "", LET(val, IFERROR(XLOOKUP($B8, 'Sponsor Connection'!$A:$A, 'Sponsor Connection'!$O:$O), ""), IF(val="", "Not Reported", val)))} -> No Data | BN8: {=IF(ISBLANK($B8), "", LET(val, IFERROR(XLOOKUP($B8, 'Sponsor Connection'!$A:$A, 'Sponsor Connection'!$P:$P), ""), IF(val="", "Not Reported", val)))} -> No Data | BO8: {=IF(ISBLANK($B8), "", LET(val, IFERROR(XLOOKUP($B8, 'Sponsor Connection'!$A:$A, 'Sponsor Connection'!$Q:$Q), ""), IF(val="", "Not Reported", val)))} -> No Data | BP8: {=IFERROR(XLOOKUP($B8, 'Sponsor Connection'!$A:$A, 'Sponsor Connection'!$L:$L), )} -> https://img.logo.dev/brookfield.com?token=pk_FIVsDKgZTvCedVXXtt2rEg&size=200&retina=true | BQ8: =AL8 -> 0.0701 | BR8: =IFERROR(VLOOKUP(L8, Benchmarks!$A$2:$D$15, 2, FALSE), "Not Analyzed") -> 0 | BS8: =IFERROR(IF(OR(ISBLANK(BQ8), ISBLANK(BR8)), "", IF(ABS(BQ8-BR8)/BQ8 <= 0.1, "Meets Average", IF(BQ8 > BR8, "Above Average", "Below Average"))), "Not Analyzed") -> Above Average | BT8: =iferror((BW8-AB8)/AB8, 0) -> 0.30491803 | BU8: =IFERROR(VLOOKUP(L8, Benchmarks!$A$2:$D$15, 4, FALSE), "Not Analyzed") -> 0.14414694 | BV8: =IFERROR(IF(OR(ISBLANK(BT8), ISBLANK(BU8)), "", IF(ABS(BT8-BU8)/BT8 <= 0.1, "Meets Average", IF(BT8 > BU8, "Above Average", "Below Average"))), "Not Analyzed") -> Above Average | BW8: =max(AB8:AK8) -> 0.0796 | BX8: =IFERROR(VLOOKUP(L8, Benchmarks!$A$2:$D$15, 3, FALSE), "Not Analyzed") -> 0.05854 | BY8: =IFERROR(IF(OR(ISBLANK(BW8), ISBLANK(BX8)), "", IF(ABS(BW8-BX8)/BW8 <= 0.1, "Meets Average", IF(BW8 > BX8, "Above Average", "Below Average"))), "Not Analyzed") -> Above Average | BZ8: ="Investment: " & A8 & " | Sponsor: " & B8 & " | Structure: " & C8 & " | Status: " & D8 & " | LTV: " & H8 & " | Availability: " & K8 & " | Location: " & N8 & " | Strategy: " & P8 & " | 721 Exchange Exit: " & Q8 & " | Estimated Hold: " & R8 & " | Cap Rate Equivalent: " & AN8 & " | Minimum Investment: " & AX8 -> Investment: BREX Net Lease Industrial I DST | Sponsor: Brookfield | Structure: Delaware Statutory Trust (DST) | Status: Limited Availability | LTV: 51.20% LTV | Availability: 0.00312283880037272 | Location: MA | Strategy: Core | 721 Exchange Exit: Mandatory | Estimated Hold: 7 years | Cap Rate Equivalent: 0.0931691494840462 | Minimum Investment: 100000 | CA8: =A8&" ("&H8&")"&CHAR(10)&CHAR(10)&"BREX Net Lease Industrial I is a single-asset DST holding a 2022-built, 221,999 SF Class A Amazon-leased warehouse in Everett, MA, an urban-infill submarket less than five miles north of downtown Boston. The property is 100% triple-net-leased to Amazon (A"&"A/A1) with ~12 years of term, 2.5% annual escalations, and three renewal options; it was acquired in March 2026 for $155.4M and financed with an $84.0M PNC loan (SOFR+1.45% hedged to 4.837% effective fixed, 51.20% LTC). The thesis is investment-grade cred"&"it-tenant net-lease income with an optional Section 721 FMV rollover into the Brookfield REIT operating partnership over a ~7-year hold to loan maturity."&CHAR(10)&CHAR(10)&">> Download Offering Documents"&CHAR(10)&"https://www.baker1031.com/sponsors/brookfield" -> BREX Net Lease Industrial I DST (51.20% LTV) BREX Net Lease Industrial I is a single-asset DST holding a 2022-built, 221,999 SF Class A Amazon-leased warehouse in Everett, MA, an urban-infill submarket less than five miles north of downtown Boston. The property is 100% triple-net-leased to Amazon (AA/A1) with ~12 years of term, 2.5% annual escalations, and three renewal options; it was acquired in March 2026 for $155.4M and financed with an $84.0M PNC loan (SOFR+1.45% hedged to 4.837% effective fixed, 51.20% LTC). The thesis is investment-grade credit-tenant net-lease income with an optional Section 721 FMV rollover into the Brookfield REIT operating partnership over a ~7-year hold to loan maturity. >> Download Offering Documents https://www.baker1031.com/sponsors/brookfield
A9: BR Parkview Multifamily, DST | B9: Bluerock | C9: Delaware Statutory Trust (DST) | D9: Available | E9: 78111498 | F9: 39486498 | G9: 38625000 | H9: 49.45% LTV | I9: 19000000 | J9: 46196 | K9: =(I9/F9) -> 0.48117714 | L9: Multifamily | M9: GA | N9: =IFERROR(__xludf.DUMMYFUNCTION("TEXTJOIN("", "", TRUE, SORT(TRANSPOSE(SPLIT(M9, "", ""))))"),"GA") -> GA | O9: 13.67% | P9: Core-Plus | Q9: Mandatory | R9: 7-10 years | S9: A newly-built (2023) Class A garden-style apartment community, the District at Parkview, at 5141 Stone Mountain Highway, Stone Mountain GA 30087, in Gwinnett County (Atlanta Metro), on 15.55 acres with 264 units across 10 buildings totaling 255,117 net rentable SF (one-, two-, and three-bedroom plans averaging 966 SF). The Trust acquired the Property for ~$66.6M (~$1.5M below appraised value), financed with a $38,625,000 KeyBank/Fannie Mae DUS first mortgage (49.45% loan-to-capitalization, 5.18% fixed, interest-only, maturing January 2036) and equity. The business plan is a stabilized newly-built hold with rental-rate-growth upside driven by marketing/SEO and revenue-management initiatives, below-market rents (~41% discount to homeownership), and a 2026-2027 tax-assessment freeze, with a nationally recognized third-party manager (sub-manager RPM Living). The Property is leased to an affiliated Master Tenant (BHM Parkview Leaseco, LLC) under a 10-year master lease paying Base Rent (debt service), Additional Rent (monthly distributions, ~4.30% going-in), and Supplemental Rent (annual performance distribution). Gwinnett County leads the Atlanta Metro in population growth with forecast housing demand ~5x the current construction pace through 2040, and the site sits in an A- (Niche) school district. Exit options include an optional Section 721 FMV rollover into a Bluerock-affiliated (Bluerock Homes Trust; NYSE American: BHM) operating partnership. | T9: The asset is newly-built 2023-vintage Class A product with top-of-market finishes and amenities (saltwater pool, 24/7 fitness center, club room, EV charging), acquired ~$1.5M below appraised value, providing a modest day-one equity cushion on new construction with minimal near-term capital needs. | U9: The Property sits in a supply-constrained, high-growth submarket: Gwinnett County ranks #1 in Atlanta-Metro population growth (27% over the prior decade), with forecast housing demand ~5x the current pace of new construction through 2040 and an A- (Niche) school district, supporting occupancy and rent durability. | V9: The rental-growth thesis is operational rather than physical: marketing/SEO and revenue-management initiatives, a ~41% discount to homeownership, and a 2026-2027 tax-assessment freeze are projected to lift cash-on-cash from 4.40% to 6.35% through performance-based Supplemental Rent, with no renovation program on the 2023-vintage asset. | W9: Financing is a $38.625M KeyBank loan under the Fannie Mae DUS program, fixed at 5.18% and interest-only for the full 10-year term (maturing January 2036) at 49.45% loan-to-capitalization, delivering a 1.91x Year 1 DSCR. The interest-only structure maximizes current distributions, but the full principal balloons at maturity with prepayment and defeasance provisions that constrain the exit. | X9: The master lease channels return through Base Rent (debt service), a flat ~4.30% Additional Rent monthly distribution, and Supplemental Rent (90% of revenue above a stated breakpoint), with an optional Section 721 FMV rollover into a Bluerock-affiliated (Bluerock Homes Trust; NYSE American: BHM) operating partnership as a tax-deferred exit; the affiliated master tenant retains the Base-Rent spread and 10% of Supplemental Rent. | Y9: A newly-built (2023) Class A multifamily asset in the supply-constrained, fast-growing Gwinnett County submarket of the Atlanta Metro, acquired ~$1.5M below appraised value at the in-place yield with minimal near-term capital needs and an A- school district supporting demand. Fannie Mae DUS fixed-rate financing at 5.18% provides a healthy 1.91x Year 1 DSCR with interest-only payments that maximize current distributions, and the master-lease Supplemental Rent gives investors performance-linked upside that ramps cash-on-cash from 4.40% to 6.35% (~5.04% average). Depreciation shelter is substantial (~86%-153% of cash flow sheltered; ~8.78% average tax-equivalent yield), a 2026-2027 tax-assessment freeze supports early NOI, and broad multifamily tailwinds (a national housing shortage, depressed new supply, and a widening homeownership affordability gap) reinforce the rental thesis. The optional Section 721 FMV option offers a tax-deferred rollover into a Bluerock-affiliated operating partnership. | Z9: The going-in distribution is modest at 4.30% (Base plus Additional Rent), and reaching the 6.35% forecast depends on revenue-management execution and organic rent growth clearing the Supplemental Rent breakpoint rather than fully contractual income. The day-one equity cushion is thin (acquired only ~$1.5M, ~2.2%, below appraised value) against 49.45% leverage, and the KeyBank loan is interest-only with the full $38.625M ballooning at the January 2036 maturity, with prepayment and defeasance provisions that constrain the 7-10 year exit window. The master tenant (BHM Parkview Leaseco) is a thinly capitalized Sponsor affiliate funded by an Operating Partnership demand note and retains the Base-Rent-to-breakpoint spread plus 10% of Supplemental Rent, partially misaligning upside. The Property is single-asset, single-market (Stone Mountain/Gwinnett), the rent-growth thesis is exposed to Atlanta-Metro multifamily supply and any submarket softening, and the tax-assessment freeze expires after 2027, after which property-tax expense may step up. Total load is high at ~13.67% of equity (including a 4.22% acquisition fee) plus a disposition fee, and the 721 consideration would be units in a Bluerock-affiliated operating partnership, an illiquid, sponsor-controlled vehicle. | AA9: BR Parkview Multifamily is a leveraged, newly-built Class A multifamily DST whose return profile mirrors Bluerock's other master-lease offerings: a modest ~4.30% contractual Additional Rent floor plus performance-linked Supplemental Rent that, if rent growth materializes, lifts cash-on-cash to ~6.35% and averages ~5.04% over a 7-10 year hold. Unlike a physical value-add play (e.g., the sponsor's Churchill Downs), the thesis here rests on operational and market-driven upside - marketing, SEO, revenue management, below-market rents, and a tax-assessment freeze - applied to a stabilized 2023-vintage asset in supply-constrained Gwinnett County, which is why it reads as core-plus rather than value-add. The Fannie Mae DUS fixed-rate interest-only loan provides solid 1.91x coverage and front-loads distributions but builds no equity and balloons in 2036, so terminal value hinges on NOI growth and exit pricing against a thin day-one basis discount. The after-tax profile is a meaningful draw (~8.78% average tax-equivalent yield on high depreciation shelter, ~86%-153% of cash flow). The dominant sensitivities are submarket rent growth and execution of the revenue-management plan, the post-2027 step-up in property taxes once the freeze expires, Atlanta-Metro multifamily supply, and refinancing or selling the balloon within the hold window; the optional Section 721 FMV conversion into a Bluerock-affiliated (Bluerock Homes Trust, NYSE American: BHM) operating partnership offers a tax-deferred alternative exit into an illiquid, sponsor-controlled vehicle. | AB9: 0.044 | AC9: 0.0442 | AD9: 0.0443 | AE9: 0.0443 | AF9: 0.0469 | AG9: 0.0496 | AH9: 0.0525 | AI9: 0.0557 | AJ9: 0.0589 | AK9: 0.0635 | AL9: 0.0504 | AM9: 0.0878 | AN9: =IFERROR((AB9 * ((1 - VALUE(SUBSTITUTE(H9, " LTV", ""))) + 0.02)) + (PMT(0.0535/12, 25*12, -VALUE(SUBSTITUTE(H9, " LTV", ""))) * 12) + (0.02/10) + (0.03/10) + 0.02, "N/A") -> 0.084032309 | AO9: KeyBank National Association | AP9: 5.18% (Fixed) | AQ9: 10 years | AR9: 10 years | AS9: N/A (interest-only) | AT9: 1.91x | AU9: 5141 Stone Mountain Highway, Stone Mountain, GA 30087 | AV9: https://lh3.googleusercontent.com/d/1xO96McQnNjSgKdvqpX8IjOJbNwbyVxL1 | AX9: 100000 | AY9: =IFERROR(__xludf.DUMMYFUNCTION("IF(ISBLANK(AV9), """", IF(REGEXMATCH(AV9, ""/file/d/""), ""https://lh3.googleusercontent.com/d/"" & REGEXEXTRACT(AV9, ""/d/([a-zA-Z0-9_-]+)""), AV9))"),"https://lh3.googleusercontent.com/d/1xO96McQnNjSgKdvqpX8IjOJbNwbyVxL1") -> https://lh3.googleusercontent.com/d/1xO96McQnNjSgKdvqpX8IjOJbNwbyVxL1 | AZ9: =IF(AM9="Not Disclosed", AB9 + ((14545 / 100000) * (0.32 / (1 - 0.32))), AM9) -> 0.0878 | BA9: =if(AM9="Not Disclosed", "Est. Tax-Adjusted Yield⁹", "Tax-Adjusted Yield") -> Tax-Adjusted Yield | BB9: =if(AW9="", "Offering Documents Available By Request", "Download Offering Documents") -> Offering Documents Available By Request | BC9: br-parkview-multifamily-dst | BD9: sponsors/bluerock | BE9: property-type/multifamily | BF9: ="Learn More About "&B9 -> Learn More About Bluerock | BG9: ="Learn More About "&L9&" Properties" -> Learn More About Multifamily Properties | BH9: {=IFERROR(XLOOKUP($B9, 'Sponsor Connection'!$A:$A, 'Sponsor Connection'!$B:$B), )} -> 2002 | BI9: {=IFERROR(XLOOKUP($B9, 'Sponsor Connection'!$A:$A, 'Sponsor Connection'!$D:$D), )} -> Bluerock has sponsored syndicated 1031 exchanges for more than eighteen years, and its Bluerock Value Exchange (BVEX) arm packages multifamily, industrial and other core sectors into what it markets as 'Premier Exchange Properties.' Backed by a broader Bluerock platform of roughly $19 billion that also spans interval funds, the firm pairs institutional acquisition capability with a long DST track record across multiple cycles. Its national footprint and sector breadth position it as a diversified mid-to-large sponsor rather than a single-asset specialist. | BJ9: {=IF($B9="", "", LET(aum, IFERROR(XLOOKUP($B9, 'Sponsor Connection'!$A:$A, 'Sponsor Connection'!$C:$C), ""), IF(OR(aum="", aum=0), "Not Reported", aum)))} -> 19000000000 | BK9: {=IF(ISBLANK($B9), "", LET(val, IFERROR(XLOOKUP($B9, 'Sponsor Connection'!$A:$A, 'Sponsor Connection'!$M:$M), ""), IF(OR(ISBLANK(val), val="", val=0), "Not Reported", val)))} -> 97 | BL9: {=IF(ISBLANK($B9), "", LET(val, IFERROR(XLOOKUP($B9, 'Sponsor Connection'!$A:$A, 'Sponsor Connection'!$N:$N), ""), IF(val="", "Not Reported", val)))} -> 0.21387835 | BM9: {=IF(ISBLANK($B9), "", LET(val, IFERROR(XLOOKUP($B9, 'Sponsor Connection'!$A:$A, 'Sponsor Connection'!$O:$O), ""), IF(val="", "Not Reported", val)))} -> 1.7736082 | BN9: {=IF(ISBLANK($B9), "", LET(val, IFERROR(XLOOKUP($B9, 'Sponsor Connection'!$A:$A, 'Sponsor Connection'!$P:$P), ""), IF(val="", "Not Reported", val)))} -> 4.0041237 | BO9: {=IF(ISBLANK($B9), "", LET(val, IFERROR(XLOOKUP($B9, 'Sponsor Connection'!$A:$A, 'Sponsor Connection'!$Q:$Q), ""), IF(val="", "Not Reported", val)))} -> 0.93814433 | BP9: {=IFERROR(XLOOKUP($B9, 'Sponsor Connection'!$A:$A, 'Sponsor Connection'!$L:$L), )} -> https://img.logo.dev/bluerockexchange.com?token=pk_FIVsDKgZTvCedVXXtt2rEg&size=200&retina=true | BQ9: =AL9 -> 0.0504 | BR9: =IFERROR(VLOOKUP(L9, Benchmarks!$A$2:$D$15, 2, FALSE), "Not Analyzed") -> 0.050338 | BS9: =IFERROR(IF(OR(ISBLANK(BQ9), ISBLANK(BR9)), "", IF(ABS(BQ9-BR9)/BQ9 <= 0.1, "Meets Average", IF(BQ9 > BR9, "Above Average", "Below Average"))), "Not Analyzed") -> Meets Average | BT9: =iferror((BW9-AB9)/AB9, 0) -> 0.44318182 | BU9: =IFERROR(VLOOKUP(L9, Benchmarks!$A$2:$D$15, 4, FALSE), "Not Analyzed") -> 0.24736349 | BV9: =IFERROR(IF(OR(ISBLANK(BT9), ISBLANK(BU9)), "", IF(ABS(BT9-BU9)/BT9 <= 0.1, "Meets Average", IF(BT9 > BU9, "Above Average", "Below Average"))), "Not Analyzed") -> Above Average | BW9: =max(AB9:AK9) -> 0.0635 | BX9: =IFERROR(VLOOKUP(L9, Benchmarks!$A$2:$D$15, 3, FALSE), "Not Analyzed") -> 0.052895455 | BY9: =IFERROR(IF(OR(ISBLANK(BW9), ISBLANK(BX9)), "", IF(ABS(BW9-BX9)/BW9 <= 0.1, "Meets Average", IF(BW9 > BX9, "Above Average", "Below Average"))), "Not Analyzed") -> Above Average | BZ9: ="Investment: " & A9 & " | Sponsor: " & B9 & " | Structure: " & C9 & " | Status: " & D9 & " | LTV: " & H9 & " | Availability: " & K9 & " | Location: " & N9 & " | Strategy: " & P9 & " | 721 Exchange Exit: " & Q9 & " | Estimated Hold: " & R9 & " | Cap Rate Equivalent: " & AN9 & " | Minimum Investment: " & AX9 -> Investment: BR Parkview Multifamily, DST | Sponsor: Bluerock | Structure: Delaware Statutory Trust (DST) | Status: Available | LTV: 49.45% LTV | Availability: 0.481177135536304 | Location: GA | Strategy: Core-Plus | 721 Exchange Exit: Mandatory | Estimated Hold: 7-10 years | Cap Rate Equivalent: 0.0840323094137907 | Minimum Investment: 100000 | CA9: =A9&" ("&H9&")"&CHAR(10)&CHAR(10)&"BR Parkview Multifamily is a newly built (2023) 264-unit Class A garden community in Gwinnett County (Stone Mountain, GA), acquired ~$1.5M below appraised value and financed with a $38.6M KeyBank/Fannie Mae DUS loan (5.18% fixed, interest-only, 49.45% LTC"&"). The stabilized-hold business plan pursues rental-rate growth via revenue management and below-market rents (~41% discount to homeownership), supported by a 2026-2027 tax-assessment freeze and RPM Living management. Gwinnett County leads Atlanta-metro p"&"opulation growth with forecast housing demand ~5x current construction pace, and the offering carries an optional Section 721 FMV rollover into a Bluerock-affiliated operating partnership."&CHAR(10)&CHAR(10)&">> Download Offering Documents"&CHAR(10)&"https://www.baker1031.com/sponsors/bluerock" -> BR Parkview Multifamily, DST (49.45% LTV) BR Parkview Multifamily is a newly built (2023) 264-unit Class A garden community in Gwinnett County (Stone Mountain, GA), acquired ~$1.5M below appraised value and financed with a $38.6M KeyBank/Fannie Mae DUS loan (5.18% fixed, interest-only, 49.45% LTC). The stabilized-hold business plan pursues rental-rate growth via revenue management and below-market rents (~41% discount to homeownership), supported by a 2026-2027 tax-assessment freeze and RPM Living management. Gwinnett County leads Atlanta-metro population growth with forecast housing demand ~5x current construction pace, and the offering carries an optional Section 721 FMV rollover into a Bluerock-affiliated operating partnership. >> Download Offering Documents https://www.baker1031.com/sponsors/bluerock
A10: Colorado Growth 1 - Holly Ridge DST | B10: Walton Global Holdings | C10: Delaware Statutory Trust (DST) | D10: Limited Availability | E10: 6469972 | F10: 6469972 | G10: 0 | H10: 0.00% LTV | I10: 1800000 | J10: 46196 | K10: =(I10/F10) -> 0.27820831 | L10: Land | M10: CO | N10: =IFERROR(__xludf.DUMMYFUNCTION("TEXTJOIN("", "", TRUE, SORT(TRANSPOSE(SPLIT(M10, "", ""))))"),"CO") -> CO | O10: 14.98% | P10: Opportunistic | Q10: None | R10: 4-5 years | S10: A Walton Global Holdings-sponsored land-banking offering to acquire ~70.5 acres of undeveloped agricultural land at the northwest corner of State Highway 7 and Holly Street in unincorporated Adams County, Colorado, in the path of growth toward the City of Thornton in the north Denver metro. The Trust acquires the land all-cash/free-and-clear for ~$4,500,000 within a $6,469,972 all-equity raise (inclusive of syndication costs, a sponsor acquisition fee, a prepaid asset-management fee, trust expenses, and reserves). The Property is not presently zoned or entitled; the business plan is to hold the raw land for appreciation and, after a minimum 12-month hold post-final-closing, market it for sale to a national homebuilder or developer via a single-buyer staged sale (up to two installments) over an anticipated ~4-5 year hold. The Trust generates no rental revenue and makes no distributions to investors until the land is sold - the entire return is appreciation realized on disposition. There is no debt, no master lease, no current income, and no 721/UPREIT exit; the bare legal title is held by the Administrative Trustee (Holly Ridge Keeper, LLC) and the Dealer Manager is ARKap Markets, LLC. Adams County/north Denver is a high-growth corridor, but the investment carries entitlement, zoning, wetlands, and absorption risk, with no assurance the exit is achieved. | T10: This is a pure land-banking appreciation play: the Trust acquires raw agricultural land for ~$4.5M with the sole objective of realizing appreciation on a future sale to a homebuilder or developer. There is no current income, so the return is binary on the eventual disposition price and timing rather than on contractual cash flow. | U10: The ~70.5-acre parcel sits in a path-of-growth location at SH-7 and Holly Street in unincorporated Adams County, in the growth corridor of the City of Thornton in the north Denver metro, a market with population and housing demand that underpins the land-appreciation thesis. | V10: The land is acquired debt-free and all-cash with no mortgage, eliminating refinancing, maturity, and foreclosure risk and removing carry-cost leverage. The offsetting feature is that, with no income, reserves and a prepaid asset-management fee are funded upfront from offering proceeds to cover a multi-year hold. | W10: Entitlement and zoning are unresolved: the Property is not presently zoned or entitled for development, future entitlements would follow City of Thornton zoning upon annexation (per the Otten Johnson entitlement memo), and the National Wetlands Inventory flags potential wetlands. Both are gating items to a developer sale and represent the central execution risk. | X10: The exit is a staged sale over an anticipated ~4-5 year hold: after a minimum 12-month hold the Trust intends a single-buyer staged sale of up to two installments. If no third-party developer is willing or able to buy on the intended terms, the land may be sold on commercially reasonable terms or to an affiliate of the Administrative Trustee, a conflict-of-interest and pricing risk. | Y10: A debt-free, all-cash land-banking DST offering exposure to ~70.5 acres of undeveloped land in the high-growth north Denver/Adams County corridor (path of growth toward Thornton), sponsored by Walton Global Holdings, an established land-investment platform. The unlevered structure removes refinancing, maturity, and foreclosure risk, and the comparatively low ~$4.5M land basis against a growing residential market underpins the appreciation thesis. The offering provides 1031-eligible like-kind real property with a defined business plan (hold, then staged sale to a homebuilder/developer over ~4-5 years) and a clean capital structure with reserves funded upfront to carry the hold. | Z10: The Property is raw, unentitled agricultural land that generates no income and pays no distributions until sale, so the entire return depends on achieving a future disposition at an appreciated price, with no current yield to cushion a delayed or failed exit. Entitlement and zoning are unresolved (the land is not presently zoned; entitlements depend on annexation to the City of Thornton), and the National Wetlands Inventory flags potential wetlands, either of which could impair developability and the sale. The exit is concentrated in a single anticipated buyer type over a staged sale, with a fallback permitting sale to an affiliate of the Administrative Trustee, a conflict and pricing risk. The offering is small ($6.47M) and single-asset, the load is high (~14.98% of equity, before a further 5.56% prepaid asset-management fee and a disposition fee), and only ~69.55% of proceeds funds the land basis. Hold duration is uncertain (anticipated 4-5 years, but the asset-management agreement runs 10 years), exposing investors to absorption timing and Denver land-market cyclicality. | AA10: Colorado Growth 1 - Holly Ridge is structurally unlike an income-producing net-lease or multifamily DST: it is a speculative, unlevered land-banking vehicle whose return is entirely appreciation realized on a future sale of ~70.5 acres of unentitled Denver-metro land, with no rental income, no distributions during the hold, no master lease, and no 721/UPREIT exit. The thesis rests on north Adams County's growth trajectory and the land's eventual entitlement and absorption by a homebuilder/developer, so the dominant sensitivities are entitlement/zoning success (annexation to Thornton, wetlands resolution), the depth of homebuilder lot demand and pricing at exit, and the timing of the staged sale within the anticipated 4-5 year hold. The debt-free structure removes financing risk but offers no income to offset a delayed exit, and the upfront load (~14.98%) plus a prepaid 5.56% asset-management fee and reserves mean a meaningful portion of equity is consumed by fees and carry rather than land basis. Underwriting feasibility cannot be assessed on contractual cash flow as with the other ledger holdings; it is a binary, appreciation-only, opportunistic bet on Denver-corridor land values and entitlement execution, with an affiliate-sale fallback that warrants scrutiny. This is the first non-income, opportunistic land position in the portfolio and is not comparable to the income-distributing DSTs on the sheet. | AB10: 0 | AC10: 0 | AD10: 0 | AE10: 0 | AF10: 0 | AG10: Sold | AH10: Sold | AI10: Sold | AJ10: Sold | AK10: Sold | AL10: N/A (no income) | AM10: N/A (no income) | AN10: =IFERROR((AB10 * ((1 - VALUE(SUBSTITUTE(H10, " LTV", ""))) + 0.02)) + (PMT(0.0535/12, 25*12, -VALUE(SUBSTITUTE(H10, " LTV", ""))) * 12) + (0.02/10) + (0.03/10) + 0.02, "N/A") -> 0.025 | AO10: None (debt-free) | AP10: N/A (no debt) | AQ10: N/A (no debt) | AR10: N/A (no debt) | AS10: N/A (no debt) | AT10: N/A - no debt service | AU10: NWC State Highway 7 & Holly Street, Adams County, CO | AV10: https://drive.google.com/file/d/1m482JRkcE8IzqWa604lKtvUl4fTBH45F/view?usp=sharing | AX10: 100000 | AY10: =IFERROR(__xludf.DUMMYFUNCTION("IF(ISBLANK(AV10), """", IF(REGEXMATCH(AV10, ""/file/d/""), ""https://lh3.googleusercontent.com/d/"" & REGEXEXTRACT(AV10, ""/d/([a-zA-Z0-9_-]+)""), AV10))"),"https://lh3.googleusercontent.com/d/1m482JRkcE8IzqWa604lKtvUl4fTBH45F") -> https://lh3.googleusercontent.com/d/1m482JRkcE8IzqWa604lKtvUl4fTBH45F | AZ10: =IF(AM10="Not Disclosed", AB10 + ((14545 / 100000) * (0.32 / (1 - 0.32))), AM10) -> N/A (no income) | BA10: =if(AM10="Not Disclosed", "Est. Tax-Adjusted Yield⁹", "Tax-Adjusted Yield") -> Tax-Adjusted Yield | BB10: =if(AW10="", "Offering Documents Available By Request", "Download Offering Documents") -> Offering Documents Available By Request | BC10: colorado-growth-1-holly-ridge-dst | BD10: sponsors/walton-global-holdings | BE10: property-type/land | BF10: ="Learn More About "&B10 -> Learn More About Walton Global Holdings | BG10: ="Learn More About "&L10&" Properties" -> Learn More About Land Properties | BH10: {=IFERROR(XLOOKUP($B10, 'Sponsor Connection'!$A:$A, 'Sponsor Connection'!$B:$B), )} -> 1979 | BI10: {=IFERROR(XLOOKUP($B10, 'Sponsor Connection'!$A:$A, 'Sponsor Connection'!$D:$D), )} -> Walton Global Holdings is a land asset manager with a 45-plus-year history, managing $3.35 billion and specializing in pre-development land that it supplies to U.S. homebuilders—a genuinely distinctive 1031 asset class. Controlling more than 85,000 acres across 170-plus master-planned communities and serving some 88,000 global investors across 91 countries, Walton has institutionalized land banking through its Builder Land Finance structure, recently bolstered by a 2025 GoldenTree co-investment. The land-to-homebuilder model offers diversification from income real estate but carries entitlement and absorption risk distinct from cash-flowing assets. | BJ10: {=IF($B10="", "", LET(aum, IFERROR(XLOOKUP($B10, 'Sponsor Connection'!$A:$A, 'Sponsor Connection'!$C:$C), ""), IF(OR(aum="", aum=0), "Not Reported", aum)))} -> 3350000000 | BK10: {=IF(ISBLANK($B10), "", LET(val, IFERROR(XLOOKUP($B10, 'Sponsor Connection'!$A:$A, 'Sponsor Connection'!$M:$M), ""), IF(OR(ISBLANK(val), val="", val=0), "Not Reported", val)))} -> 68 | BL10: {=IF(ISBLANK($B10), "", LET(val, IFERROR(XLOOKUP($B10, 'Sponsor Connection'!$A:$A, 'Sponsor Connection'!$N:$N), ""), IF(val="", "Not Reported", val)))} -> 0.082045588 | BM10: {=IF(ISBLANK($B10), "", LET(val, IFERROR(XLOOKUP($B10, 'Sponsor Connection'!$A:$A, 'Sponsor Connection'!$O:$O), ""), IF(val="", "Not Reported", val)))} -> 1.3453488 | BN10: {=IF(ISBLANK($B10), "", LET(val, IFERROR(XLOOKUP($B10, 'Sponsor Connection'!$A:$A, 'Sponsor Connection'!$P:$P), ""), IF(val="", "Not Reported", val)))} -> 7.165 | BO10: {=IF(ISBLANK($B10), "", LET(val, IFERROR(XLOOKUP($B10, 'Sponsor Connection'!$A:$A, 'Sponsor Connection'!$Q:$Q), ""), IF(val="", "Not Reported", val)))} -> 0.75 | BP10: {=IFERROR(XLOOKUP($B10, 'Sponsor Connection'!$A:$A, 'Sponsor Connection'!$L:$L), )} -> https://img.logo.dev/walton.com?token=pk_FIVsDKgZTvCedVXXtt2rEg&size=200&retina=true | BQ10: =AL10 -> N/A (no income) | BR10: =IFERROR(VLOOKUP(L10, Benchmarks!$A$2:$D$15, 2, FALSE), "Not Analyzed") | BS10: =IFERROR(IF(OR(ISBLANK(BQ10), ISBLANK(BR10)), "", IF(ABS(BQ10-BR10)/BQ10 <= 0.1, "Meets Average", IF(BQ10 > BR10, "Above Average", "Below Average"))), "Not Analyzed") -> Not Analyzed | BT10: =iferror((BW10-AB10)/AB10, 0) -> 0 | BU10: =IFERROR(VLOOKUP(L10, Benchmarks!$A$2:$D$15, 4, FALSE), "Not Analyzed") -> 0 | BV10: =IFERROR(IF(OR(ISBLANK(BT10), ISBLANK(BU10)), "", IF(ABS(BT10-BU10)/BT10 <= 0.1, "Meets Average", IF(BT10 > BU10, "Above Average", "Below Average"))), "Not Analyzed") -> Not Analyzed | BW10: =max(AB10:AK10) -> 0 | BX10: =IFERROR(VLOOKUP(L10, Benchmarks!$A$2:$D$15, 3, FALSE), "Not Analyzed") -> 0 | BY10: =IFERROR(IF(OR(ISBLANK(BW10), ISBLANK(BX10)), "", IF(ABS(BW10-BX10)/BW10 <= 0.1, "Meets Average", IF(BW10 > BX10, "Above Average", "Below Average"))), "Not Analyzed") -> Not Analyzed | BZ10: ="Investment: " & A10 & " | Sponsor: " & B10 & " | Structure: " & C10 & " | Status: " & D10 & " | LTV: " & H10 & " | Availability: " & K10 & " | Location: " & N10 & " | Strategy: " & P10 & " | 721 Exchange Exit: " & Q10 & " | Estimated Hold: " & R10 & " | Cap Rate Equivalent: " & AN10 & " | Minimum Investment: " & AX10 -> Investment: Colorado Growth 1 - Holly Ridge DST | Sponsor: Walton Global Holdings | Structure: Delaware Statutory Trust (DST) | Status: Limited Availability | LTV: 0.00% LTV | Availability: 0.278208313729951 | Location: CO | Strategy: Opportunistic | 721 Exchange Exit: None | Estimated Hold: 4-5 years | Cap Rate Equivalent: 0.025 | Minimum Investment: 100000 | CA10: =A10&" ("&H10&")"&CHAR(10)&CHAR(10)&"Colorado Growth 1 is a Walton Global land-banking offering acquiring ~70.5 acres of undeveloped agricultural land in unincorporated Adams County, in the north-Denver path of growth toward Thornton, all-cash within a $6.47M all-equity raise. The land is un"&"zoned and unentitled; the business plan holds for appreciation and, after a minimum 12-month hold, markets it to a national homebuilder via a single-buyer staged sale over a ~4-5 year hold. The vehicle generates no current income, makes no interim distrib"&"utions, and carries no debt, master lease, or 721 exit, with the entire return realized on disposition and subject to entitlement, zoning, wetlands, and absorption risk."&CHAR(10)&CHAR(10)&">> Download Offering Documents"&CHAR(10)&"https://www.baker1031.com/sponsors/walton-global-holdings" -> Colorado Growth 1 - Holly Ridge DST (0.00% LTV) Colorado Growth 1 is a Walton Global land-banking offering acquiring ~70.5 acres of undeveloped agricultural land in unincorporated Adams County, in the north-Denver path of growth toward Thornton, all-cash within a $6.47M all-equity raise. The land is unzoned and unentitled; the business plan holds for appreciation and, after a minimum 12-month hold, markets it to a national homebuilder via a single-buyer staged sale over a ~4-5 year hold. The vehicle generates no current income, makes no interim distributions, and carries no debt, master lease, or 721 exit, with the entire return realized on disposition and subject to entitlement, zoning, wetlands, and absorption risk. >> Download Offering Documents https://www.baker1031.com/sponsors/walton-global-holdings
A11: ExchangeRight Net-Leased All-Cash 19 DST | B11: ExchangeRight | C11: Delaware Statutory Trust (DST) | D11: Closed | E11: 26950000 | F11: 26950000 | G11: 0 | H11: 0.00% LTV | I11: 68202 | J11: 46204 | K11: =(I11/F11) -> 0.0025306865 | L11: Net Lease | M11: WA, AL, IL | N11: =IFERROR(__xludf.DUMMYFUNCTION("TEXTJOIN("", "", TRUE, SORT(TRANSPOSE(SPLIT(M11, "", ""))))"),"AL, IL, WA") -> AL, IL, WA | O11: 9.46% | P11: Core | Q11: Optional | R11: 10 years | S11: A debt-free portfolio of three single-tenant, necessity-based net-leased retail properties (122,149 SF total; 10.7-year WALT) acquired in early 2026 and held free and clear, sponsored by ExchangeRight Real Estate, LLC. The portfolio comprises a ~68,459 SF Fred Meyer (a wholly-owned Kroger Co. subsidiary; Kroger S&P BBB) on ~11.65 acres in Shelton WA on a double-net (NN) lease (~58% of NOI; grocery plus fuel), a 50,354 SF Hobby Lobby in Scottsboro AL leased through 2040 (~29% of NOI; three 5-year options), and a 3,336 SF Verizon Wireless (Cellular Sales of Illinois, LLC) in Roscoe IL leased through 2035 (~13% of NOI; two 5-year options). Going-in cash flow is 5.15%, escalating to 5.49% by year 10 (~5.26% average) on contractual rent. The all-equity structure removes refinancing and maturity risk. The exit is ExchangeRight's REIT aggregation strategy: the Essential Income REIT is targeted to acquire the DST interests within ~10 years via an optional Section 721 exchange, with cash-out and combination elections available. The $26,950,000 offering is 100 Class 1 interests at $269,500 ($100,000 minimum equity). | T11: The three-property portfolio is held free and clear with no mortgage, eliminating refinancing, maturity, rate-cap, and foreclosure risk and the equal-or-greater-debt 1031 requirement. Tenants operate in historically recession-resilient, necessity-based retail (grocery, discount craft retail, wireless), supporting income durability through cycles. | U11: Fred Meyer (a wholly-owned Kroger subsidiary; Kroger Co. S&P BBB) anchors ~58% of NOI on a grocery-plus-fuel format, providing an investment-grade credit backbone. The same fact concentrates the majority of income in a single tenant on a double-net (NN, not absolute-NNN) lease that leaves the trust with certain structural and capital responsibilities. | V11: A 10.7-year weighted-average lease term with staggered expirations (Verizon 2035, Hobby Lobby 2040) plus renewal options across all three tenants underpins durable contractual income across the targeted hold. Income growth is modest and contractual, lifting cash-on-cash only from 5.15% to 5.49% over ten years. | W11: The offering is engineered as a feeder into ExchangeRight's Essential Income REIT, which targets acquiring the DST interests within ~10 years. Investors may elect a tax-deferred Section 721 exchange into the REIT operating partnership, a cash-out, or a combination, providing a defined (if sponsor- and REIT-capital-dependent) exit path. | X11: Total upfront load is comparatively low at ~9.46% of equity (7.23% selling/offering plus a 1.98% acquisition fee and a 0.25% reallowance), modest for an all-cash DST, with ~1.48% of proceeds funded into reserves for operations and asset management. | Y11: A debt-free, three-property single-tenant net-lease portfolio of necessity-based retail (Fred Meyer/Kroger grocery, Hobby Lobby, Verizon) with a 10.7-year WALT and a 5.15% going-in cash flow escalating to 5.49% (~5.26% average), sponsored by ExchangeRight, a scaled net-lease DST/REIT platform (1,400+ properties across 47 states at the platform level). The unlevered structure removes all refinancing, maturity, and foreclosure risk and the equal-or-greater-debt 1031 requirement, and the largest tenant (Fred Meyer) is backed by investment-grade Kroger (S&P BBB) at ~58% of NOI. The total load is comparatively low at ~9.46%, and the offering provides a defined exit through ExchangeRight's REIT aggregation strategy with an optional Section 721 tax-deferred rollover into the Essential Income REIT plus cash-out and combination elections. | Z11: Income is concentrated in three assets and effectively two credits, with Fred Meyer/Kroger alone at ~58% of NOI, so a single vacancy or non-renewal is materially binary to portfolio cash flow; the Fred Meyer lease is double-net (NN), not absolute-triple-net, leaving the trust with certain structural, roof, and parking-lot capital responsibilities funded only from a modest ~1.48% reserve. The Verizon lease is the shortest (2035 expiry) on the smallest, most specialized 3,336 SF unit, creating earlier rollover exposure, and the lessee is a Verizon dealer (Cellular Sales of Illinois) rather than Verizon Communications itself. Going-in cash flow is modest at 5.15% with only ~0.34% of cumulative escalation over ten years (largely flat, contractual income with no value-add or operational upside), and the absence of leverage caps levered return. The targeted REIT-aggregation/721 exit is not guaranteed and depends on the ExchangeRight Essential Income REIT's capital availability and willingness to acquire the interests; any 721 consideration would be units in a non-traded, sponsor-controlled REIT operating partnership with sponsor-set NAV and limited liquidity. The portfolio is small ($26.95M), and the Sponsor's affiliated equity-financing/bridge arrangement is repaid from offering proceeds. | AA11: ExchangeRight Net-Leased All-Cash 19 is a debt-free, income-oriented core net-lease vehicle whose return is almost entirely contractual: a 5.15%-to-5.49% cash-on-cash schedule (~5.26% average) sourced from three single-tenant necessity-retail leases with a 10.7-year WALT, with no leverage and no value-add component. The credit profile is anchored by investment-grade Kroger (via Fred Meyer, ~58% of NOI) but is concentrated in two effective credits across three assets, and the Fred Meyer NN lease plus a short-dated, specialized Verizon unit are the principal asset-level vulnerabilities. The defining structural feature is ExchangeRight's REIT aggregation model: the offering is designed as a feeder whose likely terminal path is a Section 721 roll-up into the non-traded Essential Income REIT rather than a third-party sale - attractive for tax-deferral continuity and stable income, but ceding control, liquidity, and valuation transparency to a sponsor-managed NAV REIT and contingent on that REIT's capital. The debt-free design is genuinely defensive in a higher-for-longer environment and the ~9.46% load is comparatively low for an all-cash DST, but the modest, largely flat going-in yield and the absence of leverage cap total return, leaving terminal value and tenant retention at the 2035/2040 expirations as the dominant sensitivities. No tax-equivalent yield is disclosed. | AB11: 0.0515 | AC11: 0.0515 | AD11: 0.0515 | AE11: 0.0515 | AF11: 0.0518 | AG11: 0.0531 | AH11: 0.0531 | AI11: 0.0531 | AJ11: 0.0535 | AK11: 0.0549 | AL11: 0.0526 | AM11: Not disclosed | AN11: =IFERROR((AB11 * ((1 - VALUE(SUBSTITUTE(H11, " LTV", ""))) + 0.02)) + (PMT(0.0535/12, 25*12, -VALUE(SUBSTITUTE(H11, " LTV", ""))) * 12) + (0.02/10) + (0.03/10) + 0.02, "N/A") -> 0.07753 | AO11: None (debt-free) | AP11: N/A (no debt) | AQ11: N/A (no debt) | AR11: N/A (no debt) | AS11: N/A (no debt) | AT11: N/A - no debt service | AU11: 301 E Wallace Kneeland Blvd, Shelton, WA | AV11: https://drive.google.com/file/d/1yzlNMlrLLF0QvOpMI1WRQfL2c1xUiGG2/view?usp=sharing | AX11: 100000 | AY11: =IFERROR(__xludf.DUMMYFUNCTION("IF(ISBLANK(AV11), """", IF(REGEXMATCH(AV11, ""/file/d/""), ""https://lh3.googleusercontent.com/d/"" & REGEXEXTRACT(AV11, ""/d/([a-zA-Z0-9_-]+)""), AV11))"),"https://lh3.googleusercontent.com/d/1yzlNMlrLLF0QvOpMI1WRQfL2c1xUiGG2") -> https://lh3.googleusercontent.com/d/1yzlNMlrLLF0QvOpMI1WRQfL2c1xUiGG2 | AZ11: =IF(AM11="Not Disclosed", AB11 + ((14545 / 100000) * (0.32 / (1 - 0.32))), AM11) -> 0.11994706 | BA11: =if(AM11="Not Disclosed", "Est. Tax-Adjusted Yield⁹", "Tax-Adjusted Yield") -> Est. Tax-Adjusted Yield⁹ | BB11: =if(AW11="", "Offering Documents Available By Request", "Download Offering Documents") -> Offering Documents Available By Request | BC11: exchangeright-netleased-allcash-19-dst | BD11: sponsors/exchangeright | BE11: property-type/net-lease | BF11: ="Learn More About "&B11 -> Learn More About ExchangeRight | BG11: ="Learn More About "&L11&" Properties" -> Learn More About Net Lease Properties | BH11: {=IFERROR(XLOOKUP($B11, 'Sponsor Connection'!$A:$A, 'Sponsor Connection'!$B:$B), )} -> 2012 | BI11: {=IFERROR(XLOOKUP($B11, 'Sponsor Connection'!$A:$A, 'Sponsor Connection'!$D:$D), )} -> ExchangeRight has scaled into one of the defining net-lease DST franchises, ending 2025 as the fifth-largest sponsor in the 1031 DST market with roughly $7.0 billion in AUM across more than 1,400 properties and 27 million square feet in 48 states. Founded in 2012 and vertically integrated out of Pasadena, the firm anchors its portfolios in investment-grade-tenanted necessity retail and healthcare—pharmacies, grocery, dollar stores—whose recession-resistant cash flows underpin its consistency. The track record is the headline: 34 full-cycle offerings averaging an 8.60% annual return with no loss of investor capital, all 126 offerings meeting or exceeding distribution projections, and an Essential Income REIT that supplies a 721 UPREIT exit. That combination of scale, tenant credit discipline and full-cycle performance makes it a benchmark for the category. | BJ11: {=IF($B11="", "", LET(aum, IFERROR(XLOOKUP($B11, 'Sponsor Connection'!$A:$A, 'Sponsor Connection'!$C:$C), ""), IF(OR(aum="", aum=0), "Not Reported", aum)))} -> 7000000000 | BK11: {=IF(ISBLANK($B11), "", LET(val, IFERROR(XLOOKUP($B11, 'Sponsor Connection'!$A:$A, 'Sponsor Connection'!$M:$M), ""), IF(OR(ISBLANK(val), val="", val=0), "Not Reported", val)))} -> 28 | BL11: {=IF(ISBLANK($B11), "", LET(val, IFERROR(XLOOKUP($B11, 'Sponsor Connection'!$A:$A, 'Sponsor Connection'!$N:$N), ""), IF(val="", "Not Reported", val)))} -> 0.077742857 | BM11: {=IF(ISBLANK($B11), "", LET(val, IFERROR(XLOOKUP($B11, 'Sponsor Connection'!$A:$A, 'Sponsor Connection'!$O:$O), ""), IF(val="", "Not Reported", val)))} -> 1.4082143 | BN11: {=IF(ISBLANK($B11), "", LET(val, IFERROR(XLOOKUP($B11, 'Sponsor Connection'!$A:$A, 'Sponsor Connection'!$P:$P), ""), IF(val="", "Not Reported", val)))} -> 5.4146429 | BO11: {=IF(ISBLANK($B11), "", LET(val, IFERROR(XLOOKUP($B11, 'Sponsor Connection'!$A:$A, 'Sponsor Connection'!$Q:$Q), ""), IF(val="", "Not Reported", val)))} -> 1 | BP11: {=IFERROR(XLOOKUP($B11, 'Sponsor Connection'!$A:$A, 'Sponsor Connection'!$L:$L), )} -> https://img.logo.dev/exchangeright.com?token=pk_FIVsDKgZTvCedVXXtt2rEg&size=200&retina=true | BQ11: =AL11 -> 0.0526 | BR11: =IFERROR(VLOOKUP(L11, Benchmarks!$A$2:$D$15, 2, FALSE), "Not Analyzed") -> 0.051845714 | BS11: =IFERROR(IF(OR(ISBLANK(BQ11), ISBLANK(BR11)), "", IF(ABS(BQ11-BR11)/BQ11 <= 0.1, "Meets Average", IF(BQ11 > BR11, "Above Average", "Below Average"))), "Not Analyzed") -> Meets Average | BT11: =iferror((BW11-AB11)/AB11, 0) -> 0.066019417 | BU11: =IFERROR(VLOOKUP(L11, Benchmarks!$A$2:$D$15, 4, FALSE), "Not Analyzed") -> 0.090429668 | BV11: =IFERROR(IF(OR(ISBLANK(BT11), ISBLANK(BU11)), "", IF(ABS(BT11-BU11)/BT11 <= 0.1, "Meets Average", IF(BT11 > BU11, "Above Average", "Below Average"))), "Not Analyzed") -> Below Average | BW11: =max(AB11:AK11) -> 0.0549 | BX11: =IFERROR(VLOOKUP(L11, Benchmarks!$A$2:$D$15, 3, FALSE), "Not Analyzed") -> 0.053657143 | BY11: =IFERROR(IF(OR(ISBLANK(BW11), ISBLANK(BX11)), "", IF(ABS(BW11-BX11)/BW11 <= 0.1, "Meets Average", IF(BW11 > BX11, "Above Average", "Below Average"))), "Not Analyzed") -> Meets Average | BZ11: ="Investment: " & A11 & " | Sponsor: " & B11 & " | Structure: " & C11 & " | Status: " & D11 & " | LTV: " & H11 & " | Availability: " & K11 & " | Location: " & N11 & " | Strategy: " & P11 & " | 721 Exchange Exit: " & Q11 & " | Estimated Hold: " & R11 & " | Cap Rate Equivalent: " & AN11 & " | Minimum Investment: " & AX11 -> Investment: ExchangeRight Net-Leased All-Cash 19 DST | Sponsor: ExchangeRight | Structure: Delaware Statutory Trust (DST) | Status: Closed | LTV: 0.00% LTV | Availability: 0.00253068645640074 | Location: AL, IL, WA | Strategy: Core | 721 Exchange Exit: Optional | Estimated Hold: 10 years | Cap Rate Equivalent: 0.07753 | Minimum Investment: 100000 | CA11: =A11&" ("&H11&")"&CHAR(10)&CHAR(10)&"ExchangeRight Net-Leased All-Cash 19 is a debt-free portfolio of three single-tenant, necessity-based net-leased retail properties (122,149 SF; 10.7-year WALT) anchored by a Fred Meyer (Kroger; ~58% of NOI), a Hobby Lobby, and a Verizon Wireless store. Th"&"e all-equity structure removes refinancing and maturity risk while delivering contractual rent escalation across the hold. The exit follows ExchangeRight's REIT-aggregation strategy via an optional Section 721 exchange into the Essential Income REIT withi"&"n ~10 years."&CHAR(10)&CHAR(10)&">> Download Offering Documents"&CHAR(10)&"https://www.baker1031.com/sponsors/exchangeright" -> ExchangeRight Net-Leased All-Cash 19 DST (0.00% LTV) ExchangeRight Net-Leased All-Cash 19 is a debt-free portfolio of three single-tenant, necessity-based net-leased retail properties (122,149 SF; 10.7-year WALT) anchored by a Fred Meyer (Kroger; ~58% of NOI), a Hobby Lobby, and a Verizon Wireless store. The all-equity structure removes refinancing and maturity risk while delivering contractual rent escalation across the hold. The exit follows ExchangeRight's REIT-aggregation strategy via an optional Section 721 exchange into the Essential Income REIT within ~10 years. >> Download Offering Documents https://www.baker1031.com/sponsors/exchangeright
A12: ExchangeRight Net-Leased All-Cash 20 DST | B12: ExchangeRight | C12: Delaware Statutory Trust (DST) | D12: Closed | E12: 17800000 | F12: 17800000 | G12: 0 | H12: 0.00% LTV | I12: 0 | J12: 46193 | K12: =(I12/F12) -> 0 | L12: Net Lease | M12: TX, SC, AL | N12: =IFERROR(__xludf.DUMMYFUNCTION("TEXTJOIN("", "", TRUE, SORT(TRANSPOSE(SPLIT(M12, "", ""))))"),"AL, SC, TX") -> AL, SC, TX | O12: 8.83% | P12: Core | Q12: Optional | R12: 10 years | S12: A debt-free portfolio of six single-tenant, necessity-based net-leased retail properties (9.9-year WALT) acquired in early 2026 and held free and clear, sponsored by ExchangeRight Real Estate, LLC. The portfolio comprises two Dollar General stores (S&P BBB), a Dollar Tree (Dollar Tree, Inc.; S&P BBB; El Paso TX, to 2036), an O'Reilly Auto Parts (S&P BBB-; Belton TX, to 2033), a Napa Auto Parts (Genuine Parts Co.; investment grade), and a Tractor Supply (Tractor Supply Co.; S&P BBB), located across Texas (Burleson, El Paso, Belton, Converse), South Carolina (Sumter), and Alabama (Pelham). The properties are leased to an affiliated Master Lessee under a triple-net (NNN) master lease (Annual Base Rent $970,217-$1,186,055), with income diversified so the largest tenant is only ~28% of NOI. Going-in cash flow is 5.20%, escalating to 5.70% by year 10 (~5.40% average) on contractual rent. The all-equity structure removes refinancing and maturity risk. The exit is ExchangeRight's REIT aggregation strategy: the Essential Income REIT is targeted to acquire the DST interests within ~10 years via an optional Section 721 exchange, with cash-out and combination elections available. The $17,800,000 offering is 100 Class 1 interests at $178,000 ($100,000 minimum equity). | T12: The portfolio is held free and clear with no mortgage and is leased entirely to investment-grade-rated operators (Dollar General BBB, Dollar Tree BBB, O'Reilly BBB-, Tractor Supply BBB, Napa/Genuine Parts investment grade) in necessity-based discount-retail and auto-parts categories. The combination supports income durability through cycles and removes refinancing, maturity, and foreclosure risk and the equal-or-greater-debt 1031 requirement. | U12: Income is diversified across six assets and five tenant brands with no dominant tenant: the largest single tenant is only ~28% of NOI (~28/26/20/14/12% split). This is a materially more diversified cash-flow base than a single-anchor net-lease deal and a notable contrast to the sponsor's smaller All-Cash 19 portfolio, where one tenant carried ~58% of NOI. | V12: The affiliated Master Lessee bears all operating expenses, taxes, insurance, and non-structural capital improvements under a triple-net (NNN) master lease (Annual Base Rent $970,217-$1,186,055), insulating distributable cash from operating inflation, with a ~1.48% reserve funded for capital items. This is a cleaner structure than a double-net lease that would leave the trust with structural responsibility. | W12: A 9.9-year weighted-average lease term with staggered expirations (e.g., O'Reilly 2033, Dollar Tree 2036) underpins durable contractual income across the targeted hold. Income growth is modest and contractual, lifting cash-on-cash from 5.20% to 5.70% over ten years rather than through operational upside. | X12: Total upfront load is low at ~8.83% of equity (7.51% selling/offering plus a 1.07% acquisition fee and a 0.25% reallowance) - among the lowest on the ledger - and the offering feeds ExchangeRight's Essential Income REIT, which targets acquiring the DST interests within ~10 years via an optional Section 721 exchange, cash-out, or combination. | Y12: A debt-free, six-property single-tenant net-lease portfolio of necessity-based discount-retail and auto-parts tenants (Dollar General, Dollar Tree, O'Reilly, Napa, Tractor Supply) - all investment-grade-rated - with a 9.9-year WALT and a 5.20% going-in cash flow escalating to 5.70% (~5.40% average), sponsored by ExchangeRight, a scaled net-lease DST/REIT platform. Income is well diversified across six assets and five brands with no tenant above ~28% of NOI, the master lease is triple-net, and the unlevered structure removes all refinancing, maturity, and foreclosure risk and the equal-or-greater-debt 1031 requirement. The total load is low at ~8.83%, and the offering provides a defined exit through ExchangeRight's REIT aggregation with an optional Section 721 tax-deferred rollover into the Essential Income REIT plus cash-out and combination elections. | Z12: Going-in cash flow is modest at 5.20% with only ~0.50% of cumulative escalation over ten years (largely flat, contractual income with no value-add or operational upside), and the absence of leverage caps total return. The leases sit with operating subsidiaries/store-level entities rather than rated parents, and the auto-parts and dollar-store formats are smaller, more fungible boxes whose re-leasing economics depend on local trade-area demand at the 2033/2036 expirations. Geographic concentration is heavy in Texas (four of six assets), exposing the portfolio to a single state's retail and economic conditions. The targeted REIT-aggregation/721 exit is not guaranteed and depends on the ExchangeRight Essential Income REIT's capital availability and willingness to acquire the interests; any 721 consideration would be units in a non-traded, sponsor-controlled REIT operating partnership with sponsor-set NAV and limited liquidity. The portfolio is small ($17.8M), the master tenant and manager are sponsor affiliates, and the Sponsor's affiliated equity-financing/bridge arrangement is repaid from offering proceeds. | AA12: ExchangeRight Net-Leased All-Cash 20 is a debt-free, income-oriented core net-lease vehicle whose return is almost entirely contractual: a 5.20%-to-5.70% cash-on-cash schedule (~5.40% average) from six single-tenant necessity-retail leases with a 9.9-year WALT, no leverage, and no value-add. Relative to the sponsor's smaller All-Cash 19, this portfolio is more diversified (six assets/five brands, largest tenant ~28% of NOI versus a 58% anchor) and carries a uniformly investment-grade tenant roster on a true triple-net master lease - a cleaner credit and structural profile - at a slightly higher 5.20% going-in yield and a lower ~8.83% load. The defining structural feature remains ExchangeRight's REIT aggregation model: the likely terminal path is a Section 721 roll-up into the non-traded Essential Income REIT rather than a third-party sale, attractive for tax-deferral continuity and stable income but ceding control, liquidity, and valuation transparency to a sponsor-managed NAV REIT and contingent on that REIT's capital. The debt-free design is defensive in a higher-for-longer environment, but the modest, largely flat yield and the absence of leverage cap total return, leaving terminal value, Texas concentration, and tenant retention at the 2033/2036 expirations as the dominant sensitivities. No tax-equivalent yield is disclosed. | AB12: 0.052 | AC12: 0.052 | AD12: 0.0522 | AE12: 0.0529 | AF12: 0.0543 | AG12: 0.0546 | AH12: 0.0546 | AI12: 0.0548 | AJ12: 0.0554 | AK12: 0.057 | AL12: 0.054 | AM12: Not disclosed | AN12: =IFERROR((AB12 * ((1 - VALUE(SUBSTITUTE(H12, " LTV", ""))) + 0.02)) + (PMT(0.0535/12, 25*12, -VALUE(SUBSTITUTE(H12, " LTV", ""))) * 12) + (0.02/10) + (0.03/10) + 0.02, "N/A") -> 0.07804 | AO12: None (debt-free) | AP12: N/A (no debt) | AQ12: N/A (no debt) | AR12: N/A (no debt) | AS12: N/A (no debt) | AT12: N/A - no debt service | AV12: https://drive.google.com/file/d/1d1-4SuX32UpB2w3VvGO2kwoCis6n2sj9/view?usp=sharing | AX12: 100000 | AY12: =IFERROR(__xludf.DUMMYFUNCTION("IF(ISBLANK(AV12), """", IF(REGEXMATCH(AV12, ""/file/d/""), ""https://lh3.googleusercontent.com/d/"" & REGEXEXTRACT(AV12, ""/d/([a-zA-Z0-9_-]+)""), AV12))"),"https://lh3.googleusercontent.com/d/1d1-4SuX32UpB2w3VvGO2kwoCis6n2sj9") -> https://lh3.googleusercontent.com/d/1d1-4SuX32UpB2w3VvGO2kwoCis6n2sj9 | AZ12: =IF(AM12="Not Disclosed", AB12 + ((14545 / 100000) * (0.32 / (1 - 0.32))), AM12) -> 0.12044706 | BA12: =if(AM12="Not Disclosed", "Est. Tax-Adjusted Yield⁹", "Tax-Adjusted Yield") -> Est. Tax-Adjusted Yield⁹ | BB12: =if(AW12="", "Offering Documents Available By Request", "Download Offering Documents") -> Offering Documents Available By Request | BC12: exchangeright-netleased-allcash-20-dst | BD12: sponsors/exchangeright | BE12: property-type/net-lease | BF12: ="Learn More About "&B12 -> Learn More About ExchangeRight | BG12: ="Learn More About "&L12&" Properties" -> Learn More About Net Lease Properties | BH12: {=IFERROR(XLOOKUP($B12, 'Sponsor Connection'!$A:$A, 'Sponsor Connection'!$B:$B), )} -> 2012 | BI12: {=IFERROR(XLOOKUP($B12, 'Sponsor Connection'!$A:$A, 'Sponsor Connection'!$D:$D), )} -> ExchangeRight has scaled into one of the defining net-lease DST franchises, ending 2025 as the fifth-largest sponsor in the 1031 DST market with roughly $7.0 billion in AUM across more than 1,400 properties and 27 million square feet in 48 states. Founded in 2012 and vertically integrated out of Pasadena, the firm anchors its portfolios in investment-grade-tenanted necessity retail and healthcare—pharmacies, grocery, dollar stores—whose recession-resistant cash flows underpin its consistency. The track record is the headline: 34 full-cycle offerings averaging an 8.60% annual return with no loss of investor capital, all 126 offerings meeting or exceeding distribution projections, and an Essential Income REIT that supplies a 721 UPREIT exit. That combination of scale, tenant credit discipline and full-cycle performance makes it a benchmark for the category. | BJ12: {=IF($B12="", "", LET(aum, IFERROR(XLOOKUP($B12, 'Sponsor Connection'!$A:$A, 'Sponsor Connection'!$C:$C), ""), IF(OR(aum="", aum=0), "Not Reported", aum)))} -> 7000000000 | BK12: {=IF(ISBLANK($B12), "", LET(val, IFERROR(XLOOKUP($B12, 'Sponsor Connection'!$A:$A, 'Sponsor Connection'!$M:$M), ""), IF(OR(ISBLANK(val), val="", val=0), "Not Reported", val)))} -> 28 | BL12: {=IF(ISBLANK($B12), "", LET(val, IFERROR(XLOOKUP($B12, 'Sponsor Connection'!$A:$A, 'Sponsor Connection'!$N:$N), ""), IF(val="", "Not Reported", val)))} -> 0.077742857 | BM12: {=IF(ISBLANK($B12), "", LET(val, IFERROR(XLOOKUP($B12, 'Sponsor Connection'!$A:$A, 'Sponsor Connection'!$O:$O), ""), IF(val="", "Not Reported", val)))} -> 1.4082143 | BN12: {=IF(ISBLANK($B12), "", LET(val, IFERROR(XLOOKUP($B12, 'Sponsor Connection'!$A:$A, 'Sponsor Connection'!$P:$P), ""), IF(val="", "Not Reported", val)))} -> 5.4146429 | BO12: {=IF(ISBLANK($B12), "", LET(val, IFERROR(XLOOKUP($B12, 'Sponsor Connection'!$A:$A, 'Sponsor Connection'!$Q:$Q), ""), IF(val="", "Not Reported", val)))} -> 1 | BP12: {=IFERROR(XLOOKUP($B12, 'Sponsor Connection'!$A:$A, 'Sponsor Connection'!$L:$L), )} -> https://img.logo.dev/exchangeright.com?token=pk_FIVsDKgZTvCedVXXtt2rEg&size=200&retina=true | BQ12: =AL12 -> 0.054 | BR12: =IFERROR(VLOOKUP(L12, Benchmarks!$A$2:$D$15, 2, FALSE), "Not Analyzed") -> 0.051845714 | BS12: =IFERROR(IF(OR(ISBLANK(BQ12), ISBLANK(BR12)), "", IF(ABS(BQ12-BR12)/BQ12 <= 0.1, "Meets Average", IF(BQ12 > BR12, "Above Average", "Below Average"))), "Not Analyzed") -> Meets Average | BT12: =iferror((BW12-AB12)/AB12, 0) -> 0.096153846 | BU12: =IFERROR(VLOOKUP(L12, Benchmarks!$A$2:$D$15, 4, FALSE), "Not Analyzed") -> 0.090429668 | BV12: =IFERROR(IF(OR(ISBLANK(BT12), ISBLANK(BU12)), "", IF(ABS(BT12-BU12)/BT12 <= 0.1, "Meets Average", IF(BT12 > BU12, "Above Average", "Below Average"))), "Not Analyzed") -> Meets Average | BW12: =max(AB12:AK12) -> 0.057 | BX12: =IFERROR(VLOOKUP(L12, Benchmarks!$A$2:$D$15, 3, FALSE), "Not Analyzed") -> 0.053657143 | BY12: =IFERROR(IF(OR(ISBLANK(BW12), ISBLANK(BX12)), "", IF(ABS(BW12-BX12)/BW12 <= 0.1, "Meets Average", IF(BW12 > BX12, "Above Average", "Below Average"))), "Not Analyzed") -> Meets Average | BZ12: ="Investment: " & A12 & " | Sponsor: " & B12 & " | Structure: " & C12 & " | Status: " & D12 & " | LTV: " & H12 & " | Availability: " & K12 & " | Location: " & N12 & " | Strategy: " & P12 & " | 721 Exchange Exit: " & Q12 & " | Estimated Hold: " & R12 & " | Cap Rate Equivalent: " & AN12 & " | Minimum Investment: " & AX12 -> Investment: ExchangeRight Net-Leased All-Cash 20 DST | Sponsor: ExchangeRight | Structure: Delaware Statutory Trust (DST) | Status: Closed | LTV: 0.00% LTV | Availability: 0 | Location: AL, SC, TX | Strategy: Core | 721 Exchange Exit: Optional | Estimated Hold: 10 years | Cap Rate Equivalent: 0.07804 | Minimum Investment: 100000 | CA12: =A12&" ("&H12&")"&CHAR(10)&CHAR(10)&"ExchangeRight Net-Leased All-Cash 20 is a debt-free portfolio of six single-tenant, necessity-based net-leased retail properties (9.9-year WALT) leased to investment-grade-anchored tenants including Dollar General, Dollar Tree, O'Reilly, NAPA, and Tractor"&" Supply across Texas, South Carolina, and Alabama. Income is diversified under an affiliated NNN master lease such that the largest tenant represents only ~28% of NOI, and the all-equity structure removes refinancing and maturity risk. The exit follows Ex"&"changeRight's REIT-aggregation strategy via an optional Section 721 exchange into the Essential Income REIT within ~10 years."&CHAR(10)&CHAR(10)&">> Download Offering Documents"&CHAR(10)&"https://www.baker1031.com/sponsors/exchangeright" -> ExchangeRight Net-Leased All-Cash 20 DST (0.00% LTV) ExchangeRight Net-Leased All-Cash 20 is a debt-free portfolio of six single-tenant, necessity-based net-leased retail properties (9.9-year WALT) leased to investment-grade-anchored tenants including Dollar General, Dollar Tree, O'Reilly, NAPA, and Tractor Supply across Texas, South Carolina, and Alabama. Income is diversified under an affiliated NNN master lease such that the largest tenant represents only ~28% of NOI, and the all-equity structure removes refinancing and maturity risk. The exit follows ExchangeRight's REIT-aggregation strategy via an optional Section 721 exchange into the Essential Income REIT within ~10 years. >> Download Offering Documents https://www.baker1031.com/sponsors/exchangeright
A13: ExchangeRight Net-Leased Portfolio 75 DST | B13: ExchangeRight | C13: Delaware Statutory Trust (DST) | D13: Available | E13: 84900000 | F13: 47570000 | G13: 37330000 | H13: 43.97% LTV | I13: 11150094 | J13: 46204 | K13: =(I13/F13) -> 0.2343934 | L13: Net Lease | M13: TX, MI, OH, AR, NJ, GA | N13: =IFERROR(__xludf.DUMMYFUNCTION("TEXTJOIN("", "", TRUE, SORT(TRANSPOSE(SPLIT(M13, "", ""))))"),"AR, GA, MI, NJ, OH, TX") -> AR, GA, MI, NJ, OH, TX | O13: 9.36% | P13: Core | Q13: Optional | R13: 5 years | S13: A leveraged, diversified portfolio of six single-tenant net-leased properties (11.8-year WALT) acquired in early 2026 across six states, sponsored by ExchangeRight Real Estate, LLC. The portfolio spans retail, logistics, and healthcare necessity-based tenants: a FedEx distribution facility (303,596 SF, Little Rock AR, ~46% of NOI, to 2036), a Hobby Lobby (54,640 SF, East Hanover NJ, to 2036), a BioLife Plasma Services center (Takeda/Baxalta-guaranteed; Takeda S&P BBB+; Burleson TX, to 2039), two Dollar General stores (S&P BBB; Adrian MI and Strongsville OH, to 2041), and a Tractor Supply (S&P BBB; Villa Rica GA, to 2046). Five of the six tenants are investment-grade-rated. The properties were acquired for an aggregate $74.2M; total capitalization is $84,900,000 ($47,570,000 equity + $37,330,000 non-recourse debt; 43.97% LTV). Financing is a $37.33M Wells Fargo loan, 5.120% fixed, interest-only for a 5-year term (closed April 2026), non-recourse, prepayable without penalty in the final six months. Going-in cash flow is 5.00%, escalating to 5.62% by year 5 (~5.30% average); Year 1 DSCR is 2.32x. The exit is ExchangeRight's REIT aggregation: the Essential Income REIT is targeted to acquire the DST interests (with an optional Section 721 exchange, cash-out, or combination) around the 5-year loan maturity. | T13: Six single-tenant assets across six states, five industries, and five tenant brands, with five of six tenants investment-grade-rated (Takeda/BioLife BBB+, FedEx BBB, Dollar General BBB x2, Tractor Supply BBB; Hobby Lobby private), spanning retail, logistics, and healthcare necessity-based uses - a genuinely diversified footprint by geography and sector. | U13: The 303,596 SF FedEx distribution facility in Little Rock AR is the largest asset at ~46% of NOI, a long-haul logistics box leased to an investment-grade credit through 2036 - a meaningful credit anchor that simultaneously concentrates nearly half of portfolio income in one tenant and one specialized asset. | V13: An 11.8-year weighted-average lease term with staggered expirations (FedEx/Hobby Lobby 2036, BioLife 2039, Dollar General 2041, Tractor Supply 2046) underpins durable contractual income well beyond the 5-year loan/hold. Income growth is modest and contractual, lifting cash-on-cash from 5.00% to 5.62%. | W13: A $37.33M Wells Fargo (unaffiliated lender) non-recourse loan at 43.97% LTV, fixed at 5.120% and interest-only for the 5-year term, generates positive leverage and a healthy 2.32x Year 1 DSCR. The full principal balloons at the 2031 maturity (a 5-year refinancing/exit wall), and a 1.40x DSCR cash-trap covenant could suspend distributions if NOI falls. | X13: Total upfront load is ~9.36% of equity (7.12% selling/offering plus a 1.24% acquisition fee and a 1.00% reallowance), and the offering feeds ExchangeRight's Essential Income REIT, targeted to acquire the DST interests around the 5-year loan maturity via an optional Section 721 exchange, cash-out, or combination. | Y13: A leveraged, diversified six-property single-tenant net-lease portfolio across six states and five industries (retail, logistics, healthcare), with an 11.8-year WALT and five of six tenants investment-grade-rated (Takeda/BioLife BBB+, FedEx BBB, Dollar General BBB, Tractor Supply BBB). Wells Fargo non-recourse financing at a conservative 43.97% LTV, fixed at 5.120% and interest-only, generates positive leverage and a healthy 2.32x Year 1 DSCR while lifting cash-on-cash from 5.00% to 5.62% (~5.30% average) over the 5-year forecast. The total load is comparatively low at ~9.36%, the lender is an unaffiliated third party (Wells Fargo), and the offering provides a defined exit through ExchangeRight's REIT aggregation with an optional Section 721 tax-deferred rollover into the Essential Income REIT. | Z13: Despite the diversified branding, income is concentrated in the FedEx distribution facility at ~46% of NOI on a single specialized logistics asset expiring 2036, so FedEx renewal/credit is materially binary to portfolio cash flow; the top two tenants (FedEx, Hobby Lobby) are ~68% of NOI. The Wells Fargo loan is interest-only with the full $37.33M ballooning at the 5-year (2031) maturity, a near-term refinancing/exit wall in an uncertain rate environment, with a 1.40x DSCR cash-trap covenant. Going-in cash flow is modest at 5.00% with only ~0.62% of cumulative escalation over the five-year forecast, and the leases sit with operating subsidiaries/store entities rather than rated parents (Hobby Lobby is private and unrated). The targeted REIT-aggregation/721 exit is not guaranteed and depends on the ExchangeRight Essential Income REIT's capital availability; any 721 consideration would be units in a non-traded, sponsor-controlled REIT operating partnership with sponsor-set NAV and limited liquidity. The master tenant and manager are sponsor affiliates, and the Sponsor's affiliated short-term equity-financing/bridge arrangement is repaid from offering proceeds. | AA13: ExchangeRight Net-Leased Portfolio 75 is a moderately leveraged, income-oriented core net-lease vehicle, distinct from the sponsor's debt-free All-Cash series: a $37.33M Wells Fargo non-recourse loan at 43.97% LTV (5.120% fixed, interest-only) generates positive leverage on a diversified, mostly investment-grade tenant pool, lifting cash-on-cash from 5.00% to 5.62% (~5.30% average) with a healthy 2.32x Year 1 DSCR. The portfolio is genuinely diversified by geography (six states) and industry (retail, logistics, healthcare), but income concentration is real: FedEx alone is ~46% of NOI and the top two tenants ~68%, so the diversified label overstates the cash-flow dispersion. The defining structural features are the 5-year interest-only loan (which sets both the forecast horizon and a near-term refinancing/exit wall at 2031, with a 1.40x DSCR cash-trap) and ExchangeRight's REIT aggregation model, under which the likely terminal path is a Section 721 roll-up into the non-traded Essential Income REIT rather than a third-party sale. The 11.8-year WALT supports residual value well beyond the hold and the credit profile is strong, but the dominant sensitivities are FedEx renewal and credit, refinancing conditions at the 5-year maturity, the exit pricing, and the timing/terms of the REIT aggregation. The comparatively low ~9.36% load and unaffiliated Wells Fargo financing are favorable relative to higher-fee, affiliated-lender DSTs. No tax-equivalent yield is disclosed. | AB13: 0.05 | AC13: 0.0514 | AD13: 0.053 | AE13: 0.0545 | AF13: 0.0562 | AG13: Sold | AH13: Sold | AI13: Sold | AJ13: Sold | AK13: Sold | AL13: 0.053 | AM13: Not disclosed | AN13: =IFERROR((AB13 * ((1 - VALUE(SUBSTITUTE(H13, " LTV", ""))) + 0.02)) + (PMT(0.0535/12, 25*12, -VALUE(SUBSTITUTE(H13, " LTV", ""))) * 12) + (0.02/10) + (0.03/10) + 0.02, "N/A") -> 0.085945765 | AO13: Wells Fargo Bank, National Association | AP13: 5.12% (Fixed) | AQ13: 5 years | AR13: 5 years | AS13: N/A (interest-only) | AT13: 2.32x | AV13: https://lh3.googleusercontent.com/d/1D2M3mHX5vm_5EdGcho3-i9Py-KqBqmvv | AX13: 100000 | AY13: =IFERROR(__xludf.DUMMYFUNCTION("IF(ISBLANK(AV13), """", IF(REGEXMATCH(AV13, ""/file/d/""), ""https://lh3.googleusercontent.com/d/"" & REGEXEXTRACT(AV13, ""/d/([a-zA-Z0-9_-]+)""), AV13))"),"https://lh3.googleusercontent.com/d/1D2M3mHX5vm_5EdGcho3-i9Py-KqBqmvv") -> https://lh3.googleusercontent.com/d/1D2M3mHX5vm_5EdGcho3-i9Py-KqBqmvv | AZ13: =IF(AM13="Not Disclosed", AB13 + ((14545 / 100000) * (0.32 / (1 - 0.32))), AM13) -> 0.11844706 | BA13: =if(AM13="Not Disclosed", "Est. Tax-Adjusted Yield⁹", "Tax-Adjusted Yield") -> Est. Tax-Adjusted Yield⁹ | BB13: =if(AW13="", "Offering Documents Available By Request", "Download Offering Documents") -> Offering Documents Available By Request | BC13: exchangeright-netleased-portfolio-75-dst | BD13: sponsors/exchangeright | BE13: property-type/net-lease | BF13: ="Learn More About "&B13 -> Learn More About ExchangeRight | BG13: ="Learn More About "&L13&" Properties" -> Learn More About Net Lease Properties | BH13: {=IFERROR(XLOOKUP($B13, 'Sponsor Connection'!$A:$A, 'Sponsor Connection'!$B:$B), )} -> 2012 | BI13: {=IFERROR(XLOOKUP($B13, 'Sponsor Connection'!$A:$A, 'Sponsor Connection'!$D:$D), )} -> ExchangeRight has scaled into one of the defining net-lease DST franchises, ending 2025 as the fifth-largest sponsor in the 1031 DST market with roughly $7.0 billion in AUM across more than 1,400 properties and 27 million square feet in 48 states. Founded in 2012 and vertically integrated out of Pasadena, the firm anchors its portfolios in investment-grade-tenanted necessity retail and healthcare—pharmacies, grocery, dollar stores—whose recession-resistant cash flows underpin its consistency. The track record is the headline: 34 full-cycle offerings averaging an 8.60% annual return with no loss of investor capital, all 126 offerings meeting or exceeding distribution projections, and an Essential Income REIT that supplies a 721 UPREIT exit. That combination of scale, tenant credit discipline and full-cycle performance makes it a benchmark for the category. | BJ13: {=IF($B13="", "", LET(aum, IFERROR(XLOOKUP($B13, 'Sponsor Connection'!$A:$A, 'Sponsor Connection'!$C:$C), ""), IF(OR(aum="", aum=0), "Not Reported", aum)))} -> 7000000000 | BK13: {=IF(ISBLANK($B13), "", LET(val, IFERROR(XLOOKUP($B13, 'Sponsor Connection'!$A:$A, 'Sponsor Connection'!$M:$M), ""), IF(OR(ISBLANK(val), val="", val=0), "Not Reported", val)))} -> 28 | BL13: {=IF(ISBLANK($B13), "", LET(val, IFERROR(XLOOKUP($B13, 'Sponsor Connection'!$A:$A, 'Sponsor Connection'!$N:$N), ""), IF(val="", "Not Reported", val)))} -> 0.077742857 | BM13: {=IF(ISBLANK($B13), "", LET(val, IFERROR(XLOOKUP($B13, 'Sponsor Connection'!$A:$A, 'Sponsor Connection'!$O:$O), ""), IF(val="", "Not Reported", val)))} -> 1.4082143 | BN13: {=IF(ISBLANK($B13), "", LET(val, IFERROR(XLOOKUP($B13, 'Sponsor Connection'!$A:$A, 'Sponsor Connection'!$P:$P), ""), IF(val="", "Not Reported", val)))} -> 5.4146429 | BO13: {=IF(ISBLANK($B13), "", LET(val, IFERROR(XLOOKUP($B13, 'Sponsor Connection'!$A:$A, 'Sponsor Connection'!$Q:$Q), ""), IF(val="", "Not Reported", val)))} -> 1 | BP13: {=IFERROR(XLOOKUP($B13, 'Sponsor Connection'!$A:$A, 'Sponsor Connection'!$L:$L), )} -> https://img.logo.dev/exchangeright.com?token=pk_FIVsDKgZTvCedVXXtt2rEg&size=200&retina=true | BQ13: =AL13 -> 0.053 | BR13: =IFERROR(VLOOKUP(L13, Benchmarks!$A$2:$D$15, 2, FALSE), "Not Analyzed") -> 0.051845714 | BS13: =IFERROR(IF(OR(ISBLANK(BQ13), ISBLANK(BR13)), "", IF(ABS(BQ13-BR13)/BQ13 <= 0.1, "Meets Average", IF(BQ13 > BR13, "Above Average", "Below Average"))), "Not Analyzed") -> Meets Average | BT13: =iferror((BW13-AB13)/AB13, 0) -> 0.124 | BU13: =IFERROR(VLOOKUP(L13, Benchmarks!$A$2:$D$15, 4, FALSE), "Not Analyzed") -> 0.090429668 | BV13: =IFERROR(IF(OR(ISBLANK(BT13), ISBLANK(BU13)), "", IF(ABS(BT13-BU13)/BT13 <= 0.1, "Meets Average", IF(BT13 > BU13, "Above Average", "Below Average"))), "Not Analyzed") -> Above Average | BW13: =max(AB13:AK13) -> 0.0562 | BX13: =IFERROR(VLOOKUP(L13, Benchmarks!$A$2:$D$15, 3, FALSE), "Not Analyzed") -> 0.053657143 | BY13: =IFERROR(IF(OR(ISBLANK(BW13), ISBLANK(BX13)), "", IF(ABS(BW13-BX13)/BW13 <= 0.1, "Meets Average", IF(BW13 > BX13, "Above Average", "Below Average"))), "Not Analyzed") -> Meets Average | BZ13: ="Investment: " & A13 & " | Sponsor: " & B13 & " | Structure: " & C13 & " | Status: " & D13 & " | LTV: " & H13 & " | Availability: " & K13 & " | Location: " & N13 & " | Strategy: " & P13 & " | 721 Exchange Exit: " & Q13 & " | Estimated Hold: " & R13 & " | Cap Rate Equivalent: " & AN13 & " | Minimum Investment: " & AX13 -> Investment: ExchangeRight Net-Leased Portfolio 75 DST | Sponsor: ExchangeRight | Structure: Delaware Statutory Trust (DST) | Status: Available | LTV: 43.97% LTV | Availability: 0.234393399201177 | Location: AR, GA, MI, NJ, OH, TX | Strategy: Core | 721 Exchange Exit: Optional | Estimated Hold: 5 years | Cap Rate Equivalent: 0.0859457645080764 | Minimum Investment: 100000 | CA13: =A13&" ("&H13&")"&CHAR(10)&CHAR(10)&"ExchangeRight Net-Leased Portfolio 75 is a leveraged, diversified portfolio of six single-tenant net-leased properties (11.8-year WALT) across six states, anchored by a FedEx distribution facility (~46% of NOI) with five of six tenants investment-grade-ra"&"ted. Total capitalization is $84.9M ($47.57M equity + $37.33M non-recourse Wells Fargo debt at 5.120% fixed, interest-only, 43.97% LTV), with a Year-1 DSCR of 2.32x. The exit follows ExchangeRight's REIT-aggregation strategy via an optional Section 721 ex"&"change into the Essential Income REIT around the 5-year loan maturity."&CHAR(10)&CHAR(10)&">> Download Offering Documents"&CHAR(10)&"https://www.baker1031.com/sponsors/exchangeright" -> ExchangeRight Net-Leased Portfolio 75 DST (43.97% LTV) ExchangeRight Net-Leased Portfolio 75 is a leveraged, diversified portfolio of six single-tenant net-leased properties (11.8-year WALT) across six states, anchored by a FedEx distribution facility (~46% of NOI) with five of six tenants investment-grade-rated. Total capitalization is $84.9M ($47.57M equity + $37.33M non-recourse Wells Fargo debt at 5.120% fixed, interest-only, 43.97% LTV), with a Year-1 DSCR of 2.32x. The exit follows ExchangeRight's REIT-aggregation strategy via an optional Section 721 exchange into the Essential Income REIT around the 5-year loan maturity. >> Download Offering Documents https://www.baker1031.com/sponsors/exchangeright
A14: Florida Growth 2 - Jubilee 1 DST | B14: Walton Global Holdings | C14: Delaware Statutory Trust (DST) | D14: Available | E14: 9671490 | F14: 9671490 | G14: 0 | H14: 0.00% LTV | I14: 1434292 | J14: 46167 | K14: =(I14/F14) -> 0.14830104 | L14: Land | M14: FL | N14: =IFERROR(__xludf.DUMMYFUNCTION("TEXTJOIN("", "", TRUE, SORT(TRANSPOSE(SPLIT(M14, "", ""))))"),"FL") -> FL | O14: 17.77% | P14: Opportunistic | Q14: None | R14: 3-5 years | S14: Approximately 268 acres of undeveloped forest land north of Berryhill Road and south of Willard Norris Road in Pace, Santa Rosa County, Florida, within the Pensacola-Ferry Pass-Brent MSA. The parcel sits inside the planned Jubilee Master Planned Community along the Florida Panhandle's northerly path of growth, roughly 20 minutes from Naval Air Station Whiting Field and within 10 miles of Interstate 10 and US Highway 90. The thesis is a pre-development land-banking play: acquire entitlable residential land at a basis approximating its February 2024 as-is appraised value ($6,800,000 against a $6,839,610 purchase price), hold it unimproved through an anticipated three-to-five-year hold, and dispose to a single national homebuilder or developer via a staged sale of up to three installments. The vehicle is unleveraged and non-operating, producing no rental income, no depreciation shelter, and no interim distributions, with all investor proceeds back-ended to disposition. Bare legal title is held by the Administrative Trustee (Jubilee Keeper 1, LLC); the Depositor is Jubilee Depositor 1, LLC and the Dealer Manager is Emerson Equity, LLC. Operating strategy is limited to value maintenance, entitlement positioning, and buyer negotiation rather than active asset management or repositioning. | T14: The asset's defining attribute is its position within the contiguous Jubilee Master Planned Community footprint along an established northerly growth corridor of the Pensacola MSA, which confers takeout optionality with national homebuilders seeking pre-entitled, scaled residential tracts. Large single-ownership parcels of this size inside a master plan are scarce, and the embedded master-plan framework reduces the entitlement friction a builder would otherwise underwrite, supporting a basis-to-finished-lot spread that anchors the appreciation thesis. | U14: Demand fundamentals are anchored by Naval Air Station Whiting Field, which sustains roughly 2,700 active-duty members and 1,200 civilian employees as a durable, non-cyclical regional employment base, layered atop documented MSA in-migration, retiree settlement, and median household income growth projected near 18.3% over five years. The convergence of military-driven baseline demand with discretionary retiree and family migration diversifies the absorption profile across multiple buyer cohorts. | V14: The all-cash, unleveraged capital structure eliminates the financing-side fragilities that typically dominate DST risk profiles: there is no loan maturity wall, no interest-rate-cap replacement cost, no DSCR covenant, and no lender foreclosure exposure on an asset that by design produces no debt-service coverage. For a non-cash-flowing land position, the absence of leverage removes the most acute mechanism by which a holding-period extension would otherwise destroy equity value. | W14: The exit is architected as a staged sale to a single homebuilder or developer in no more than three installments, a structure that mirrors builder lot-takedown economics and allows the buyer to phase capital deployment against absorption. This alignment can compress marketing risk relative to a fragmented retail land sale and supports price realization at the finished-lot-demand end of the value chain rather than at raw-acreage discounts. | X14: The Sponsor's specialization is narrow and long-tenured, with land-based investment strategies dating to 1979 and an institutional underwriting process evidenced by a third-party market study commissioned from John Burns Research and Consulting. This depth in pre-development land sourcing, entitlement navigation, and homebuilder relationships is the principal operational input distinguishing the vehicle, given that the strategy depends almost entirely on buyer-side execution rather than property operations. | Y14: At the micro level, the offering benefits from a purchase price effectively at appraised value, a scaled and contiguous land position inside a coordinated master plan, and an unleveraged structure that insulates equity from rate and refinancing shocks during the hold. The submarket exhibits favorable demographic momentum, with above-MSA income levels, sustained employment growth since 2021, and a defense-anchored demand floor at Naval Air Station Whiting Field. At the macro level, the Florida Panhandle continues to capture domestic migration and retiree formation, and national homebuilders have maintained appetite for entitled land pipelines in lower-cost, high-growth Sun Belt corridors. The reserve account is pre-funded for operating costs, insurance, and property taxes, mitigating carrying-cost shortfall risk during the early hold. | Z14: The principal asset-specific vulnerability is the binary, back-ended return profile: because the parcel generates no interim income and is non-depreciable raw land, the entire investor outcome depends on a single disposition event, with no current yield to cushion a delayed or impaired exit. Buyer concentration is acute, as the strategy contemplates a sale to one homebuilder, exposing realization to that counterparty's absorption pace, financing access, and rate sensitivity, with an affiliate of the Administrative Trustee positioned as the fallback buyer should no third party transact, an arrangement that introduces a pricing conflict at the most value-critical moment. Entitlement and horizontal-development assumptions embedded in the homebuilder takeout are unexecuted as of acquisition, and large-tract land appraisals rest on thin, subjective comparable sets. Carrying economics deteriorate on extension: an additional asset-management fee accrues at $11,399 per month from the thirty-seventh month through the earlier of sale or the ten-year agreement term, compounding against an asset producing no offsetting income, while the stated three-to-five-year hold is explicitly subject to extension. The aggregate fee and syndication load is substantial relative to a non-operating asset whose only value driver is appreciation. | AA14: On a risk-adjusted basis, the vehicle trades the financing and operational risks of a conventional leveraged DST for a concentrated, duration-sensitive bet on Florida Panhandle residential land appreciation and homebuilder takeout demand. The positioning is coherent within the current macro cycle insofar as Sun Belt migration and constrained entitled-lot supply continue to support builder land acquisition, but the underwriting's feasibility hinges on two unhedged variables: the timeline to convert raw acreage into builder-ready inventory, and the resilience of homebuilder demand against a higher-for-longer rate environment that directly compresses lot absorption and land bids. The unleveraged structure materially de-risks the hold itself, yet it cannot offset the fact that return realization is singular and exit-dependent, with carrying costs that escalate precisely when a soft homebuilder market would extend the hold. The basis at appraised value provides a measure of downside anchoring, but the appreciation spread required to clear fees and deliver investor return remains the operative assumption, supported by market-study projection rather than in-place cash flow. This is a non-income, opportunistic land position directly analogous to the ledger's Colorado Growth 1 - Holly Ridge holding and is not comparable to the income-distributing DSTs on the sheet. | AB14: 0 | AC14: 0 | AD14: 0 | AE14: 0 | AF14: 0 | AG14: Sold | AH14: Sold | AI14: Sold | AJ14: Sold | AK14: Sold | AL14: N/A (no income) | AM14: N/A (no income) | AN14: =IFERROR((AB14 * ((1 - VALUE(SUBSTITUTE(H14, " LTV", ""))) + 0.02)) + (PMT(0.0535/12, 25*12, -VALUE(SUBSTITUTE(H14, " LTV", ""))) * 12) + (0.02/10) + (0.03/10) + 0.02, "N/A") -> 0.025 | AO14: None (debt-free) | AP14: N/A (no debt) | AQ14: N/A (no debt) | AR14: N/A (no debt) | AS14: N/A (no debt) | AT14: N/A - no debt service | AU14: North of Berryhill Road, Pace, Santa Rosa County, FL | AV14: https://drive.google.com/file/d/1i91BiYn7XZtKB0-u7yKPmdaWTp0c0rDr/view?usp=sharing | AX14: 100000 | AY14: =IFERROR(__xludf.DUMMYFUNCTION("IF(ISBLANK(AV14), """", IF(REGEXMATCH(AV14, ""/file/d/""), ""https://lh3.googleusercontent.com/d/"" & REGEXEXTRACT(AV14, ""/d/([a-zA-Z0-9_-]+)""), AV14))"),"https://lh3.googleusercontent.com/d/1i91BiYn7XZtKB0-u7yKPmdaWTp0c0rDr") -> https://lh3.googleusercontent.com/d/1i91BiYn7XZtKB0-u7yKPmdaWTp0c0rDr | AZ14: =IF(AM14="Not Disclosed", AB14 + ((14545 / 100000) * (0.32 / (1 - 0.32))), AM14) -> N/A (no income) | BA14: =if(AM14="Not Disclosed", "Est. Tax-Adjusted Yield⁹", "Tax-Adjusted Yield") -> Tax-Adjusted Yield | BB14: =if(AW14="", "Offering Documents Available By Request", "Download Offering Documents") -> Offering Documents Available By Request | BC14: florida-growth-2-jubilee-1-dst | BD14: sponsors/walton-global-holdings | BE14: property-type/land | BF14: ="Learn More About "&B14 -> Learn More About Walton Global Holdings | BG14: ="Learn More About "&L14&" Properties" -> Learn More About Land Properties | BH14: {=IFERROR(XLOOKUP($B14, 'Sponsor Connection'!$A:$A, 'Sponsor Connection'!$B:$B), )} -> 1979 | BI14: {=IFERROR(XLOOKUP($B14, 'Sponsor Connection'!$A:$A, 'Sponsor Connection'!$D:$D), )} -> Walton Global Holdings is a land asset manager with a 45-plus-year history, managing $3.35 billion and specializing in pre-development land that it supplies to U.S. homebuilders—a genuinely distinctive 1031 asset class. Controlling more than 85,000 acres across 170-plus master-planned communities and serving some 88,000 global investors across 91 countries, Walton has institutionalized land banking through its Builder Land Finance structure, recently bolstered by a 2025 GoldenTree co-investment. The land-to-homebuilder model offers diversification from income real estate but carries entitlement and absorption risk distinct from cash-flowing assets. | BJ14: {=IF($B14="", "", LET(aum, IFERROR(XLOOKUP($B14, 'Sponsor Connection'!$A:$A, 'Sponsor Connection'!$C:$C), ""), IF(OR(aum="", aum=0), "Not Reported", aum)))} -> 3350000000 | BK14: {=IF(ISBLANK($B14), "", LET(val, IFERROR(XLOOKUP($B14, 'Sponsor Connection'!$A:$A, 'Sponsor Connection'!$M:$M), ""), IF(OR(ISBLANK(val), val="", val=0), "Not Reported", val)))} -> 68 | BL14: {=IF(ISBLANK($B14), "", LET(val, IFERROR(XLOOKUP($B14, 'Sponsor Connection'!$A:$A, 'Sponsor Connection'!$N:$N), ""), IF(val="", "Not Reported", val)))} -> 0.082045588 | BM14: {=IF(ISBLANK($B14), "", LET(val, IFERROR(XLOOKUP($B14, 'Sponsor Connection'!$A:$A, 'Sponsor Connection'!$O:$O), ""), IF(val="", "Not Reported", val)))} -> 1.3453488 | BN14: {=IF(ISBLANK($B14), "", LET(val, IFERROR(XLOOKUP($B14, 'Sponsor Connection'!$A:$A, 'Sponsor Connection'!$P:$P), ""), IF(val="", "Not Reported", val)))} -> 7.165 | BO14: {=IF(ISBLANK($B14), "", LET(val, IFERROR(XLOOKUP($B14, 'Sponsor Connection'!$A:$A, 'Sponsor Connection'!$Q:$Q), ""), IF(val="", "Not Reported", val)))} -> 0.75 | BP14: {=IFERROR(XLOOKUP($B14, 'Sponsor Connection'!$A:$A, 'Sponsor Connection'!$L:$L), )} -> https://img.logo.dev/walton.com?token=pk_FIVsDKgZTvCedVXXtt2rEg&size=200&retina=true | BQ14: =AL14 -> N/A (no income) | BR14: =IFERROR(VLOOKUP(L14, Benchmarks!$A$2:$D$15, 2, FALSE), "Not Analyzed") | BS14: =IFERROR(IF(OR(ISBLANK(BQ14), ISBLANK(BR14)), "", IF(ABS(BQ14-BR14)/BQ14 <= 0.1, "Meets Average", IF(BQ14 > BR14, "Above Average", "Below Average"))), "Not Analyzed") -> Not Analyzed | BT14: =iferror((BW14-AB14)/AB14, 0) -> 0 | BU14: =IFERROR(VLOOKUP(L14, Benchmarks!$A$2:$D$15, 4, FALSE), "Not Analyzed") -> 0 | BV14: =IFERROR(IF(OR(ISBLANK(BT14), ISBLANK(BU14)), "", IF(ABS(BT14-BU14)/BT14 <= 0.1, "Meets Average", IF(BT14 > BU14, "Above Average", "Below Average"))), "Not Analyzed") -> Not Analyzed | BW14: =max(AB14:AK14) -> 0 | BX14: =IFERROR(VLOOKUP(L14, Benchmarks!$A$2:$D$15, 3, FALSE), "Not Analyzed") -> 0 | BY14: =IFERROR(IF(OR(ISBLANK(BW14), ISBLANK(BX14)), "", IF(ABS(BW14-BX14)/BW14 <= 0.1, "Meets Average", IF(BW14 > BX14, "Above Average", "Below Average"))), "Not Analyzed") -> Not Analyzed | BZ14: ="Investment: " & A14 & " | Sponsor: " & B14 & " | Structure: " & C14 & " | Status: " & D14 & " | LTV: " & H14 & " | Availability: " & K14 & " | Location: " & N14 & " | Strategy: " & P14 & " | 721 Exchange Exit: " & Q14 & " | Estimated Hold: " & R14 & " | Cap Rate Equivalent: " & AN14 & " | Minimum Investment: " & AX14 -> Investment: Florida Growth 2 - Jubilee 1 DST | Sponsor: Walton Global Holdings | Structure: Delaware Statutory Trust (DST) | Status: Available | LTV: 0.00% LTV | Availability: 0.148301037378935 | Location: FL | Strategy: Opportunistic | 721 Exchange Exit: None | Estimated Hold: 3-5 years | Cap Rate Equivalent: 0.025 | Minimum Investment: 100000 | CA14: =A14&" ("&H14&")"&CHAR(10)&CHAR(10)&"Florida Growth 2 is a Walton Global land-banking offering acquiring ~268 acres of undeveloped forest land in Pace (Santa Rosa County), within the planned Jubilee master-planned community along the Florida Panhandle's path of growth. The unleveraged, non-o"&"perating vehicle holds the land unimproved at a basis approximating its February 2024 appraised value and targets disposition to a single national homebuilder via a staged sale over a ~3-5 year hold. It produces no rental income, depreciation shelter, or "&"interim distributions, with all investor proceeds back-ended to disposition."&CHAR(10)&CHAR(10)&">> Download Offering Documents"&CHAR(10)&"https://www.baker1031.com/sponsors/walton-global-holdings" -> Florida Growth 2 - Jubilee 1 DST (0.00% LTV) Florida Growth 2 is a Walton Global land-banking offering acquiring ~268 acres of undeveloped forest land in Pace (Santa Rosa County), within the planned Jubilee master-planned community along the Florida Panhandle's path of growth. The unleveraged, non-operating vehicle holds the land unimproved at a basis approximating its February 2024 appraised value and targets disposition to a single national homebuilder via a staged sale over a ~3-5 year hold. It produces no rental income, depreciation shelter, or interim distributions, with all investor proceeds back-ended to disposition. >> Download Offering Documents https://www.baker1031.com/sponsors/walton-global-holdings
A15: FSX Industrial 34, DST | B15: Four Springs Capital | C15: Delaware Statutory Trust (DST) | D15: Limited Availability | E15: 97720000 | F15: 50200000 | G15: 47520000 | H15: 48.63% LTV | I15: 5000000 | J15: 46193 | K15: =(I15/F15) -> 0.099601594 | L15: Industrial | M15: KY, SC | N15: =IFERROR(__xludf.DUMMYFUNCTION("TEXTJOIN("", "", TRUE, SORT(TRANSPOSE(SPLIT(M15, "", ""))))"),"KY, SC") -> KY, SC | O15: 15.32% | P15: Core | Q15: Optional | R15: 7 years | S15: A two-property, single-tenant absolute-NNN industrial portfolio (995,781 SF total) acquired through a leveraged DST, diversified by geography and tenant. Property 1 is a 680,508 SF build-to-suit distribution hub at 380 Estill Baker Road, Hanson KY (54.8 acres, built 1998 / expanded 2009, up to 70-foot clear heights, 48 dock doors), serving as Carhartt's primary national SKU facility, into which Carhartt has invested over $70 million in robotics, racking, and conveyor automation plus $1 million-plus of annual capex since 2015; the lease has 11.8 years remaining, 2.50% annual escalations, and eight 5-year renewal options. Property 2 is a 315,273 SF warehouse/manufacturing/office facility at 1730 East Main Street, Duncan SC (30.3 acres, built 1980 / expanded 2011, 29-31-foot clear heights), leased to Eaton Corporation (NYSE: ETN) for its Electrical segment and occupied since 1984, in the institutional Greenville-Spartanburg market (Spartanburg West submarket, 2.6% vacancy, inland-port and I-85 access); the lease has 11.9 years remaining, 2.00% escalations, and five 5-year options. The portfolio carries an 11-plus-year WALT and was acquired for $86,400,000 (First Year property-level NOI of $5,447,009), capitalized with $50,200,000 equity and a $47,520,000 Old National Bank first mortgage (7-year term, SOFR+1.95% swapped to a fixed 5.495%, interest-only for 48 months then 30-year amortization, nonrecourse). Distributions are monthly, beginning at a 5.05% annualized cash-on-cash yield. Both tenants' credit is rated 'good' by Alliance Research; Eaton is an investment-grade public company and Carhartt is a privately held, century-old workwear manufacturer. Sponsored by Four Springs TEN31 Xchange (founded 2014); securities offered through Third Seven Capital, LLC and distributed by Four Springs Capital Markets. | T15: The portfolio's credit profile is a barbell of one transparent, investment-grade public credit and one strong but opaque private credit. Eaton Corporation (NYSE: ETN) is a globally diversified, century-old power-management company serving customers in over 170 countries, providing rated, publicly reported counterparty strength on the Duncan SC asset. Carhartt is a privately held, 135-year-old workwear manufacturer whose creditworthiness rests on a sponsor-commissioned Alliance Research review rated 'good' rather than a public agency rating, so the larger of the two assets by footprint carries materially less credit transparency, and both leases are with the operating tenants. | U15: Both assets are demonstrably mission-critical to their tenants, which raises renewal probability and switching costs well above a generic warehouse. The Hanson KY facility is Carhartt's primary national SKU distribution hub, into which the tenant has sunk over $70 million of fixed automation (robotics, racking, conveyor) plus more than $1 million of annual capital since 2015, embedding the operation in the building. Eaton has occupied Duncan SC continuously since 1984 and funded a roughly $5 million, 127,000 SF expansion, reflecting four decades of operational entrenchment. | V15: The lease economics are durable and long-dated: absolute-NNN structure with minimal landlord responsibility, an 11-plus-year weighted-average remaining term (11.8 and 11.9 years), contractual escalators, and unusually deep renewal optionality (eight 5-year options at Carhartt extending up to 40 years, five 5-year options at Eaton extending up to 25 years). The qualifier is that the 2.00% to 2.50% escalators sit at or below long-run inflation expectations, so real income growth is limited and the blended roughly 2.35% step-up modestly lags a higher-for-longer cost environment. | W15: Submarket quality is asymmetric across the two assets. The Eaton property sits in the Greenville-Spartanburg industrial market's largest submarket (Spartanburg West), a top-tier institutional logistics corridor with a record-low 2.6% vacancy rate, 5.1% availability, inland-port access at Greer, and I-85 frontage, supporting strong re-leasing economics. The Carhartt property, while logistically well-connected (I-69, CSX rail interchange, Ohio River ports, central to Carhartt's Kentucky manufacturing cluster), is in a rural, tertiary Western Kentucky location where alternative-tenant demand is thin if the incumbent ever vacates. | X15: The financing structure generates positive leverage and, atypically for the ledger, builds principal equity. The $47.52 million Old National Bank loan is swapped to a fixed 5.495% against the in-place yield at 48.63% loan-to-capitalization, and amortizes on a 30-year schedule beginning in year 5, so investors accrete modest equity through the back half of the hold rather than facing a full interest-only balloon. The offset is that the interest-rate swap introduces breakage and termination cost if the assets are sold or the loan is prepaid, and scheduled amortization lifts annual debt service from roughly $2.65 million to about $3.27 million in years 5 through 7, compressing coverage. | Y15: The offering pairs two mission-critical, absolute-NNN industrial distribution assets with an 11-plus-year WALT, contractual escalators, and minimal landlord obligation, diversified across two states, two tenants, and two end-industries (apparel logistics and electrical-equipment distribution). Eaton supplies a rated, investment-grade public credit, and both tenants exhibit deep physical and operational commitment to their facilities through substantial tenant-funded capital investment and multi-decade occupancy. The Eaton asset occupies one of the strongest institutional industrial submarkets in the Southeast, and the broader sector benefits from secular e-commerce and supply-chain demand for distribution space. The capital structure uses moderate, fixed-rate (swapped) leverage at 48.63% loan-to-capitalization that produces positive leverage over the in-place yield, supports a healthy 2.06x Year 1 coverage, amortizes to build equity from year 5, and underpins monthly distributions rising from 5.05% to 5.25% over the hold, with reserves funded at closing. | Z15: The portfolio is a two-asset, two-tenant pool, so any single vacancy is binary to cash flow, and Carhartt alone represents roughly 68% of square footage, concentrating exposure in the privately held, unrated tenant and its specialized, rural Hanson KY facility where re-leasing or repurposing demand is thin despite the asset's mission-criticality. The two leases expire within roughly one year of each other (approximately years 12 and 12), clustering rollover risk into a narrow window that a buyer at the projected year-7 exit will underwrite with only about five years of residual term remaining. The Eaton building is 1980-vintage with 29-31-foot clear heights, below modern bulk-distribution standards (36-foot-plus), limiting its functional competitiveness for alternative logistics users, and it mixes warehouse, manufacturing, and office space that is more tenant-specific. The financing carries a 7-year balloon and refinancing wall, swap breakage cost on early disposition, and an amortization step-up that raises debt service to roughly $3.27 million in years 5 through 7, causing distributable cash to dip (Year 5 distributable cash of about $2.57 million versus $2.94 million in Year 4) such that distributions are sustained partly through reserve management. Escalators of 2.00% to 2.50% may lag inflation, and the upfront load is high at 15.32% of equity (a 5.16% acquisition fee, 9.69% in offering and selling costs, and a 0.47% finance fee), before a disposition fee at exit, against modest reserves of $864,000. | AA15: FSX Industrial 34 is a moderately leveraged, core single-tenant industrial net-lease DST whose return is leverage-amplified contractual income: a fixed (swapped) 5.495% loan at 48.63% loan-to-capitalization against the in-place yield lifts cash-on-cash from 5.05% to 5.25% (roughly 5.11% average) over a 7-year hold, with a healthy 2.06x Year 1 coverage. It is closest in profile to the ledger's leveraged net-lease holdings (BREX Net Lease Industrial, ExchangeRight Portfolio 75) rather than the debt-free all-cash series, but is distinguished by being the only entry whose loan amortizes, accreting modest principal equity into the exit. The investment case rests on two mission-critical distribution assets with long WALT and a barbell of one investment-grade public credit (Eaton) and one strong-but-unrated private credit (Carhartt), set against a favorable industrial-demand backdrop and, for Eaton, a premier Spartanburg submarket. The dominant risk-adjusted considerations are the two-asset/two-tenant concentration skewed toward unrated Carhartt in a tertiary market, the older sub-modern Eaton box, two near-simultaneous lease expirations a few years beyond the exit, and a 7-year balloon whose amortization step-up compresses coverage and whose swap imposes breakage cost on early sale. Underwriting feasibility is high on in-place contractual income; the credible variance lies in the exit pricing, refinancing conditions at maturity, re-leasing of two specialized assets at rollover, and the form and timing of the optional Section 721 conversion, which investors may decline in favor of cash. The 15.32% load and below-inflation escalators are the principal economic drags on net return. | AB15: 0.0505 | AC15: 0.0505 | AD15: 0.0505 | AE15: 0.051 | AF15: 0.051 | AG15: 0.0515 | AH15: 0.0525 | AI15: Sold | AJ15: Sold | AK15: Sold | AL15: 0.0511 | AM15: Not disclosed | AN15: =IFERROR((AB15 * ((1 - VALUE(SUBSTITUTE(H15, " LTV", ""))) + 0.02)) + (PMT(0.0535/12, 25*12, -VALUE(SUBSTITUTE(H15, " LTV", ""))) * 12) + (0.02/10) + (0.03/10) + 0.02, "N/A") -> 0.08726668 | AO15: Old National Bank | AP15: 5.50% (Fixed via swap) | AQ15: 7 years | AR15: 4 years | AS15: 30 years | AT15: 2.06x | AU15: 380 Estill Baker Road, Hanson, KY | AV15: https://drive.google.com/file/d/1KLhX3b8jJT97sJ5o2TvUb0ahiiV-ugjX/view?usp=sharing | AX15: 100000 | AY15: =IFERROR(__xludf.DUMMYFUNCTION("IF(ISBLANK(AV15), """", IF(REGEXMATCH(AV15, ""/file/d/""), ""https://lh3.googleusercontent.com/d/"" & REGEXEXTRACT(AV15, ""/d/([a-zA-Z0-9_-]+)""), AV15))"),"https://lh3.googleusercontent.com/d/1KLhX3b8jJT97sJ5o2TvUb0ahiiV-ugjX") -> https://lh3.googleusercontent.com/d/1KLhX3b8jJT97sJ5o2TvUb0ahiiV-ugjX | AZ15: =IF(AM15="Not Disclosed", AB15 + ((14545 / 100000) * (0.32 / (1 - 0.32))), AM15) -> 0.11894706 | BA15: =if(AM15="Not Disclosed", "Est. Tax-Adjusted Yield⁹", "Tax-Adjusted Yield") -> Est. Tax-Adjusted Yield⁹ | BB15: =if(AW15="", "Offering Documents Available By Request", "Download Offering Documents") -> Offering Documents Available By Request | BC15: fsx-industrial-34-dst | BD15: sponsors/four-springs-capital | BE15: property-type/industrial | BF15: ="Learn More About "&B15 -> Learn More About Four Springs Capital | BG15: ="Learn More About "&L15&" Properties" -> Learn More About Industrial Properties | BH15: {=IFERROR(XLOOKUP($B15, 'Sponsor Connection'!$A:$A, 'Sponsor Connection'!$B:$B), )} -> 2012 | BI15: {=IFERROR(XLOOKUP($B15, 'Sponsor Connection'!$A:$A, 'Sponsor Connection'!$D:$D), )} -> Four Springs Capital reaches the 1031 market through Four Springs TEN31 Xchange, sponsoring net-lease DSTs concentrated in single-tenant industrial and medical properties under long-term leases to credit tenants such as Ford, Eaton and Carhartt. A deliberate focus on the $5 million-to-$200 million deal range keeps it below the institutional bid and above the retail scrum, a niche it has worked across more than 1,000 completed exchanges and over $1 billion in equity raised. As a subsidiary of Four Springs Capital Trust, it offers an UPREIT roll-up into the REIT, combining credit-tenant durability with a defined exit. | BJ15: {=IF($B15="", "", LET(aum, IFERROR(XLOOKUP($B15, 'Sponsor Connection'!$A:$A, 'Sponsor Connection'!$C:$C), ""), IF(OR(aum="", aum=0), "Not Reported", aum)))} -> 1300000000 | BK15: {=IF(ISBLANK($B15), "", LET(val, IFERROR(XLOOKUP($B15, 'Sponsor Connection'!$A:$A, 'Sponsor Connection'!$M:$M), ""), IF(OR(ISBLANK(val), val="", val=0), "Not Reported", val)))} -> 24 | BL15: {=IF(ISBLANK($B15), "", LET(val, IFERROR(XLOOKUP($B15, 'Sponsor Connection'!$A:$A, 'Sponsor Connection'!$N:$N), ""), IF(val="", "Not Reported", val)))} -> 0.070495833 | BM15: {=IF(ISBLANK($B15), "", LET(val, IFERROR(XLOOKUP($B15, 'Sponsor Connection'!$A:$A, 'Sponsor Connection'!$O:$O), ""), IF(val="", "Not Reported", val)))} -> 1.47125 | BN15: {=IF(ISBLANK($B15), "", LET(val, IFERROR(XLOOKUP($B15, 'Sponsor Connection'!$A:$A, 'Sponsor Connection'!$P:$P), ""), IF(val="", "Not Reported", val)))} -> 3.3358333 | BO15: {=IF(ISBLANK($B15), "", LET(val, IFERROR(XLOOKUP($B15, 'Sponsor Connection'!$A:$A, 'Sponsor Connection'!$Q:$Q), ""), IF(val="", "Not Reported", val)))} -> 1 | BP15: {=IFERROR(XLOOKUP($B15, 'Sponsor Connection'!$A:$A, 'Sponsor Connection'!$L:$L), )} -> https://img.logo.dev/ten31xchange.com?token=pk_FIVsDKgZTvCedVXXtt2rEg&size=200&retina=true | BQ15: =AL15 -> 0.0511 | BR15: =IFERROR(VLOOKUP(L15, Benchmarks!$A$2:$D$15, 2, FALSE), "Not Analyzed") -> 0 | BS15: =IFERROR(IF(OR(ISBLANK(BQ15), ISBLANK(BR15)), "", IF(ABS(BQ15-BR15)/BQ15 <= 0.1, "Meets Average", IF(BQ15 > BR15, "Above Average", "Below Average"))), "Not Analyzed") -> Above Average | BT15: =iferror((BW15-AB15)/AB15, 0) -> 0.03960396 | BU15: =IFERROR(VLOOKUP(L15, Benchmarks!$A$2:$D$15, 4, FALSE), "Not Analyzed") -> 0.14414694 | BV15: =IFERROR(IF(OR(ISBLANK(BT15), ISBLANK(BU15)), "", IF(ABS(BT15-BU15)/BT15 <= 0.1, "Meets Average", IF(BT15 > BU15, "Above Average", "Below Average"))), "Not Analyzed") -> Below Average | BW15: =max(AB15:AK15) -> 0.0525 | BX15: =IFERROR(VLOOKUP(L15, Benchmarks!$A$2:$D$15, 3, FALSE), "Not Analyzed") -> 0.05854 | BY15: =IFERROR(IF(OR(ISBLANK(BW15), ISBLANK(BX15)), "", IF(ABS(BW15-BX15)/BW15 <= 0.1, "Meets Average", IF(BW15 > BX15, "Above Average", "Below Average"))), "Not Analyzed") -> Below Average | BZ15: ="Investment: " & A15 & " | Sponsor: " & B15 & " | Structure: " & C15 & " | Status: " & D15 & " | LTV: " & H15 & " | Availability: " & K15 & " | Location: " & N15 & " | Strategy: " & P15 & " | 721 Exchange Exit: " & Q15 & " | Estimated Hold: " & R15 & " | Cap Rate Equivalent: " & AN15 & " | Minimum Investment: " & AX15 -> Investment: FSX Industrial 34, DST | Sponsor: Four Springs Capital | Structure: Delaware Statutory Trust (DST) | Status: Limited Availability | LTV: 48.63% LTV | Availability: 0.099601593625498 | Location: KY, SC | Strategy: Core | 721 Exchange Exit: Optional | Estimated Hold: 7 years | Cap Rate Equivalent: 0.0872666800665853 | Minimum Investment: 100000 | CA15: =A15&" ("&H15&")"&CHAR(10)&CHAR(10)&"FSX Industrial 34 is a leveraged DST holding a two-property, single-tenant absolute-NNN industrial portfolio (995,781 SF; 11-plus-year WALT) anchored by Carhartt's primary national distribution hub in Hanson, KY and an Eaton Corporation facility in Duncan"&", SC. The portfolio was acquired for $86.4M and financed with a $47.52M Old National Bank loan (SOFR+1.95% swapped to 5.495% fixed, interest-only for 48 months then 30-year amortization, 48.63% LTV). Carhartt has invested over $70M in automation at its mi"&"ssion-critical SKU facility, and both tenants carry strong credit, with monthly distributions beginning at a 5.05% cash-on-cash yield."&CHAR(10)&CHAR(10)&">> Download Offering Documents"&CHAR(10)&"https://www.baker1031.com/sponsors/four-springs-capital" -> FSX Industrial 34, DST (48.63% LTV) FSX Industrial 34 is a leveraged DST holding a two-property, single-tenant absolute-NNN industrial portfolio (995,781 SF; 11-plus-year WALT) anchored by Carhartt's primary national distribution hub in Hanson, KY and an Eaton Corporation facility in Duncan, SC. The portfolio was acquired for $86.4M and financed with a $47.52M Old National Bank loan (SOFR+1.95% swapped to 5.495% fixed, interest-only for 48 months then 30-year amortization, 48.63% LTV). Carhartt has invested over $70M in automation at its mission-critical SKU facility, and both tenants carry strong credit, with monthly distributions beginning at a 5.05% cash-on-cash yield. >> Download Offering Documents https://www.baker1031.com/sponsors/four-springs-capital
